Workbook
Name UPDATE: 'Data Sheet'!$E$1

Sheet Summary
C1: =Financial!A2
A2: INR Cr | B2: =Financial!I3 | C2: =Financial!J3 | D2: =Financial!K3 | E2: =Financial!L3 | F2: =CONCATENATE(TEXT(Financial!M3,"MMM-YY")," e") | G2: =CONCATENATE(TEXT(Financial!N3,"MMM-YY")," e") | H2: =CONCATENATE(TEXT(Financial!O3,"MMM-YY")," e") | I2: =CONCATENATE(TEXT(B2,"YY"),"-",TEXT(E2,"YY")," 3Y CAGR") | J2: =CONCATENATE(TEXT(E2,"YY"),"-",MID(TRIM(G2), 5, 2)," 2Y CAGR") | K2: =CONCATENATE(TEXT(E2,"YY"),"-",MID(TRIM(H2), 5, 2)," 3Y CAGR") | N2: Particulars | O2: FY22A | P2: FY23A | Q2: FY24E | R2: FY25E
A3: Revenue | B3: =Financial!I9 | C3: =Financial!J9 | D3: =Financial!K9 | E3: =Financial!L9 | F3: =Financial!M9 | G3: =Financial!N9 | H3: =Financial!O9 | I3: =(E3/B3)^(1/3)-1 | J3: =(G3/E3)^(1/2)-1 | K3: =(H3/E3)^(1/3)-1 | N3: Net Revenue | O3: =D3 | P3: =E3 | Q3: =F3 | R3: =G3
A4: EBITDA | B4: =Financial!I13 | C4: =Financial!J13 | D4: =Financial!K13 | E4: =Financial!L13 | F4: =Financial!M13 | G4: =Financial!N13 | H4: =Financial!O13 | I4: =(E4/B4)^(1/3)-1 | J4: =(G4/E4)^(1/2)-1 | K4: =(H4/E4)^(1/3)-1 | N4: % Chg y-o-y | O4: =(O3-C3)/C3 | P4: =(P3-O3)/O3 | Q4: =(Q3-P3)/P3 | R4: =(R3-Q3)/Q3
A5: EBITDA Margin | B5: =Financial!I27 | C5: =Financial!J27 | D5: =Financial!K27 | E5: =Financial!L27 | F5: =Financial!M27 | G5: =Financial!N27 | H5: =Financial!O27 | N5: EBITDA | O5: =D4 | P5: =E4 | Q5: =F4 | R5: =G4
A6: PAT | B6: =Financial!I20 | C6: =Financial!J20 | D6: =Financial!K20 | E6: =Financial!L20 | F6: =Financial!M20 | G6: =Financial!N20 | H6: =Financial!O20 | I6: =(E6/B6)^(1/3)-1 | J6: =(G6/E6)^(1/2)-1 | K6: =(H6/E6)^(1/3)-1 | N6: EBITDA Margin (%) | O6: =D5 | P6: =E5 | Q6: =F5 | R6: =G5
A7: PAT Margin | B7: =Financial!I31 | C7: =Financial!J31 | D7: =Financial!K31 | E7: =Financial!L31 | F7: =Financial!M31 | G7: =Financial!N31 | H7: =Financial!O31 | N7: Net Profit | O7: =D6 | P7: =E6 | Q7: =F6 | R7: =G6
A8: EPS | B8: =Financial!I22 | C8: =Financial!J22 | D8: =Financial!K22 | E8: =Financial!L22 | F8: =Financial!M22 | G8: =Financial!N22 | H8: =Financial!O22 | I8: =(E8/B8)^(1/3)-1 | J8: =(G8/E8)^(1/2)-1 | K8: =(H8/E8)^(1/3)-1 | N8: EPS (RS) | O8: =D8 | P8: =E8 | Q8: =F8 | R8: =G8
A9: BVPS | B9: =Financial!I86 | C9: =Financial!J86 | D9: =Financial!K86 | E9: =Financial!L86 | F9: =Financial!M86 | G9: =Financial!N86 | H9: =Financial!O86 | I9: =(E9/B9)^(1/3)-1 | J9: =(G9/E9)^(1/2)-1 | K9: =(H9/E9)^(1/3)-1 | N9: EPS % Chg | O9: =(O8-C8)/C8 | P9: =(P8-O8)/O8 | Q9: =(Q8-P8)/P8 | R9: =(R8-Q8)/Q8
A10: PE | B10: ='Data Sheet'!$B$8/Summary!B8 | C10: ='Data Sheet'!$B$8/Summary!C8 | D10: ='Data Sheet'!$B$8/Summary!D8 | E10: ='Data Sheet'!$B$8/Summary!E8 | F10: ='Data Sheet'!$B$8/Summary!F8 | G10: ='Data Sheet'!$B$8/Summary!G8 | H10: ='Data Sheet'!$B$8/Summary!H8 | N10: P/E (X) | O10: =D10 | P10: =E10 | Q10: =F10 | R10: =G10
A11: P/B | B11: ='Data Sheet'!$B$8/Summary!B9 | C11: ='Data Sheet'!$B$8/Summary!C9 | D11: ='Data Sheet'!$B$8/Summary!D9 | E11: ='Data Sheet'!$B$8/Summary!E9 | F11: ='Data Sheet'!$B$8/Summary!F9 | G11: ='Data Sheet'!$B$8/Summary!G9 | H11: ='Data Sheet'!$B$8/Summary!H9 | N11: EV/EBITDA(X) | O11: =D12 | P11: =E12 | Q11: =F12 | R11: =G12
A12: EV/EBITDA | B12: =Financial!I95 | C12: =Financial!J95 | D12: =Financial!K95 | E12: =Financial!L95 | F12: =Financial!M95 | G12: =Financial!N95 | H12: =Financial!O95 | N12: P/BV | O12: =D11 | P12: =E11 | Q12: =F11 | R12: =G11
A13: RoE | B13: =Financial!I79 | C13: =Financial!J79 | D13: =Financial!K79 | E13: =Financial!L79 | F13: =Financial!M79 | G13: =Financial!N79 | H13: =Financial!O79 | N13: BV/SHARE | O13: =D9 | P13: =E9 | Q13: =F9 | R13: =G9
A14: RoCE | B14: =Financial!I80 | C14: =Financial!J80 | D14: =Financial!K80 | E14: =Financial!L80 | F14: =Financial!M80 | G14: =Financial!N80 | H14: =Financial!O80 | N14: ROE | O14: =D13 | P14: =E13 | Q14: =F13 | R14: =G13
A15: RoIC | B15: =Financial!I81 | C15: =Financial!J81 | D15: =Financial!K81 | E15: =Financial!L81 | F15: =Financial!M81 | G15: =Financial!N81 | H15: =Financial!O81 | N15: ROCE | O15: =D14 | P15: =E14 | Q15: =F14 | R15: =G14
A16: WC Sales % | B16: =Financial!I71 | C16: =Financial!J71 | D16: =Financial!K71 | E16: =Financial!L71 | F16: =Financial!M71 | G16: =Financial!N71 | H16: =Financial!O71
A17: OCF / EBITDA | B17: =Financial!I73 | C17: =Financial!J73 | D17: =Financial!K73 | E17: =Financial!L73 | F17: =Financial!M73 | G17: =Financial!N73 | H17: =Financial!O73

Sheet Valuation
A1: =Financial!A2
A2: DCF Value | B2: 10 year | F2: 3 year | G2: 0 | H2: =G2+1 | I2: =H2+1 | J2: =I2+1 | K2: =J2+1 | L2: =K2+1 | M2: =L2+1 | N2: =M2+1 | O2: =N2+1 | ... Q2: =P2+1 | S2: 4th - 7th | T2: 8th -10th
A3: DCF (Rs Cr) | B3: Hi | C3: Low | D3: Avg | E3: Median | F3: Avg | G3: FY22 | H3: FY23 | I3: FY24 | J3: FY25 | K3: FY26 | L3: FY27 | M3: FY28 | N3: FY29 | O3: FY30 | P3: FY31 | Q3: FY32
A4: Revenues | B4: =MAX(Financial!D9:L9) | C4: =MIN(Financial!D9:L9) | D4: =AVERAGE(Financial!D9:L9) | E4: =MEDIAN(Financial!D9:L9) | F4: =AVERAGE(Financial!J9:L9) | G4: =Financial!M9 | H4: =Financial!N9 | I4: =Financial!O9 | J4: =+I4*(1+J5) | K4: =+J4*(1+K5) | L4: =+K4*(1+L5) | M4: =+L4*(1+M5) | N4: =+M4*(1+N5) | O4: =+N4*(1+O5) | P4: =+O4*(1+P5) | Q4: =+P4*(1+Q5) | S4: 0.66 | T4: 0.66
A5: % yoy growth | B5: =MAX(Financial!D35:L35) | C5: =MIN(Financial!D35:L35) | D5: =AVERAGE(Financial!D35:L35) | E5: =MEDIAN(Financial!D35:L35) | F5: =AVERAGE(Financial!J35:L35) | H5: =+H4/G4-1 | I5: =+I4/H4-1 | J5: =I5 | K5: =S5 | L5: =+K5 | M5: =+L5 | N5: =+M5 | O5: =T5 | P5: =+O5 | Q5: =+P5 | S5: =J5*S4 | T5: =S5*T4
A6: EBITDA | B6: =MAX(Financial!D13:L13) | C6: =MIN(Financial!D13:L13) | D6: =AVERAGE(Financial!D13:L13) | E6: =MEDIAN(Financial!D13:L13) | F6: =AVERAGE(Financial!J13:L13) | G6: =Financial!M13 | H6: =Financial!N13 | I6: =Financial!O13 | J6: =+J7*J4 | K6: =+K7*K4 | L6: =+L7*L4 | M6: =+M7*M4 | N6: =+N7*N4 | O6: =+O7*O4 | P6: =+P7*P4 | Q6: =+Q7*Q4 | S6: 0.9 | T6: 0.9
A7: EBITDA margin | B7: =MAX(Financial!C27:L27) | C7: =MIN(Financial!C27:L27) | D7: =AVERAGE(Financial!C27:L27) | E7: =MEDIAN(Financial!C27:L27) | F7: =AVERAGE(Financial!J27:L27) | G7: =+G6/G4 | H7: =+H6/H4 | I7: =+I6/I4 | J7: =I7 | K7: =S7 | L7: =+K7 | M7: =+L7 | N7: =+M7 | O7: =T7 | P7: =+O7 | Q7: =+P7 | S7: =J7*S6 | T7: =S7*T6
A8: CFO/EBITDA | B8: =MAX(Financial!C73:L73) | C8: =MIN(Financial!C73:L73) | D8: =AVERAGE(Financial!C73:L73) | E8: =MEDIAN(Financial!C73:L73) | F8: =AVERAGE(Financial!J73:L73) | G8: =Financial!M73 | H8: =Financial!N73 | I8: =Financial!O73 | J8: =I8 | K8: =+J8 | L8: =+K8 | M8: =+L8 | N8: =+M8 | O8: =+N8 | P8: =+O8 | Q8: =+P8
A9: CFO | B9: =MAX(Financial!C64:L64) | C9: =MIN(Financial!C64:L64) | D9: =AVERAGE(Financial!C64:L64) | E9: =MEDIAN(Financial!C64:L64) | F9: =AVERAGE(Financial!J64:L64) | G9: =+G8*G6 | H9: =+H8*H6 | I9: =+I8*I6 | J9: =+J8*J6 | K9: =+K8*K6 | L9: =+L8*L6 | M9: =+M8*M6 | N9: =+N8*N6 | ... Q9: =+Q8*Q6
A10: Fixed asset turns | B10: =MAX(Financial!C72:L72) | C10: =MIN(Financial!C72:L72) | D10: =AVERAGE(Financial!C72:L72) | E10: =MEDIAN(Financial!C72:L72) | F10: =AVERAGE(Financial!J72:L72) | G10: =Financial!M72 | H10: =Financial!N72 | I10: =Financial!O72 | J10: =I10 | K10: =+J10 | L10: =+K10 | M10: =+L10 | N10: =+M10 | O10: =+N10 | P10: =+O10 | Q10: =+P10
A11: Capex | B11: =MAX(Financial!C65:L65) | C11: =MIN(Financial!C65:L65) | D11: =AVERAGE(Financial!C65:L65) | E11: =MEDIAN(Financial!C65:L65) | F11: =AVERAGE(Financial!J65:L65) | G11: =-Financial!M65 | H11: =-Financial!N65 | I11: =-Financial!O65 | J11: =-+(J4-I4)/J10 | K11: =-+(K4-J4)/K10 | L11: =-+(L4-K4)/L10 | M11: =-+(M4-L4)/M10 | N11: =-+(N4-M4)/N10 | O11: =-+(O4-N4)/O10 | P11: =-+(P4-O4)/P10 | Q11: =-+(Q4-P4)/Q10
A12: FCFF | B12: =MAX(Financial!C66:L66) | C12: =MIN(Financial!C66:L66) | D12: =AVERAGE(Financial!C66:L66) | E12: =MEDIAN(Financial!C66:L66) | F12: =AVERAGE(Financial!J66:L66) | G12: =+G9+G11 | H12: =+H9+H11 | I12: =+I9+I11 | J12: =+J9+J11 | K12: =+K9+K11 | L12: =+L9+L11 | M12: =+M9+M11 | N12: =+N9+N11 | ... Q12: =+Q9+Q11
A13: Discounting factor | G13: =1/((1+$N$17)^G2) | H13: =1/((1+$N$17)^H2) | I13: =1/((1+$N$17)^I2) | J13: =1/((1+$N$17)^J2) | K13: =1/((1+$N$17)^K2) | L13: =1/((1+$N$17)^L2) | M13: =1/((1+$N$17)^M2) | N13: =1/((1+$N$17)^N2) | ... Q13: =1/((1+$N$17)^Q2)
A14: Terminal value | Q14: =+Q12*(1+$N$18)/($N$17-$N$18)
A16: WACC calculations | H16: Cost of Equity | K16: DCF Valuations | P16: Mcap | Q16: =Financial!P6 | S16: Debt | T16: =Financial!P42
B17: =B3 | C17: =C3 | D17: =D3 | E17: =E3 | F17: =F3 | H17: Cost of Equity | J17: =J18+J19*(J20-J18) | K17: Discount rate (WACC Below) | N17: =G22 | O17: % of value | P17: CMP | Q17: =Financial!P4
A18: Debt:Equity | B18: =MAX(Financial!D76:L76) | C18: =MIN(Financial!D76:L76) | D18: =AVERAGE(Financial!D76:L76) | E18: =MEDIAN(Financial!D76:L76) | F18: =AVERAGE(Financial!J76:L76) | G18: =MAX(Financial!L76)/(1+MAX(Financial!L76)) | H18: Risk-Free Return | J18: 0.07 | K18: Terminal growth rate | N18: 0.03
A19: Cost of debt | B19: =MAX(Financial!D29:L29) | C19: =MIN(Financial!D29:L29) | D19: =AVERAGE(Financial!D29:L29) | E19: =MEDIAN(Financial!D29:L29) | F19: =AVERAGE(Financial!J29:L29) | G19: =F19+J22 | H19: Beta | J19: 2 | K19: Discounted Terminal Value | N19: =Q14*Q13 | O19: =N19/$N$22 | P19: High range | T19: Low
A20: Tax rate | G20: =AVERAGE(Financial!J30:L30) | H20: Market Return | J20: 0.12 | K20: NPV of FCFF | N20: =SUMPRODUCT(G12:Q12,G13:Q13) | O20: =N20/$N$22 | P20: PE 3Y | Q20: =MAX(Financial!J91:L91,Financial!P91) | R20: =Financial!$O$22*Q20 | S20: =R20/Financial!$P$4-1 | T20: PE 5Y | U20: =MIN(Financial!I91:L91,Financial!P91) | V20: =Financial!$O$22*U20 | W20: =V20/Financial!$P$4-1
A21: Cost of equity | G21: =J17 | K21: Net (Debt)/Cash | N21: =-Financial!L42+Financial!L47 | O21: =N21/$N$22 | P21: EV/E 3Y | Q21: =MAX(Financial!J95:L95,Financial!P95) | R21: =((Q21*Financial!$O$13)-Financial!$O$42)/Financial!$O$5 | S21: =R21/Financial!$P$4-1 | T21: EV/E 5Y | U21: =MIN(Financial!I95:L95,Financial!P95) | V21: =((U21*Financial!$O$13)-Financial!$O$42)/Financial!$O$5 | W21: =V21/Financial!$P$4-1
A22: WACC | G22: =G21*(1-G18)+((G18*G19)*(1-G20)) | H22: Inc in Int Rate | J22: 0.005 | K22: NPV | N22: =SUM(N19:N21) | O22: =SUM(O19:O21) | P22: P/S 3Y | Q22: =MAX(Financial!J96:L96,Financial!P96) | R22: =((Q22*Financial!$O$9)-Financial!$O$42)/Financial!$O$5 | S22: =R22/Financial!$P$4-1 | T22: P/S 5Y | U22: =MIN(Financial!I96:L96,Financial!P96) | V22: =((U22*Financial!$O$9)-Financial!$O$42)/Financial!$O$5 | W22: =V22/Financial!$P$4-1
K23: O/s Equity Shares | N23: =Financial!O5
K24: DCF Price | N24: =+N22/N23 | P24: DCF | R24: =N24 | S24: =R24/Financial!$P$4-1

Sheet Financial
B1: Shree Ganeshaya Namah - TIKONA CAPITAL
A2: =CONCATENATE('Data Sheet'!$B$1," Mcap ",TEXT(ROUND($P$6,0),"0,000")," Cr CMP ",TEXT($P$4,"##,##0.0")) | U2: Assumptions
C3: ='Data Sheet'!B16 | D3: ='Data Sheet'!C16 | E3: ='Data Sheet'!D16 | F3: ='Data Sheet'!E16 | G3: ='Data Sheet'!F16 | H3: ='Data Sheet'!G16 | I3: ='Data Sheet'!H16 | J3: ='Data Sheet'!I16 | ... L3: ='Data Sheet'!K16 | M3: =L3+365 | N3: =M3+365 | O3: =N3+365 | P3: TTM | Q3: 3 Yr Proj CAGR | R3: 3 Yr CAGR | S3: 5 Yr CAGR | T3: 9Yr CAGR | U3: =M3 | V3: =N3 | W3: =O3
A4: Mkt Price | B4: INR | C4: ='Data Sheet'!B90 | D4: ='Data Sheet'!C90 | E4: ='Data Sheet'!D90 | F4: ='Data Sheet'!E90 | G4: ='Data Sheet'!F90 | H4: ='Data Sheet'!G90 | I4: ='Data Sheet'!H90 | J4: ='Data Sheet'!I90 | ... L4: ='Data Sheet'!K90 | M4: =P4 | N4: =P4 | O4: =P4 | P4: ='Data Sheet'!B8 | R4: =((P4/I4)^(1/R8))-1 | S4: =((P4/G4)^(1/S8))-1 | T4: =IF(C4>0,((P4/C4)^(1/T8))-1,"-")
A5: O/s Equity Shares | B5: Cr | C5: ='Data Sheet'!B93 | D5: ='Data Sheet'!C93 | E5: ='Data Sheet'!D93 | F5: ='Data Sheet'!E93 | G5: ='Data Sheet'!F93 | H5: ='Data Sheet'!G93 | I5: ='Data Sheet'!H93 | J5: ='Data Sheet'!I93 | ... L5: ='Data Sheet'!K93 | M5: =L5 | N5: =M5 | O5: =N5 | P5: =O5 | R5: =((L5/I5)^(1/3))-1 | S5: =((L5/G5)^(1/5))-1 | T5: =IF(C5>0,((L5/C5)^(1/9))-1,"-")
A6: Mcap | B6: Cr | C6: =C4*C5 | D6: =D4*D5 | E6: =E4*E5 | F6: =F4*F5 | G6: =G4*G5 | H6: =H4*H5 | I6: =I4*I5 | J6: =J4*J5 | ... L6: =L4*L5 | M6: =P6 | N6: =P6 | O6: =P6 | P6: =P4*P5 | R6: =((L6/I6)^(1/3))-1 | S6: =((L6/G6)^(1/5))-1 | T6: =IF(C6>0,((L6/C6)^(1/9))-1,"-")
A7: Enterprise Value | B7: Cr | C7: =C6+C42 | D7: =D6+D42 | E7: =E6+E42 | F7: =F6+F42 | G7: =G6+G42 | H7: =H6+H42 | I7: =I6+I42 | J7: =J6+J42 | ... P7: =P6+P42 | R7: =((L7/I7)^(1/3))-1 | S7: =((L7/G7)^(1/5))-1 | T7: =IF(C7>0,((L7/C7)^(1/9))-1,"-")
R8: =(TODAY()-I3)/365 | S8: =(TODAY()-G3)/365 | T8: =(TODAY()-C3)/365
A9: Revenue | B9: Cr | C9: ='Data Sheet'!B17 | D9: ='Data Sheet'!C17 | E9: ='Data Sheet'!D17 | F9: ='Data Sheet'!E17 | G9: ='Data Sheet'!F17 | H9: ='Data Sheet'!G17 | I9: ='Data Sheet'!H17 | J9: ='Data Sheet'!I17 | ... L9: ='Data Sheet'!K17 | M9: =L9*(1+$U9) | N9: =M9*(1+$V9) | O9: =N9*(1+$W9) | P9: =SUM(I99:L99) | Q9: =((O9/L9)^(1/3))-1 | R9: =((L9/I9)^(1/3))-1 | S9: =((L9/G9)^(1/5))-1 | T9: =IF(C9>0,((L9/C9)^(1/9))-1,"-") | U9: =R9 | V9: =U9 | W9: =V9
A10: Growth (YoY) | D10: =D9/C9-1 | E10: =E9/D9-1 | F10: =F9/E9-1 | G10: =G9/F9-1 | H10: =H9/G9-1 | I10: =I9/H9-1 | J10: =J9/I9-1 | K10: =K9/J9-1 | ... O10: =O9/N9-1
A11: Gross Profits | B11: Cr | C11: =C9-SUM('Data Sheet'!B18,-1*'Data Sheet'!B19) | D11: =D9-SUM('Data Sheet'!C18,-1*'Data Sheet'!C19) | E11: =E9-SUM('Data Sheet'!D18,-1*'Data Sheet'!D19) | F11: =F9-SUM('Data Sheet'!E18,-1*'Data Sheet'!E19) | G11: =G9-SUM('Data Sheet'!F18,-1*'Data Sheet'!F19) | H11: =H9-SUM('Data Sheet'!G18,-1*'Data Sheet'!G19) | I11: =I9-SUM('Data Sheet'!H18,-1*'Data Sheet'!H19) | J11: =J9-SUM('Data Sheet'!I18,-1*'Data Sheet'!I19) | ... L11: =L9-SUM('Data Sheet'!K18,-1*'Data Sheet'!K19)
A12: Growth (YoY) | D12: =D11/C11-1 | E12: =E11/D11-1 | F12: =F11/E11-1 | H12: =H11/G11-1 | I12: =I11/H11-1 | J12: =J11/I11-1 | K12: =K11/J11-1 | L12: =L11/K11-1
A13: EBITDA | B13: Cr | C13: =C9-SUM('Data Sheet'!B18,'Data Sheet'!B20:B24,-1*'Data Sheet'!B19) | D13: =D9-SUM('Data Sheet'!C18,'Data Sheet'!C20:C24,-1*'Data Sheet'!C19) | E13: =E9-SUM('Data Sheet'!D18,'Data Sheet'!D20:D24,-1*'Data Sheet'!D19) | F13: =F9-SUM('Data Sheet'!E18,'Data Sheet'!E20:E24,-1*'Data Sheet'!E19) | G13: =G9-SUM('Data Sheet'!F18,'Data Sheet'!F20:F24,-1*'Data Sheet'!F19) | H13: =H9-SUM('Data Sheet'!G18,'Data Sheet'!G20:G24,-1*'Data Sheet'!G19) | I13: =I9-SUM('Data Sheet'!H18,'Data Sheet'!H20:H24,-1*'Data Sheet'!H19) | J13: =J9-SUM('Data Sheet'!I18,'Data Sheet'!I20:I24,-1*'Data Sheet'!I19) | ... L13: =L9-SUM('Data Sheet'!K18,'Data Sheet'!K20:K24,-1*'Data Sheet'!K19) | M13: =M9*$U27 | N13: =N9*$V27 | O13: =O9*$W27 | P13: =SUM(I101:L101) | Q13: =((O13/L13)^(1/3))-1 | R13: =((L13/I13)^(1/3))-1 | S13: =((L13/G13)^(1/5))-1 | T13: =IF(C13>0,((L13/C13)^(1/9))-1,"-")
A14: Growth (YoY) | D14: =D13/C13-1 | E14: =E13/D13-1 | F14: =F13/E13-1 | G14: =G13/F13-1 | H14: =H13/G13-1 | I14: =I13/H13-1 | J14: =J13/I13-1 | K14: =K13/J13-1 | ... O14: =O13/N13-1
A15: Other Income | B15: Cr | C15: ='Data Sheet'!B25 | D15: ='Data Sheet'!C25 | E15: ='Data Sheet'!D25 | F15: ='Data Sheet'!E25 | G15: ='Data Sheet'!F25 | H15: ='Data Sheet'!G25 | I15: ='Data Sheet'!H25 | J15: ='Data Sheet'!I25 | ... L15: ='Data Sheet'!K25 | M15: =AVERAGE(J15:L15) | N15: =AVERAGE(K15:M15) | O15: =AVERAGE(L15:N15) | P15: =SUM(I114:L114)
A16: Depreciation | B16: Cr | C16: ='Data Sheet'!B26 | D16: ='Data Sheet'!C26 | E16: ='Data Sheet'!D26 | F16: ='Data Sheet'!E26 | G16: ='Data Sheet'!F26 | H16: ='Data Sheet'!G26 | I16: ='Data Sheet'!H26 | J16: ='Data Sheet'!I26 | ... L16: ='Data Sheet'!K26 | M16: =L16*(1+$U16) | N16: =M16*(1+$V16) | O16: =N16*(1+$W16) | P16: =SUM(I115:L115) | U16: =R45 | V16: =U16 | W16: =V16
A17: Interest | B17: Cr | C17: ='Data Sheet'!B27 | D17: ='Data Sheet'!C27 | E17: ='Data Sheet'!D27 | F17: ='Data Sheet'!E27 | G17: ='Data Sheet'!F27 | H17: ='Data Sheet'!G27 | I17: ='Data Sheet'!H27 | J17: ='Data Sheet'!I27 | ... L17: ='Data Sheet'!K27 | M17: =L17*(1+$U17) | N17: =M17*(1+$V17) | O17: =N17*(1+$W17) | P17: =SUM(I116:L116) | U17: 0.1 | V17: =U17 | W17: =V17
A18: PBT | B18: Cr | C18: ='Data Sheet'!B28 | D18: ='Data Sheet'!C28 | E18: ='Data Sheet'!D28 | F18: ='Data Sheet'!E28 | G18: ='Data Sheet'!F28 | H18: ='Data Sheet'!G28 | I18: ='Data Sheet'!H28 | J18: ='Data Sheet'!I28 | ... L18: ='Data Sheet'!K28 | M18: =M13+M15-M16-M17 | N18: =N13+N15-N16-N17 | O18: =O13+O15-O16-O17 | P18: =P13+P15-P16-P17
A19: Tax | B19: Cr | C19: ='Data Sheet'!B29 | D19: ='Data Sheet'!C29 | E19: ='Data Sheet'!D29 | F19: ='Data Sheet'!E29 | G19: ='Data Sheet'!F29 | H19: ='Data Sheet'!G29 | I19: ='Data Sheet'!H29 | J19: ='Data Sheet'!I29 | ... L19: ='Data Sheet'!K29 | M19: =M18*$U30 | N19: =N18*$V30 | O19: =O18*$W30 | P19: =P18-P20
A20: PAT | B20: Cr | C20: ='Data Sheet'!B30 | D20: ='Data Sheet'!C30 | E20: ='Data Sheet'!D30 | F20: ='Data Sheet'!E30 | G20: ='Data Sheet'!F30 | H20: ='Data Sheet'!G30 | I20: ='Data Sheet'!H30 | J20: ='Data Sheet'!I30 | ... L20: ='Data Sheet'!K30 | M20: =M18-M19 | N20: =N18-N19 | O20: =O18-O19 | P20: =SUM(I105:L105) | Q20: =((O20/L20)^(1/3))-1 | R20: =((L20/I20)^(1/3))-1 | S20: =((L20/G20)^(1/5))-1 | T20: =IF(C20>0,((L20/C20)^(1/9))-1,"-")
A21: Growth (YoY) | D21: =D20/C20-1 | E21: =E20/D20-1 | F21: =F20/E20-1 | G21: =G20/F20-1 | H21: =H20/G20-1 | I21: =I20/H20-1 | J21: =J20/I20-1 | K21: =K20/J20-1 | ... O21: =O20/N20-1
A22: EPS | B22: INR | C22: =C20/C5 | D22: =D20/D5 | E22: =E20/E5 | F22: =F20/F5 | G22: =G20/G5 | H22: =H20/H5 | I22: =I20/I5 | J22: =J20/J5 | ... P22: =P20/P5 | R22: =((L22/I22)^(1/3))-1 | S22: =((L22/G22)^(1/5))-1 | T22: =IF(C22>0,((L22/C22)^(1/9))-1,"-")
A23: DPS | B23: INR | C23: ='Data Sheet'!B31/C5 | D23: ='Data Sheet'!C31/D5 | E23: ='Data Sheet'!D31/E5 | F23: ='Data Sheet'!E31/F5 | G23: ='Data Sheet'!F31/G5 | H23: ='Data Sheet'!G31/H5 | I23: ='Data Sheet'!H31/I5 | J23: ='Data Sheet'!I31/J5 | ... L23: ='Data Sheet'!K31/L5 | M23: =M22*$U32 | N23: =N22*$V32 | O23: =O22*$W32 | R23: =((L23/I23)^(1/3))-1 | S23: =((L23/G23)^(1/5))-1 | T23: =IF(C23>0,((L23/C23)^(1/9))-1,"-")
A25: RATIOS
A26: GPM | B26: % | C26: =C11/C$9 | D26: =D11/D$9 | E26: =E11/E$9 | F26: =F11/F$9 | G26: =G11/G$9 | H26: =H11/H$9 | I26: =I11/I$9 | J26: =J11/J$9 | ... L26: =L11/L$9 | R26: =AVERAGE(J26:L26) | S26: =AVERAGE(H26:L26) | T26: =AVERAGE(C26:L26)
A27: EBITDAM | B27: % | C27: =C13/C$9 | D27: =D13/D$9 | E27: =E13/E$9 | F27: =F13/F$9 | G27: =G13/G$9 | H27: =H13/H$9 | I27: =I13/I$9 | J27: =J13/J$9 | ... P27: =P13/P$9 | R27: =AVERAGE(J27:L27) | S27: =AVERAGE(H27:L27) | T27: =AVERAGE(C27:L27) | U27: =R27 | V27: =U27 | W27: =V27
A28: Depn / Net Assets | B28: % | C28: =C16/(C45+C46) | D28: =D16/(D45+D46) | E28: =E16/(E45+E46) | F28: =F16/(F45+F46) | G28: =G16/(G45+G46) | H28: =H16/(H45+H46) | I28: =I16/(I45+I46) | J28: =J16/(J45+J46) | ... O28: =O16/(O45+O46) | Q28: =AVERAGE(M28:O28) | R28: =AVERAGE(J28:L28) | S28: =AVERAGE(H28:L28) | T28: =AVERAGE(C28:L28)
A29: Interest /Total Debt | B29: % | C29: =C17/C42 | D29: =D17/D42 | E29: =E17/E42 | F29: =F17/F42 | G29: =G17/G42 | H29: =H17/H42 | I29: =I17/I42 | J29: =J17/J42 | ... O29: =O17/O42 | Q29: =AVERAGE(M29:O29) | R29: =AVERAGE(J29:L29) | S29: =AVERAGE(H29:L29) | T29: =AVERAGE(C29:L29)
A30: Tax Rate | B30: % | C30: =C19/C18 | D30: =D19/D18 | E30: =E19/E18 | F30: =F19/F18 | G30: =G19/G18 | H30: =H19/H18 | I30: =I19/I18 | J30: =J19/J18 | ... P30: =P19/P18 | Q30: =AVERAGE(M30:O30) | R30: =AVERAGE(J30:L30) | S30: =AVERAGE(H30:L30) | T30: =AVERAGE(C30:L30) | U30: =R30 | V30: =U30 | W30: =V30
A31: PAT Margins | B31: % | C31: =C20/C$9 | D31: =D20/D$9 | E31: =E20/E$9 | F31: =F20/F$9 | G31: =G20/G$9 | H31: =H20/H$9 | I31: =I20/I$9 | J31: =J20/J$9 | ... P31: =P20/P$9 | R31: =AVERAGE(J31:L31) | S31: =AVERAGE(H31:L31) | T31: =AVERAGE(C31:L31)
A32: Payout Ratio | B32: % | C32: =C23/C22 | D32: =D23/D22 | E32: =E23/E22 | F32: =F23/F22 | G32: =G23/G22 | H32: =H23/H22 | I32: =I23/I22 | J32: =J23/J22 | ... O32: =O23/O22 | R32: =AVERAGE(J32:L32) | S32: =AVERAGE(H32:L32) | T32: =AVERAGE(C32:L32) | U32: =R32 | V32: =U32 | W32: =V32
A34: Growth - YoY
A35: =A9 | B35: % | D35: =D9/C9-1 | E35: =E9/D9-1 | F35: =F9/E9-1 | G35: =G9/F9-1 | H35: =H9/G9-1 | I35: =I9/H9-1 | J35: =J9/I9-1 | K35: =K9/J9-1 | ... O35: =O9/N9-1 | P35: =P9/L9-1
A36: GP growth | B36: % | D36: =D11/C11-1 | E36: =E11/D11-1 | F36: =F11/E11-1 | G36: =G11/F11-1 | H36: =H11/G11-1 | I36: =I11/H11-1 | J36: =J11/I11-1 | K36: =K11/J11-1 | L36: =L11/K11-1
A37: EBITDA | B37: % | D37: =D13/C13-1 | E37: =E13/D13-1 | F37: =F13/E13-1 | G37: =G13/F13-1 | H37: =H13/G13-1 | I37: =I13/H13-1 | J37: =J13/I13-1 | K37: =K13/J13-1 | ... O37: =O13/N13-1 | P37: =P13/L13-1
A38: PAT | B38: % | D38: =D20/C20-1 | E38: =E20/D20-1 | F38: =F20/E20-1 | G38: =G20/F20-1 | H38: =H20/G20-1 | I38: =I20/H20-1 | J38: =J20/I20-1 | K38: =K20/J20-1 | ... O38: =O20/N20-1 | P38: =P20/L20-1
A40: BALANCE SHEET
A41: Networth | B41: Cr | C41: ='Data Sheet'!B57+'Data Sheet'!B58 | D41: ='Data Sheet'!C57+'Data Sheet'!C58 | E41: ='Data Sheet'!D57+'Data Sheet'!D58 | F41: ='Data Sheet'!E57+'Data Sheet'!E58 | G41: ='Data Sheet'!F57+'Data Sheet'!F58 | H41: ='Data Sheet'!G57+'Data Sheet'!G58 | I41: ='Data Sheet'!H57+'Data Sheet'!H58 | J41: ='Data Sheet'!I57+'Data Sheet'!I58 | ... L41: ='Data Sheet'!K57+'Data Sheet'!K58 | M41: =L41+M20-M5*M23 | N41: =M41+N20-N5*N23 | O41: =N41+O20-O5*O23 | Q41: =((O41/L41)^(1/3))-1 | R41: =((L41/I41)^(1/3))-1 | S41: =((L41/G41)^(1/5))-1 | T41: =IF(C41>0,((L41/C41)^(1/9))-1,"-")
A42: Total Debt | B42: Cr | C42: ='Data Sheet'!B59 | D42: ='Data Sheet'!C59 | E42: ='Data Sheet'!D59 | F42: ='Data Sheet'!E59 | G42: ='Data Sheet'!F59 | H42: ='Data Sheet'!G59 | I42: ='Data Sheet'!H59 | J42: ='Data Sheet'!I59 | ... L42: ='Data Sheet'!K59 | M42: =(M45+M46+M47+M50)-M41 | N42: =(N45+N46+N47+N50)-N41 | O42: =(O45+O46+O47+O50)-O41 | P42: =L42 | Q42: =((O42/L42)^(1/3))-1 | R42: =((L42/I42)^(1/3))-1 | S42: =((L42/G42)^(1/5))-1 | T42: =IF(C42>0,((L42/C42)^(1/9))-1,"-")
A43: CAPITAL EMPLOYED | B43: Cr | C43: =SUM(C41:C42) | D43: =SUM(D41:D42) | E43: =SUM(E41:E42) | F43: =SUM(F41:F42) | G43: =SUM(G41:G42) | H43: =SUM(H41:H42) | I43: =SUM(I41:I42) | J43: =SUM(J41:J42) | ... O43: =SUM(O41:O42) | Q43: =((O43/L43)^(1/3))-1 | R43: =((L43/I43)^(1/3))-1 | S43: =((L43/G43)^(1/5))-1 | T43: =IF(C43>0,((L43/C43)^(1/9))-1,"-")
A44: DEPLOYED AS
A45: Net Block | B45: Cr | C45: ='Data Sheet'!B62 | D45: ='Data Sheet'!C62 | E45: ='Data Sheet'!D62 | F45: ='Data Sheet'!E62 | G45: ='Data Sheet'!F62 | H45: ='Data Sheet'!G62 | I45: ='Data Sheet'!H62 | J45: ='Data Sheet'!I62 | ... L45: ='Data Sheet'!K62 | M45: =L45+M65-M16 | N45: =M45+N65-N16 | O45: =N45+O65-O16 | Q45: =((O45/L45)^(1/3))-1 | R45: =((L45/I45)^(1/3))-1 | S45: =((L45/G45)^(1/5))-1 | T45: =IF(C45>0,((L45/C45)^(1/9))-1,"-")
A46: Capital WIP | B46: Cr | C46: ='Data Sheet'!B63 | D46: ='Data Sheet'!C63 | E46: ='Data Sheet'!D63 | F46: ='Data Sheet'!E63 | G46: ='Data Sheet'!F63 | H46: ='Data Sheet'!G63 | I46: ='Data Sheet'!H63 | J46: ='Data Sheet'!I63 | ... L46: ='Data Sheet'!K63 | M46: =L46 | N46: =M46 | O46: =N46 | Q46: =((O46/L46)^(1/3))-1 | R46: =((L46/I46)^(1/3))-1 | S46: =((L46/G46)^(1/5))-1 | T46: =IF(C46>0,((L46/C46)^(1/9))-1,"-")
A47: Investments | B47: Cr | C47: ='Data Sheet'!B64 | D47: ='Data Sheet'!C64 | E47: ='Data Sheet'!D64 | F47: ='Data Sheet'!E64 | G47: ='Data Sheet'!F64 | H47: ='Data Sheet'!G64 | I47: ='Data Sheet'!H64 | J47: ='Data Sheet'!I64 | ... L47: ='Data Sheet'!K64 | M47: =L47 | N47: =M47 | O47: =N47
A48: Other Assets | B48: Cr | C48: ='Data Sheet'!B65 | D48: ='Data Sheet'!C65 | E48: ='Data Sheet'!D65 | F48: ='Data Sheet'!E65 | G48: ='Data Sheet'!F65 | H48: ='Data Sheet'!G65 | I48: ='Data Sheet'!H65 | J48: ='Data Sheet'!I65 | ... L48: ='Data Sheet'!K65 | R48: =((L48/I48)^(1/3))-1 | S48: =((L48/G48)^(1/5))-1 | T48: =IF(C48>0,((L48/C48)^(1/9))-1,"-")
A49: Other Liabilities | B49: Cr | C49: ='Data Sheet'!B60 | D49: ='Data Sheet'!C60 | E49: ='Data Sheet'!D60 | F49: ='Data Sheet'!E60 | G49: ='Data Sheet'!F60 | H49: ='Data Sheet'!G60 | I49: ='Data Sheet'!H60 | J49: ='Data Sheet'!I60 | ... L49: ='Data Sheet'!K60 | R49: =((L49/I49)^(1/3))-1 | S49: =((L49/G49)^(1/5))-1 | T49: =IF(C49>0,((L49/C49)^(1/9))-1,"-")
A50: Working Capital | B50: Cr | C50: =C48-C49 | D50: =D48-D49 | E50: =E48-E49 | F50: =F48-F49 | G50: =G48-G49 | H50: =H48-H49 | I50: =I48-I49 | J50: =J48-J49 | ... L50: =L48-L49 | M50: =M9*$U71 | N50: =N9*$V71 | O50: =O9*$W71 | R50: =((L50/I50)^(1/3))-1 | S50: =((L50/G50)^(1/5))-1 | T50: =IF(C50>0,((L50/C50)^(1/9))-1,"-")
A51: CHECK | C51: =C45+C46+C47+C50-C43 | D51: =D45+D46+D47+D50-D43 | E51: =E45+E46+E47+E50-E43 | F51: =F45+F46+F47+F50-F43 | G51: =G45+G46+G47+G50-G43 | H51: =H45+H46+H47+H50-H43 | I51: =I45+I46+I47+I50-I43 | J51: =J45+J46+J47+J50-J43 | ... O51: =O45+O46+O47+O50-O43
A53: ='Data Sheet'!A67 | B53: Cr | C53: ='Data Sheet'!B67 | D53: ='Data Sheet'!C67 | E53: ='Data Sheet'!D67 | F53: ='Data Sheet'!E67 | G53: ='Data Sheet'!F67 | H53: ='Data Sheet'!G67 | I53: ='Data Sheet'!H67 | J53: ='Data Sheet'!I67 | ... L53: ='Data Sheet'!K67 | R53: =((L53/I53)^(1/3))-1 | S53: =((L53/G53)^(1/5))-1 | T53: =IF(C53>0,((L53/C53)^(1/9))-1,"-")
A54: ='Data Sheet'!A68 | B54: Cr | C54: ='Data Sheet'!B68 | D54: ='Data Sheet'!C68 | E54: ='Data Sheet'!D68 | F54: ='Data Sheet'!E68 | G54: ='Data Sheet'!F68 | H54: ='Data Sheet'!G68 | I54: ='Data Sheet'!H68 | J54: ='Data Sheet'!I68 | ... L54: ='Data Sheet'!K68 | R54: =((L54/I54)^(1/3))-1 | S54: =((L54/G54)^(1/5))-1 | T54: =IF(C54>0,((L54/C54)^(1/9))-1,"-")
A55: ='Data Sheet'!A69 | B55: Cr | C55: ='Data Sheet'!B69 | D55: ='Data Sheet'!C69 | E55: ='Data Sheet'!D69 | F55: ='Data Sheet'!E69 | G55: ='Data Sheet'!F69 | H55: ='Data Sheet'!G69 | I55: ='Data Sheet'!H69 | J55: ='Data Sheet'!I69 | ... L55: ='Data Sheet'!K69 | R55: =((L55/I55)^(1/3))-1 | S55: =((L55/G55)^(1/5))-1 | T55: =IF(C55>0,((L55/C55)^(1/9))-1,"-")
A57: Growth - YoY
A58: Networth | B58: % | D58: =D41/C41-1 | E58: =E41/D41-1 | F58: =F41/E41-1 | G58: =G41/F41-1 | H58: =H41/G41-1 | I58: =I41/H41-1 | J58: =J41/I41-1 | K58: =K41/J41-1 | L58: =L41/K41-1
A59: Total Debt | B59: % | D59: =D42/C42-1 | E59: =E42/D42-1 | F59: =F42/E42-1 | G59: =G42/F42-1 | H59: =H42/G42-1 | I59: =I42/H42-1 | J59: =J42/I42-1 | K59: =K42/J42-1 | L59: =L42/K42-1
A60: Capital Employed | B60: % | D60: =D43/C43-1 | E60: =E43/D43-1 | F60: =F43/E43-1 | G60: =G43/F43-1 | H60: =H43/G43-1 | I60: =I43/H43-1 | J60: =J43/I43-1 | K60: =K43/J43-1 | L60: =L43/K43-1
A61: Working Capital | B61: % | D61: =D50/C50-1 | E61: =E50/D50-1 | F61: =F50/E50-1 | G61: =G50/F50-1 | H61: =H50/G50-1 | I61: =I50/H50-1 | J61: =J50/I50-1 | K61: =K50/J50-1 | L61: =L50/K50-1
A63: CASH FLOWS
A64: CFO | B64: Cr | C64: ='Data Sheet'!B82 | D64: ='Data Sheet'!C82 | E64: ='Data Sheet'!D82 | F64: ='Data Sheet'!E82 | G64: ='Data Sheet'!F82 | H64: ='Data Sheet'!G82 | I64: ='Data Sheet'!H82 | J64: ='Data Sheet'!I82 | ... L64: ='Data Sheet'!K82 | M64: =M13-M19-M50+L50 | N64: =N13-N19-N50+M50 | O64: =O13-O19-O50+N50 | Q64: =((O64/L64)^(1/3))-1 | R64: =((L64/I64)^(1/3))-1 | S64: =((L64/G64)^(1/5))-1 | T64: =IF(C64>0,((L64/C64)^(1/9))-1,"-")
A65: Capital Exp | B65: Cr | C65: =C16 | D65: =(D45+D46+D16)-(C45+C46) | E65: =(E45+E46+E16)-(D45+D46) | F65: =(F45+F46+F16)-(E45+E46) | G65: =(G45+G46+G16)-(F45+F46) | H65: =(H45+H46+H16)-(G45+G46) | I65: =(I45+I46+I16)-(H45+H46) | J65: =(J45+J46+J16)-(I45+I46) | K65: =(K45+K46+K16)-(J45+J46) | L65: =(L45+L46+L16)-(K45+K46) | M65: =AVERAGE(J65:L65) | N65: =AVERAGE(K65:M65) | O65: =AVERAGE(L65:N65) | Q65: =((O65/L65)^(1/3))-1 | R65: =((L65/I65)^(1/3))-1 | S65: =((L65/G65)^(1/5))-1 | T65: =IF(C65>0,((L65/C65)^(1/9))-1,"-")
A66: FCF to Equity | B66: Cr | C66: =C64-C65 | D66: =D64-D65 | E66: =E64-E65 | F66: =F64-F65 | G66: =G64-G65 | H66: =H64-H65 | I66: =I64-I65 | J66: =J64-J65 | ... O66: =O64-O65 | Q66: =((O66/L66)^(1/3))-1 | R66: =((L66/I66)^(1/3))-1 | S66: =((L66/G66)^(1/5))-1 | T66: =IF(C66>0,((L66/C66)^(1/9))-1,"-")
A68: Receivable Days | B68: No | C68: =C53/C$9*365 | D68: =D53/D$9*365 | E68: =E53/E$9*365 | F68: =F53/F$9*365 | G68: =G53/G$9*365 | H68: =H53/H$9*365 | I68: =I53/I$9*365 | J68: =J53/J$9*365 | ... L68: =L53/L$9*365 | R68: =AVERAGE(J68:L68) | S68: =AVERAGE(H68:L68) | T68: =AVERAGE(C68:L68)
A69: Inventory Days | B69: No | C69: =C54/C$9*365 | D69: =D54/D$9*365 | E69: =E54/E$9*365 | F69: =F54/F$9*365 | G69: =G54/G$9*365 | H69: =H54/H$9*365 | I69: =I54/I$9*365 | J69: =J54/J$9*365 | ... L69: =L54/L$9*365 | R69: =AVERAGE(J69:L69) | S69: =AVERAGE(H69:L69) | T69: =AVERAGE(C69:L69)
A70: Working Cap Days | B70: No | C70: =C50/C$9*365 | D70: =D50/D$9*365 | E70: =E50/E$9*365 | F70: =F50/F$9*365 | G70: =G50/G$9*365 | H70: =H50/H$9*365 | I70: =I50/I$9*365 | J70: =J50/J$9*365 | ... L70: =L50/L$9*365 | R70: =AVERAGE(J70:L70) | S70: =AVERAGE(H70:L70) | T70: =AVERAGE(C70:L70)
A71: Working Cap/Sales | B71: % | C71: =C50/C9 | D71: =D50/D9 | E71: =E50/E9 | F71: =F50/F9 | G71: =G50/G9 | H71: =H50/H9 | I71: =I50/I9 | J71: =J50/J9 | ... O71: =O50/O9 | R71: =AVERAGE(J71:L71) | S71: =AVERAGE(H71:L71) | T71: =AVERAGE(C71:L71) | U71: =R71 | V71: =U71 | W71: =V71
A72: Asset Turnover | B72: x | C72: =C9/SUM(C45:C46) | D72: =D9/SUM(D45:D46) | E72: =E9/SUM(E45:E46) | F72: =F9/SUM(F45:F46) | G72: =G9/SUM(G45:G46) | H72: =H9/SUM(H45:H46) | I72: =I9/SUM(I45:I46) | J72: =J9/SUM(J45:J46) | ... O72: =O9/SUM(O45:O46)
A73: OCF/EBITDA | B73: % | C73: =C64/C13 | D73: =D64/D13 | E73: =E64/E13 | F73: =F64/F13 | G73: =G64/G13 | H73: =H64/H13 | I73: =I64/I13 | J73: =J64/J13 | ... O73: =O64/O13 | R73: =AVERAGE(J73:L73) | S73: =AVERAGE(H73:L73) | T73: =AVERAGE(C73:L73) | U73: =R73 | V73: =U73 | W73: =V73
A74: FCF/PAT | B74: % | D74: =D66/D20 | E74: =E66/E20 | F74: =F66/F20 | G74: =G66/G20 | H74: =H66/H20 | I74: =I66/I20 | J74: =J66/J20 | K74: =K66/K20 | ... O74: =O66/O20 | R74: =AVERAGE(J74:L74) | S74: =AVERAGE(H74:L74) | T74: =AVERAGE(C74:L74)
A76: Debt Equity | B76: x | C76: =C42/C41 | D76: =D42/D41 | E76: =E42/E41 | F76: =F42/F41 | G76: =G42/G41 | H76: =H42/H41 | I76: =I42/I41 | J76: =J42/J41 | ... O76: =O42/O41 | R76: =AVERAGE(J76:L76) | S76: =AVERAGE(H76:L76) | T76: =AVERAGE(C76:L76)
A77: Interest Coverage | B77: x | C77: =(C18+C17)/C17 | D77: =(D18+D17)/D17 | E77: =(E18+E17)/E17 | F77: =(F18+F17)/F17 | G77: =(G18+G17)/G17 | H77: =(H18+H17)/H17 | I77: =(I18+I17)/I17 | J77: =(J18+J17)/J17 | ... O77: =(O18+O17)/O17 | R77: =AVERAGE(J77:L77) | S77: =AVERAGE(H77:L77) | T77: =AVERAGE(C77:L77)
A78: Performance Ratios
A79: ROE | B79: % | C79: =C20/C41 | D79: =D20/D41 | E79: =E20/E41 | F79: =F20/F41 | G79: =G20/G41 | H79: =H20/H41 | I79: =I20/I41 | J79: =J20/J41 | ... O79: =O20/O41 | R79: =AVERAGE(J79:L79) | S79: =AVERAGE(H79:L79) | T79: =AVERAGE(C79:L79)
A80: ROCE | B80: % | D80: =(D18+D17)/AVERAGE(C43:D43) | E80: =(E18+E17)/AVERAGE(D43:E43) | F80: =(F18+F17)/AVERAGE(E43:F43) | G80: =(G18+G17)/AVERAGE(F43:G43) | H80: =(H18+H17)/AVERAGE(G43:H43) | I80: =(I18+I17)/AVERAGE(H43:I43) | J80: =(J18+J17)/AVERAGE(I43:J43) | K80: =(K18+K17)/AVERAGE(J43:K43) | ... O80: =(O18+O17)/AVERAGE(N43:O43) | R80: =AVERAGE(J80:L80) | S80: =AVERAGE(H80:L80) | T80: =AVERAGE(C80:L80)
A81: ROIC | D81: =(D18+D17)/(AVERAGE((C43-C47-C55),(D43-D47-D55))) | E81: =(E18+E17)/(AVERAGE((D43-D47-D55),(E43-E47-E55))) | F81: =(F18+F17)/(AVERAGE((E43-E47-E55),(F43-F47-F55))) | G81: =(G18+G17)/(AVERAGE((F43-F47-F55),(G43-G47-G55))) | H81: =(H18+H17)/(AVERAGE((G43-G47-G55),(H43-H47-H55))) | I81: =(I18+I17)/(AVERAGE((H43-H47-H55),(I43-I47-I55))) | J81: =(J18+J17)/(AVERAGE((I43-I47-I55),(J43-J47-J55))) | K81: =(K18+K17)/(AVERAGE((J43-J47-J55),(K43-K47-K55))) | ... O81: =(O18+O17)/(AVERAGE((N43-N47-N55),(O43-O47-O55))) | R81: =AVERAGE(J81:L81) | S81: =AVERAGE(H81:L81) | T81: =AVERAGE(C81:L81)
A82: OCF/Cap Emp | B82: % | C82: =C64/C43 | D82: =D64/D43 | E82: =E64/E43 | F82: =F64/F43 | G82: =G64/G43 | H82: =H64/H43 | I82: =I64/I43 | J82: =J64/J43 | ... O82: =O64/O43
A84: Earnings/share | B84: INR | C84: =C22 | D84: =D22 | E84: =E22 | F84: =F22 | G84: =G22 | H84: =H22 | I84: =I22 | J84: =J22 | ... O84: =O22 | R84: =((L84/I84)^(1/3))-1 | S84: =((L84/G84)^(1/5))-1 | T84: =IF(C84>0,((L84/C84)^(1/9))-1,"-")
A85: Dividend/share | B85: INR | C85: =C23 | D85: =D23 | E85: =E23 | F85: =F23 | G85: =G23 | H85: =H23 | I85: =I23 | J85: =J23 | ... O85: =O23 | R85: =((L85/I85)^(1/3))-1 | S85: =((L85/G85)^(1/5))-1 | T85: =IF(C85>0,((L85/C85)^(1/9))-1,"-")
A86: Book Value/share | B86: INR | C86: =C41/C5 | D86: =D41/D5 | E86: =E41/E5 | F86: =F41/F5 | G86: =G41/G5 | H86: =H41/H5 | I86: =I41/I5 | J86: =J41/J5 | ... O86: =O41/O5 | R86: =((L86/I86)^(1/3))-1 | S86: =((L86/G86)^(1/5))-1 | T86: =IF(C86>0,((L86/C86)^(1/9))-1,"-")
A87: Sales/share | B87: INR | C87: =C9/C5 | D87: =D9/D5 | E87: =E9/E5 | F87: =F9/F5 | G87: =G9/G5 | H87: =H9/H5 | I87: =I9/I5 | J87: =J9/J5 | ... O87: =O9/O5 | R87: =((L87/I87)^(1/3))-1 | S87: =((L87/G87)^(1/5))-1 | T87: =IF(C87>0,((L87/C87)^(1/9))-1,"-")
A88: Cash/share | B88: INR | C88: =(C55-C42)/C5 | D88: =(D55-D42)/D5 | E88: =(E55-E42)/E5 | F88: =(F55-F42)/F5 | G88: =(G55-G42)/G5 | H88: =(H55-H42)/H5 | I88: =(I55-I42)/I5 | J88: =(J55-J42)/J5 | ... O88: =(O55-O42)/O5
A90: Valuations
A91: Price/Earnings | B91: x | C91: =C$4/C84 | D91: =D$4/D84 | E91: =E$4/E84 | F91: =F$4/F84 | G91: =G$4/G84 | H91: =H$4/H84 | I91: =I$4/I84 | J91: =J$4/J84 | ... O91: =O$4/O84 | P91: =P4/P22 | R91: =AVERAGE(J91:L91) | S91: =AVERAGE(H91:L91) | T91: =AVERAGE(C91:L91)
A92: Price/Book | B92: x | C92: =C$4/C86 | D92: =D$4/D86 | E92: =E$4/E86 | F92: =F$4/F86 | G92: =G$4/G86 | H92: =H$4/H86 | I92: =I$4/I86 | J92: =J$4/J86 | ... O92: =O$4/O86 | R92: =AVERAGE(J92:L92) | S92: =AVERAGE(H92:L92) | T92: =AVERAGE(C92:L92)
A93: Price/Sales | B93: x | C93: =C$4/C87 | D93: =D$4/D87 | E93: =E$4/E87 | F93: =F$4/F87 | G93: =G$4/G87 | H93: =H$4/H87 | I93: =I$4/I87 | J93: =J$4/J87 | ... O93: =O$4/O87 | R93: =AVERAGE(J93:L93) | S93: =AVERAGE(H93:L93) | T93: =AVERAGE(C93:L93)
A95: EV/EBITDA | B95: x | C95: =C7/C13 | D95: =D7/D13 | E95: =E7/E13 | F95: =F7/F13 | G95: =G7/G13 | H95: =H7/H13 | I95: =I7/I13 | J95: =J7/J13 | ... P95: =P7/P13 | R95: =AVERAGE(J95:L95) | S95: =AVERAGE(H95:L95) | T95: =AVERAGE(C95:L95)
A96: EV/Sales | B96: x | C96: =C7/C9 | D96: =D7/D9 | E96: =E7/E9 | F96: =F7/F9 | G96: =G7/G9 | H96: =H7/H9 | I96: =I7/I9 | J96: =J7/J9 | ... P96: =P7/P9 | R96: =AVERAGE(J96:L96) | S96: =AVERAGE(H96:L96) | T96: =AVERAGE(C96:L96)
H97: =IF(H98>$L$3,IF(H98<=$M$3,"1","0"),"0") | I97: =IF(I98>$L$3,IF(I98<=$M$3,"1","0"),"0") | J97: =IF(J98>$L$3,IF(J98<=$M$3,"1","0"),"0") | K97: =IF(K98>$L$3,IF(K98<=$M$3,"1","0"),"0") | L97: =IF(L98>$L$3,IF(L98<=$M$3,"1","0"),"0") | M97: =IF(M98>$L$3,IF(M98<=$M$3,"1","0"),"0") | N97: =IF(N98>$L$3,IF(N98<=$M$3,"1","0"),"0") | O97: =IF(O98>$L$3,IF(O98<=$M$3,"1","0"),"0") | P97: =IF(P98>$L$3,IF(P98<=$M$3,"1","0"),"0")
A98: QUARTERLY | C98: ='Data Sheet'!B41 | D98: ='Data Sheet'!C41 | E98: ='Data Sheet'!D41 | F98: ='Data Sheet'!E41 | G98: ='Data Sheet'!F41 | H98: ='Data Sheet'!G41 | I98: ='Data Sheet'!H41 | J98: ='Data Sheet'!I41 | ... L98: ='Data Sheet'!K41 | M98: =L98+90 | N98: =M98+90 | O98: =N98+90 | P98: =O98+90 | Q98: forecast
A99: Revenue Qtr | B99: Cr | C99: ='Data Sheet'!B42 | D99: ='Data Sheet'!C42 | E99: ='Data Sheet'!D42 | F99: ='Data Sheet'!E42 | G99: ='Data Sheet'!F42 | H99: ='Data Sheet'!G42 | I99: ='Data Sheet'!H42 | J99: ='Data Sheet'!I42 | ... L99: ='Data Sheet'!K42 | M99: =I99*(1+$U$9) | N99: =J99*(1+$U$9) | O99: =K99*(1+$U$9) | P99: =L99*(1+$U$9) | Q99: =SUMIF(H$97:P$97,"=1",H99:P99) | R99: =Q99/M9
A100: Growth (QoQ) | D100: =D99/C99-1 | E100: =E99/D99-1 | F100: =F99/E99-1 | G100: =G99/F99-1 | H100: =H99/G99-1 | I100: =I99/H99-1 | J100: =J99/I99-1 | K100: =K99/J99-1 | ... P100: =P99/O99-1
A101: EBITDA Qtr | B101: Cr | C101: ='Data Sheet'!B50 | D101: ='Data Sheet'!C50 | E101: ='Data Sheet'!D50 | F101: ='Data Sheet'!E50 | G101: ='Data Sheet'!F50 | H101: ='Data Sheet'!G50 | I101: ='Data Sheet'!H50 | J101: ='Data Sheet'!I50 | ... L101: ='Data Sheet'!K50 | M101: =M99*$U$27 | N101: =N99*$U$27 | O101: =O99*$U$27 | P101: =P99*$U$27 | Q101: =SUMIF(H$97:P$97,"=1",H101:P101) | R101: =Q101/M13
A102: Growth (QoQ) | D102: =D101/C101-1 | E102: =E101/D101-1 | F102: =F101/E101-1 | G102: =G101/F101-1 | H102: =H101/G101-1 | I102: =I101/H101-1 | J102: =J101/I101-1 | K102: =K101/J101-1 | ... P102: =P101/O101-1
A103: EBITDAM Qtr | B103: % | C103: =C101/C99 | D103: =D101/D99 | E103: =E101/E99 | F103: =F101/F99 | G103: =G101/G99 | H103: =H101/H99 | I103: =I101/I99 | J103: =J101/J99 | ... Q103: =Q101/Q99 | R103: =Q103/M27
A104: Tax rate | B104: % | C104: ='Data Sheet'!B48/'Data Sheet'!B47 | D104: ='Data Sheet'!C48/'Data Sheet'!C47 | E104: ='Data Sheet'!D48/'Data Sheet'!D47 | F104: ='Data Sheet'!E48/'Data Sheet'!E47 | G104: ='Data Sheet'!F48/'Data Sheet'!F47 | H104: ='Data Sheet'!G48/'Data Sheet'!G47 | I104: ='Data Sheet'!H48/'Data Sheet'!H47 | J104: ='Data Sheet'!I48/'Data Sheet'!I47 | ... L104: ='Data Sheet'!K48/'Data Sheet'!K47 | M104: =$U$30 | N104: =$U$30 | O104: =$U$30 | P104: =$U$30
A105: PAT Qtr | B105: Cr | C105: ='Data Sheet'!B49 | D105: ='Data Sheet'!C49 | E105: ='Data Sheet'!D49 | F105: ='Data Sheet'!E49 | G105: ='Data Sheet'!F49 | H105: ='Data Sheet'!G49 | I105: ='Data Sheet'!H49 | J105: ='Data Sheet'!I49 | ... L105: ='Data Sheet'!K49 | M105: =(M101+M114-M115-M116)*(1-M104) | N105: =(N101+N114-N115-N116)*(1-N104) | O105: =(O101+O114-O115-O116)*(1-O104) | P105: =(P101+P114-P115-P116)*(1-P104) | Q105: =SUMIF(H$97:P$97,"=1",H105:P105) | R105: =Q105/M20
A106: Growth (QoQ) | D106: =D105/C105-1 | E106: =E105/D105-1 | F106: =F105/E105-1 | G106: =G105/F105-1 | H106: =H105/G105-1 | I106: =I105/H105-1 | J106: =J105/I105-1 | K106: =K105/J105-1 | ... P106: =P105/O105-1
A107: PAT Qtr Margin | C107: =C105/C99 | D107: =D105/D99 | E107: =E105/E99 | F107: =F105/F99 | G107: =G105/G99 | H107: =H105/H99 | I107: =I105/I99 | J107: =J105/J99 | ... P107: =P105/P99
A109: YoY Growth | Q109: 2 Yr CAGR
A110: Revenue Qtr - YoY Growth | B110: % | G110: =G99/C99-1 | H110: =H99/D99-1 | I110: =I99/E99-1 | J110: =J99/F99-1 | K110: =K99/G99-1 | L110: =L99/H99-1 | M110: =M99/I99-1 | N110: =N99/J99-1 | ... P110: =P99/L99-1 | Q110: =((L99/D99)^(1/2))-1
A111: EBITDA Qtr - YoY Growth | B111: % | G111: =G101/C101-1 | H111: =H101/D101-1 | I111: =I101/E101-1 | J111: =J101/F101-1 | K111: =K101/G101-1 | L111: =L101/H101-1 | M111: =M101/I101-1 | N111: =N101/J101-1 | ... P111: =P101/L101-1 | Q111: =((L101/D101)^(1/2))-1
A112: PAT Qtr - YoY Growth | B112: % | G112: =G105/C105-1 | H112: =H105/D105-1 | I112: =I105/E105-1 | J112: =J105/F105-1 | K112: =K105/G105-1 | L112: =L105/H105-1 | M112: =M105/I105-1 | N112: =N105/J105-1 | ... P112: =P105/L105-1 | Q112: =((L105/D105)^(1/2))-1
...

Sheet Segments
D1: ='Data Sheet'!B16 | E1: ='Data Sheet'!C16 | F1: ='Data Sheet'!D16 | G1: ='Data Sheet'!E16 | H1: ='Data Sheet'!F16 | I1: ='Data Sheet'!G16 | J1: ='Data Sheet'!H16 | K1: ='Data Sheet'!I16 | ... M1: ='Data Sheet'!K16 | N1: =M1+365 | O1: =N1+365 | P1: =O1+365 | Q1: TTM | R1: 3 Yr Proj CAGR | S1: 3 Yr CAGR | T1: 5 Yr CAGR | U1: 9Yr CAGR | V1: =N1 | W1: =O1 | X1: =P1
A2: Revenue | B2: Cr | D2: ='Data Sheet'!B17 | E2: ='Data Sheet'!C17 | F2: ='Data Sheet'!D17 | G2: ='Data Sheet'!E17 | H2: ='Data Sheet'!F17 | I2: ='Data Sheet'!G17 | J2: ='Data Sheet'!H17 | K2: ='Data Sheet'!I17 | ... M2: ='Data Sheet'!K17 | N2: =M2*(1+$V2) | O2: =N2*(1+$W2) | P2: =O2*(1+$X2) | Q2: =SUM(J53:M53) | R2: =((P2/M2)^(1/3))-1 | S2: =((M2/J2)^(1/3))-1 | T2: =((M2/H2)^(1/5))-1 | U2: =IF(D2>0,((M2/D2)^(1/9))-1,"-") | V2: =S2 | W2: =V2 | X2: =W2
A3: PBIT | B3: Cr | D3: ='Data Sheet'!B28+'Data Sheet'!B27 | E3: ='Data Sheet'!C28+'Data Sheet'!C27 | F3: ='Data Sheet'!D28+'Data Sheet'!D27 | G3: ='Data Sheet'!E28+'Data Sheet'!E27 | H3: ='Data Sheet'!F28+'Data Sheet'!F27 | I3: ='Data Sheet'!G28+'Data Sheet'!G27 | J3: ='Data Sheet'!H28+'Data Sheet'!H27 | K3: ='Data Sheet'!I28+'Data Sheet'!I27 | ... M3: ='Data Sheet'!K28+'Data Sheet'!K27 | N3: =Financial!M18+Financial!M17 | O3: =Financial!N18+Financial!N17 | P3: =Financial!O18+Financial!O17 | Q3: =SUM('Data Sheet'!H47:K47)+SUM('Data Sheet'!H46:K46)
A4: CAPITAL EMPLOYED | D4: =Financial!C43 | E4: =Financial!D43 | F4: =Financial!E43 | G4: =Financial!F43 | H4: =Financial!G43 | I4: =Financial!H43 | J4: =Financial!I43 | K4: =Financial!J43 | ... P4: =Financial!O43
A5: DEVIATION
A6: Revenue | D6: =D2/D20-1 | E6: =E2/E20-1 | F6: =F2/F20-1 | G6: =G2/G20-1 | H6: =H2/H20-1 | I6: =I2/I20-1 | J6: =J2/J20-1 | K6: =K2/K20-1 | ... P6: =P2/P20-1
A7: PBIT | D7: =D3/D32-1 | E7: =E3/E32-1 | F7: =F3/F32-1 | G7: =G3/G32-1 | H7: =H3/H32-1 | I7: =I3/I32-1 | J7: =J3/J32-1 | K7: =K3/K32-1 | ... M7: =M3/M32-1
A8: CAPITAL EMPLOYED
A10: SEGMENT REVENUE | D10: =D1 | E10: =E1 | F10: =F1 | G10: =G1 | H10: =H1 | I10: =I1 | J10: =J1 | K10: =K1 | ... P10: =P1
A11: Banking Finance Insurance | B11: 21062 | C11: 27146 | D11: 35112 | E11: 38566 | F11: 44163 | G11: 47505 | H11: 48418 | I11: 57938 | J11: 61095 | K11: 65634 | L11: 75126 | M11: 86127 | N11: =M11*(1+$V11) | O11: =N11*(1+$W11) | P11: =O11*(1+$X11) | R11: =((P11/M11)^(1/3))-1 | S11: =((M11/J11)^(1/3))-1 | T11: =((M11/H11)^(1/5))-1 | U11: =IF(D11>0,((M11/D11)^(1/9))-1,"-") | V11: =S11 | W11: =V11 | X11: =W11
A12: Communication, Media and Technology | B12: 6205 | C12: 7540 | D12: 9614 | E12: 10934 | F12: 18040 | G12: 19521 | H12: 21131 | I12: 23925 | J12: 25978 | K12: 27077 | L12: 31874 | M12: 37653 | N12: =M12*(1+$V12) | O12: =N12*(1+$W12) | P12: =O12*(1+$X12) | R12: =((P12/M12)^(1/3))-1 | S12: =((M12/J12)^(1/3))-1 | T12: =((M12/H12)^(1/5))-1 | U12: =IF(D12>0,((M12/D12)^(1/9))-1,"-") | V12: =S12 | W12: =V12 | X12: =W12
A13: Retail and Consumer Packing Goods | B13: 5954 | C13: 8401 | D13: 11309 | E13: 12829 | F13: 19204 | G13: 20459 | H13: 21055 | I13: 25164 | J13: 26280 | K13: 25589 | L13: 30715 | M13: 37506 | N13: =M13*(1+$V13) | O13: =N13*(1+$W13) | P13: =O13*(1+$X13) | R13: =((P13/M13)^(1/3))-1 | S13: =((M13/J13)^(1/3))-1 | T13: =((M13/H13)^(1/5))-1 | U13: =IF(D13>0,((M13/D13)^(1/9))-1,"-") | V13: =S13 | W13: =V13 | X13: =W13
A14: Life Sciences and Healthcare | B14: 0 | C14: 0 | D14: 0 | E14: 0 | F14: 0 | G14: 0 | H14: 0 | I14: 0 | J14: 0 | K14: 16968 | L14: 20462 | M14: 24605 | N14: =M14*(1+$V14) | O14: =N14*(1+$W14) | P14: =O14*(1+$X14) | R14: =((P14/M14)^(1/3))-1 | S14: =((M14/J14)^(1/3))-1 | T14: =((M14/H14)^(1/5))-1 | U14: =IF(D14>0,((M14/D14)^(1/9))-1,"-") | V14: =S14 | W14: =V14 | X14: =W14
A15: Manufacturing | B15: 3801 | C15: 5216 | D15: 6989 | E15: 9242 | F15: 10909 | G15: 12486 | H15: 13361 | I15: 15682 | J15: 16468 | K15: 15950 | L15: 18610 | M15: 21236 | N15: =M15*(1+$V15) | O15: =N15*(1+$W15) | P15: =O15*(1+$X15) | R15: =((P15/M15)^(1/3))-1 | S15: =((M15/J15)^(1/3))-1 | T15: =((M15/H15)^(1/5))-1 | U15: =IF(D15>0,((M15/D15)^(1/9))-1,"-") | V15: =S15 | W15: =V15 | X15: =W15
A16: Others | B16: 11872 | C16: 14687 | D16: 18785 | E16: 23078 | F16: 16330 | G16: 17995 | H16: 19139 | I16: 23754 | J16: 27128 | K16: 12959 | L16: 14967 | M16: 18331 | N16: =M16*(1+$V16) | O16: =N16*(1+$W16) | P16: =O16*(1+$X16) | R16: =((P16/M16)^(1/3))-1 | S16: =((M16/J16)^(1/3))-1 | T16: =((M16/H16)^(1/5))-1 | U16: =IF(D16>0,((M16/D16)^(1/9))-1,"-") | V16: =S16 | W16: =V16 | X16: =W16
N17: =M17*(1+$V17) | O17: =N17*(1+$W17) | P17: =O17*(1+$X17) | R17: =((P17/M17)^(1/3))-1 | S17: =((M17/J17)^(1/3))-1 | T17: =((M17/H17)^(1/5))-1 | U17: =IF(D17>0,((M17/D17)^(1/9))-1,"-") | V17: =S17 | W17: =V17 | X17: =W17
N18: =M18*(1+$V18) | O18: =N18*(1+$W18) | P18: =O18*(1+$X18) | R18: =((P18/M18)^(1/3))-1 | S18: =((M18/J18)^(1/3))-1 | T18: =((M18/H18)^(1/5))-1 | U18: =IF(D18>0,((M18/D18)^(1/9))-1,"-") | V18: =S18 | W18: =V18 | X18: =W18
A19: Pledge | N19: =M19*(1+$V19) | O19: =N19*(1+$W19) | P19: =O19*(1+$X19) | R19: =((P19/M19)^(1/3))-1 | S19: =((M19/J19)^(1/3))-1 | T19: =((M19/H19)^(1/5))-1 | U19: =IF(D19>0,((M19/D19)^(1/9))-1,"-") | V19: =S19 | W19: =V19 | X19: =W19
A20: TOTAL | D20: =SUM(D11:D19) | E20: =SUM(E11:E19) | F20: =SUM(F11:F19) | G20: =SUM(G11:G19) | H20: =SUM(H11:H19) | I20: =SUM(I11:I19) | J20: =SUM(J11:J19) | K20: =SUM(K11:K19) | ... P20: =SUM(P11:P19) | R20: =((P20/M20)^(1/3))-1 | S20: =((M20/J20)^(1/3))-1 | T20: =((M20/H20)^(1/5))-1 | U20: =IF(D20>0,((M20/D20)^(1/9))-1,"-") | V20: =S20 | W20: =V20 | X20: =W20
A21: Managerial Remuneration | B21: Cr | R21: =((P21/M21)^(1/3))-1 | S21: =((M21/J21)^(1/3))-1 | T21: =((M21/H21)^(1/5))-1 | U21: =IF(D21>0,((M21/D21)^(1/9))-1,"-") | V21: =S21 | W21: =V21 | X21: =W21
A22: SEGMENT PBIT | R22: =((P22/M22)^(1/3))-1 | S22: =((M22/J22)^(1/3))-1 | T22: =((M22/H22)^(1/5))-1 | U22: =IF(D22>0,((M22/D22)^(1/9))-1,"-") | V22: =S22 | W22: =V22 | X22: =W22
A23: Banking Finance Insurance | B23: 6493 | C23: 8014 | D23: 11523 | E23: 10594 | F23: 12851 | G23: 13098 | H23: 13045 | I23: 16089 | J23: 16950 | K23: 18681 | L23: 20174 | M23: 22345 | N23: =M23*(1+$V23) | O23: =N23*(1+$W23) | P23: =O23*(1+$X23) | R23: =((P23/M23)^(1/3))-1 | S23: =((M23/J23)^(1/3))-1 | T23: =((M23/H23)^(1/5))-1 | U23: =IF(D23>0,((M23/D23)^(1/9))-1,"-") | V23: =S23 | W23: =V23 | X23: =W23
A24: Communication, Media and Technology | B24: 1890 | C24: 1949 | D24: 2749 | E24: 2771 | F24: 5190 | G24: 5552 | H24: 5797 | I24: 6644 | J24: 7703 | K24: 8010 | L24: 9518 | M24: 10667 | N24: =M24*(1+$V24) | O24: =N24*(1+$W24) | P24: =O24*(1+$X24) | R24: =((P24/M24)^(1/3))-1 | S24: =((M24/J24)^(1/3))-1 | T24: =((M24/H24)^(1/5))-1 | U24: =IF(D24>0,((M24/D24)^(1/9))-1,"-") | V24: =S24 | W24: =V24 | X24: =W24
A25: Retail and Consumer Packing Goods | B25: 1742 | C25: 2581 | D25: 3674 | E25: 3254 | F25: 5330 | G25: 5740 | H25: 5580 | I25: 6871 | J25: 6870 | K25: 7151 | L25: 8534 | M25: 9636 | N25: =M25*(1+$V25) | O25: =N25*(1+$W25) | P25: =O25*(1+$X25) | R25: =((P25/M25)^(1/3))-1 | S25: =((M25/J25)^(1/3))-1 | T25: =((M25/H25)^(1/5))-1 | U25: =IF(D25>0,((M25/D25)^(1/9))-1,"-") | V25: =S25 | W25: =V25 | X25: =W25
A26: Life Sciences and Healthcare | B26: 0 | C26: 0 | D26: 0 | E26: 0 | F26: 0 | G26: 0 | H26: 0 | I26: 0 | J26: 0 | K26: 5253 | L26: 6139 | M26: 6894 | N26: =M26*(1+$V26) | O26: =N26*(1+$W26) | P26: =O26*(1+$X26) | R26: =((P26/M26)^(1/3))-1 | S26: =((M26/J26)^(1/3))-1 | T26: =((M26/H26)^(1/5))-1 | U26: =IF(D26>0,((M26/D26)^(1/9))-1,"-") | V26: =S26 | W26: =V26 | X26: =W26
A27: Manufacturing | B27: 986 | C27: 1363 | D27: 2051 | E27: 2223 | F27: 2924 | G27: 3574 | H27: 3698 | I27: 4311 | J27: 4445 | K27: 4483 | L27: 5602 | M27: 5842 | N27: =M27*(1+$V27) | O27: =N27*(1+$W27) | P27: =O27*(1+$X27) | R27: =((P27/M27)^(1/3))-1 | S27: =((M27/J27)^(1/3))-1 | T27: =((M27/H27)^(1/5))-1 | U27: =IF(D27>0,((M27/D27)^(1/9))-1,"-") | V27: =S27 | W27: =V27 | X27: =W27
A28: Others | B28: 3203 | C28: 3992 | D28: 5029 | E28: 5480 | F28: 4294 | G28: 4271 | H28: 4339 | I28: 5554 | J28: 6141 | K28: 2968 | L28: 3090 | M28: 3875 | N28: =M28*(1+$V28) | O28: =N28*(1+$W28) | P28: =O28*(1+$X28) | R28: =((P28/M28)^(1/3))-1 | S28: =((M28/J28)^(1/3))-1 | T28: =((M28/H28)^(1/5))-1 | U28: =IF(D28>0,((M28/D28)^(1/9))-1,"-") | V28: =S28 | W28: =V28 | X28: =W28
A29: Unallocated | B29: -390 | C29: 192 | D29: 377 | E29: 1486 | F29: 1251 | G29: 2278 | H29: 1633 | I29: 2094 | J29: 139 | K29: -2786 | L29: -1370 | M29: -2352 | N29: =M29*(1+$V29) | O29: =N29*(1+$W29) | P29: =O29*(1+$X29) | R29: =((P29/M29)^(1/3))-1 | S29: =((M29/J29)^(1/3))-1 | T29: =((M29/H29)^(1/5))-1 | U29: =IF(D29>0,((M29/D29)^(1/9))-1,"-") | V29: =S29 | W29: =V29 | X29: =W29
N30: =M30*(1+$V30) | O30: =N30*(1+$W30) | P30: =O30*(1+$X30) | R30: =((P30/M30)^(1/3))-1 | S30: =((M30/J30)^(1/3))-1 | T30: =((M30/H30)^(1/5))-1 | U30: =IF(D30>0,((M30/D30)^(1/9))-1,"-") | V30: =S30 | W30: =V30 | X30: =W30
A31: Pledge | N31: =M31*(1+$V31) | O31: =N31*(1+$W31) | P31: =O31*(1+$X31) | R31: =((P31/M31)^(1/3))-1 | S31: =((M31/J31)^(1/3))-1 | T31: =((M31/H31)^(1/5))-1 | U31: =IF(D31>0,((M31/D31)^(1/9))-1,"-") | V31: =S31 | W31: =V31 | X31: =W31
A32: TOTAL | B32: =SUM(B23:B31) | C32: =SUM(C23:C31) | D32: =SUM(D23:D31) | E32: =SUM(E23:E31) | F32: =SUM(F23:F31) | G32: =SUM(G23:G31) | H32: =SUM(H23:H31) | I32: =SUM(I23:I31) | ... P32: =SUM(P23:P31) | R32: =((P32/M32)^(1/3))-1 | S32: =((M32/J32)^(1/3))-1 | T32: =((M32/H32)^(1/5))-1 | U32: =IF(D32>0,((M32/D32)^(1/9))-1,"-") | V32: =S32 | W32: =V32 | X32: =W32
R33: =((P33/M33)^(1/3))-1 | S33: =((M33/J33)^(1/3))-1 | T33: =((M33/H33)^(1/5))-1 | U33: =IF(D33>0,((M33/D33)^(1/9))-1,"-") | V33: =S33 | W33: =V33 | X33: =W33
A34: SEGMENT CAPITAL EMPLOYED | R34: =((P34/M34)^(1/3))-1 | S34: =((M34/J34)^(1/3))-1 | T34: =((M34/H34)^(1/5))-1 | U34: =IF(D34>0,((M34/D34)^(1/9))-1,"-") | V34: =S34 | W34: =V34 | X34: =W34
A35: Banking Finance Insurance | B35: 8570 | C35: 10045 | D35: 8344 | E35: 7057 | F35: 9681 | G35: 8635 | H35: 9039 | I35: 10483 | J35: 0 | K35: 0 | L35: 0 | M35: 0 | R35: =((P35/M35)^(1/3))-1 | S35: =((M35/J35)^(1/3))-1 | T35: =((M35/H35)^(1/5))-1 | U35: =IF(D35>0,((M35/D35)^(1/9))-1,"-") | V35: =S35 | W35: =V35 | X35: =W35
A36: Communication, Media and Technology | B36: 1901 | C36: 2336 | D36: 2977 | E36: 2697 | F36: 4639 | G36: 4671 | H36: 5605 | I36: 5590 | J36: 0 | K36: 0 | L36: 0 | M36: 0 | R36: =((P36/M36)^(1/3))-1 | S36: =((M36/J36)^(1/3))-1 | T36: =((M36/H36)^(1/5))-1 | U36: =IF(D36>0,((M36/D36)^(1/9))-1,"-") | V36: =S36 | W36: =V36 | X36: =W36
A37: Retail and Consumer Packing Goods | B37: 1384 | C37: 2051 | D37: 2924 | E37: 2768 | F37: 4641 | G37: 4850 | H37: 5546 | I37: 0 | J37: 0 | K37: 0 | L37: 0 | M37: 0 | R37: =((P37/M37)^(1/3))-1 | S37: =((M37/J37)^(1/3))-1 | T37: =((M37/H37)^(1/5))-1 | U37: =IF(D37>0,((M37/D37)^(1/9))-1,"-") | V37: =S37 | W37: =V37 | X37: =W37
A38: Manufacturing | B38: 991 | C38: 1493 | D38: 1994 | E38: 2148 | F38: 2676 | G38: 3100 | H38: 3381 | I38: 4043 | J38: 0 | K38: 0 | L38: 0 | M38: 0 | R38: =((P38/M38)^(1/3))-1 | S38: =((M38/J38)^(1/3))-1 | T38: =((M38/H38)^(1/5))-1 | U38: =IF(D38>0,((M38/D38)^(1/9))-1,"-") | V38: =S38 | W38: =V38 | X38: =W38
A39: Others | B39: 5179 | C39: 6027 | D39: 7009 | E39: 7121 | F39: 5531 | G39: 5569 | H39: 6223 | I39: 6864 | J39: 0 | K39: 0 | L39: 0 | M39: 0 | R39: =((P39/M39)^(1/3))-1 | S39: =((M39/J39)^(1/3))-1 | T39: =((M39/H39)^(1/5))-1 | U39: =IF(D39>0,((M39/D39)^(1/9))-1,"-") | V39: =S39 | W39: =V39 | X39: =W39
A40: Retail and Distribution | B40: 0 | C40: 0 | D40: 0 | E40: 0 | F40: 0 | G40: 0 | H40: 0 | I40: 6447 | J40: 0 | K40: 0 | L40: 0 | M40: 0 | R40: =((P40/M40)^(1/3))-1 | S40: =((M40/J40)^(1/3))-1 | T40: =((M40/H40)^(1/5))-1 | U40: =IF(D40>0,((M40/D40)^(1/9))-1,"-") | V40: =S40 | W40: =V40 | X40: =W40
A41: Unallocated | B41: 12112 | C41: 17389 | D41: 26655 | E41: 29971 | F41: 44259 | G41: 59755 | H41: 55736 | I41: 56472 | J41: 0 | K41: 0 | L41: 0 | M41: 0 | R41: =((P41/M41)^(1/3))-1 | S41: =((M41/J41)^(1/3))-1 | T41: =((M41/H41)^(1/5))-1 | U41: =IF(D41>0,((M41/D41)^(1/9))-1,"-") | V41: =S41 | W41: =V41 | X41: =W41
R42: =((P42/M42)^(1/3))-1 | S42: =((M42/J42)^(1/3))-1 | T42: =((M42/H42)^(1/5))-1 | U42: =IF(D42>0,((M42/D42)^(1/9))-1,"-") | V42: =S42 | W42: =V42 | X42: =W42
A43: Pledge | R43: =((P43/M43)^(1/3))-1 | S43: =((M43/J43)^(1/3))-1 | T43: =((M43/H43)^(1/5))-1 | U43: =IF(D43>0,((M43/D43)^(1/9))-1,"-") | V43: =S43 | W43: =V43 | X43: =W43
A44: TOTAL | B44: =SUM(B35:B43) | C44: =SUM(C35:C43) | D44: =SUM(D35:D43) | E44: =SUM(E35:E43) | F44: =SUM(F35:F43) | G44: =SUM(G35:G43) | H44: =SUM(H35:H43) | I44: =SUM(I35:I43) | ... M44: =SUM(M35:M43) | R44: =((P44/M44)^(1/3))-1 | S44: =((M44/J44)^(1/3))-1 | T44: =((M44/H44)^(1/5))-1 | U44: =IF(D44>0,((M44/D44)^(1/9))-1,"-") | V44: =S44 | W44: =V44 | X44: =W44
I51: =IF(I52>$M$1,IF(I52<=$N$1,"1","0"),"0") | J51: =IF(J52>$M$1,IF(J52<=$N$1,"1","0"),"0") | K51: =IF(K52>$M$1,IF(K52<=$N$1,"1","0"),"0") | L51: =IF(L52>$M$1,IF(L52<=$N$1,"1","0"),"0") | M51: =IF(M52>$M$1,IF(M52<=$N$1,"1","0"),"0") | N51: =IF(N52>$M$1,IF(N52<=$N$1,"1","0"),"0") | O51: =IF(O52>$M$1,IF(O52<=$N$1,"1","0"),"0") | P51: =IF(P52>$M$1,IF(P52<=$N$1,"1","0"),"0") | Q51: =IF(Q52>$M$1,IF(Q52<=$N$1,"1","0"),"0")
A52: QUARTERLY | D52: ='Data Sheet'!B41 | E52: ='Data Sheet'!C41 | F52: ='Data Sheet'!D41 | G52: ='Data Sheet'!E41 | H52: ='Data Sheet'!F41 | I52: ='Data Sheet'!G41 | J52: ='Data Sheet'!H41 | K52: ='Data Sheet'!I41 | ... M52: ='Data Sheet'!K41 | N52: =M52+90 | O52: =N52+90 | P52: =O52+90 | Q52: =P52+90
A53: Revenue Qtr | B53: Cr | D53: ='Data Sheet'!B42 | E53: ='Data Sheet'!C42 | F53: ='Data Sheet'!D42 | G53: ='Data Sheet'!E42 | H53: ='Data Sheet'!F42 | I53: ='Data Sheet'!G42 | J53: ='Data Sheet'!H42 | K53: ='Data Sheet'!I42 | ... M53: ='Data Sheet'!K42 | N53: =J53*(1+$V$2) | O53: =K53*(1+$V$2) | P53: =L53*(1+$V$2) | Q53: =M53*(1+$V$2)
A54: PBIT | B54: Cr | D54: ='Data Sheet'!B47+'Data Sheet'!B46 | E54: ='Data Sheet'!C47+'Data Sheet'!C46 | F54: ='Data Sheet'!D47+'Data Sheet'!D46 | G54: ='Data Sheet'!E47+'Data Sheet'!E46 | H54: ='Data Sheet'!F47+'Data Sheet'!F46 | I54: ='Data Sheet'!G47+'Data Sheet'!G46 | J54: ='Data Sheet'!H47+'Data Sheet'!H46 | K54: ='Data Sheet'!I47+'Data Sheet'!I46 | ... M54: ='Data Sheet'!K47+'Data Sheet'!K46 | N54: =Financial!M101+Financial!M114-Financial!M115 | O54: =Financial!N101+Financial!N114-Financial!N115 | P54: =Financial!O101+Financial!O114-Financial!O115 | Q54: =Financial!P101+Financial!P114-Financial!P115
A59: SEGMENT REVENUE | D59: =D50 | E59: =E50 | F59: =F50 | G59: =G50 | H59: =H50 | I59: =I50 | J59: =J50 | K59: =K50 | ... M59: =M50
A60: Banking Finance Insurance | B60: 21062 | C60: 27146 | D60: 35112 | E60: 38566 | F60: 44163 | G60: 47505 | H60: 48418 | I60: 57938 | J60: 61095 | K60: 65634 | L60: 75126 | M60: 86127 | N60: =M60*(1+$V60) | O60: =N60*(1+$W60) | P60: =O60*(1+$X60) | R60: =((P60/M60)^(1/3))-1 | S60: =((M60/J60)^(1/3))-1 | T60: =((M60/H60)^(1/5))-1 | U60: =IF(D60>0,((M60/D60)^(1/9))-1,"-") | V60: =S60 | W60: =V60 | X60: =W60
A61: Communication, Media and Technology | B61: 6205 | C61: 7540 | D61: 9614 | E61: 10934 | F61: 18040 | G61: 19521 | H61: 21131 | I61: 23925 | J61: 25978 | K61: 27077 | L61: 31874 | M61: 37653 | N61: =M61*(1+$V61) | O61: =N61*(1+$W61) | P61: =O61*(1+$X61) | R61: =((P61/M61)^(1/3))-1 | S61: =((M61/J61)^(1/3))-1 | T61: =((M61/H61)^(1/5))-1 | U61: =IF(D61>0,((M61/D61)^(1/9))-1,"-") | V61: =S61 | W61: =V61 | X61: =W61
A62: Retail and Consumer Packing Goods | B62: 5954 | C62: 8401 | D62: 11309 | E62: 12829 | F62: 19204 | G62: 20459 | H62: 21055 | I62: 25164 | J62: 26280 | K62: 25589 | L62: 30715 | M62: 37506 | N62: =M62*(1+$V62) | O62: =N62*(1+$W62) | P62: =O62*(1+$X62) | R62: =((P62/M62)^(1/3))-1 | S62: =((M62/J62)^(1/3))-1 | T62: =((M62/H62)^(1/5))-1 | U62: =IF(D62>0,((M62/D62)^(1/9))-1,"-") | V62: =S62 | W62: =V62 | X62: =W62
A63: Life Sciences and Healthcare | B63: 0 | C63: 0 | D63: 0 | E63: 0 | F63: 0 | G63: 0 | H63: 0 | I63: 0 | J63: 0 | K63: 16968 | L63: 20462 | M63: 24605 | N63: =M63*(1+$V63) | O63: =N63*(1+$W63) | P63: =O63*(1+$X63) | R63: =((P63/M63)^(1/3))-1 | S63: =((M63/J63)^(1/3))-1 | T63: =((M63/H63)^(1/5))-1 | U63: =IF(D63>0,((M63/D63)^(1/9))-1,"-") | V63: =S63 | W63: =V63 | X63: =W63
A64: Manufacturing | B64: 3801 | C64: 5216 | D64: 6989 | E64: 9242 | F64: 10909 | G64: 12486 | H64: 13361 | I64: 15682 | J64: 16468 | K64: 15950 | L64: 18610 | M64: 21236 | N64: =M64*(1+$V64) | O64: =N64*(1+$W64) | P64: =O64*(1+$X64) | R64: =((P64/M64)^(1/3))-1 | S64: =((M64/J64)^(1/3))-1 | T64: =((M64/H64)^(1/5))-1 | U64: =IF(D64>0,((M64/D64)^(1/9))-1,"-") | V64: =S64 | W64: =V64 | X64: =W64
A65: Others | B65: 11872 | C65: 14687 | D65: 18785 | E65: 23078 | F65: 16330 | G65: 17995 | H65: 19139 | I65: 23754 | J65: 27128 | K65: 12959 | L65: 14967 | M65: 18331 | N65: =M65*(1+$V65) | O65: =N65*(1+$W65) | P65: =O65*(1+$X65) | R65: =((P65/M65)^(1/3))-1 | S65: =((M65/J65)^(1/3))-1 | T65: =((M65/H65)^(1/5))-1 | U65: =IF(D65>0,((M65/D65)^(1/9))-1,"-") | V65: =S65 | W65: =V65 | X65: =W65
N66: =M66*(1+$V66) | O66: =N66*(1+$W66) | P66: =O66*(1+$X66) | R66: =((P66/M66)^(1/3))-1 | S66: =((M66/J66)^(1/3))-1 | T66: =((M66/H66)^(1/5))-1 | U66: =IF(D66>0,((M66/D66)^(1/9))-1,"-") | V66: =S66 | W66: =V66 | X66: =W66
N67: =M67*(1+$V67) | O67: =N67*(1+$W67) | P67: =O67*(1+$X67) | R67: =((P67/M67)^(1/3))-1 | S67: =((M67/J67)^(1/3))-1 | T67: =((M67/H67)^(1/5))-1 | U67: =IF(D67>0,((M67/D67)^(1/9))-1,"-") | V67: =S67 | W67: =V67 | X67: =W67
A68: Pledge | N68: =M68*(1+$V68) | O68: =N68*(1+$W68) | P68: =O68*(1+$X68) | R68: =((P68/M68)^(1/3))-1 | S68: =((M68/J68)^(1/3))-1 | T68: =((M68/H68)^(1/5))-1 | U68: =IF(D68>0,((M68/D68)^(1/9))-1,"-") | V68: =S68 | W68: =V68 | X68: =W68
A69: TOTAL | D69: =SUM(D60:D68) | E69: =SUM(E60:E68) | F69: =SUM(F60:F68) | G69: =SUM(G60:G68) | H69: =SUM(H60:H68) | I69: =SUM(I60:I68) | J69: =SUM(J60:J68) | K69: =SUM(K60:K68) | ... P69: =SUM(P60:P68) | R69: =((P69/M69)^(1/3))-1 | S69: =((M69/J69)^(1/3))-1 | T69: =((M69/H69)^(1/5))-1 | U69: =IF(D69>0,((M69/D69)^(1/9))-1,"-") | V69: =S69 | W69: =V69 | X69: =W69
A70: Managerial Remuneration | B70: Cr | R70: =((P70/M70)^(1/3))-1 | S70: =((M70/J70)^(1/3))-1 | T70: =((M70/H70)^(1/5))-1 | U70: =IF(D70>0,((M70/D70)^(1/9))-1,"-") | V70: =S70 | W70: =V70 | X70: =W70
A71: SEGMENT PBIT | R71: =((P71/M71)^(1/3))-1 | S71: =((M71/J71)^(1/3))-1 | T71: =((M71/H71)^(1/5))-1 | U71: =IF(D71>0,((M71/D71)^(1/9))-1,"-") | V71: =S71 | W71: =V71 | X71: =W71
A72: Banking Finance Insurance | B72: 6493 | C72: 8014 | D72: 11523 | E72: 10594 | F72: 12851 | G72: 13098 | H72: 13045 | I72: 16089 | J72: 16950 | K72: 18681 | L72: 20174 | M72: 22345 | N72: =M72*(1+$V72) | O72: =N72*(1+$W72) | P72: =O72*(1+$X72) | R72: =((P72/M72)^(1/3))-1 | S72: =((M72/J72)^(1/3))-1 | T72: =((M72/H72)^(1/5))-1 | U72: =IF(D72>0,((M72/D72)^(1/9))-1,"-") | V72: =S72 | W72: =V72 | X72: =W72
A73: Communication, Media and Technology | B73: 1890 | C73: 1949 | D73: 2749 | E73: 2771 | F73: 5190 | G73: 5552 | H73: 5797 | I73: 6644 | J73: 7703 | K73: 8010 | L73: 9518 | M73: 10667 | N73: =M73*(1+$V73) | O73: =N73*(1+$W73) | P73: =O73*(1+$X73) | R73: =((P73/M73)^(1/3))-1 | S73: =((M73/J73)^(1/3))-1 | T73: =((M73/H73)^(1/5))-1 | U73: =IF(D73>0,((M73/D73)^(1/9))-1,"-") | V73: =S73 | W73: =V73 | X73: =W73
A74: Retail and Consumer Packing Goods | B74: 1742 | C74: 2581 | D74: 3674 | E74: 3254 | F74: 5330 | G74: 5740 | H74: 5580 | I74: 6871 | J74: 6870 | K74: 7151 | L74: 8534 | M74: 9636 | N74: =M74*(1+$V74) | O74: =N74*(1+$W74) | P74: =O74*(1+$X74) | R74: =((P74/M74)^(1/3))-1 | S74: =((M74/J74)^(1/3))-1 | T74: =((M74/H74)^(1/5))-1 | U74: =IF(D74>0,((M74/D74)^(1/9))-1,"-") | V74: =S74 | W74: =V74 | X74: =W74
A75: Life Sciences and Healthcare | B75: 0 | C75: 0 | D75: 0 | E75: 0 | F75: 0 | G75: 0 | H75: 0 | I75: 0 | J75: 0 | K75: 5253 | L75: 6139 | M75: 6894 | N75: =M75*(1+$V75) | O75: =N75*(1+$W75) | P75: =O75*(1+$X75) | R75: =((P75/M75)^(1/3))-1 | S75: =((M75/J75)^(1/3))-1 | T75: =((M75/H75)^(1/5))-1 | U75: =IF(D75>0,((M75/D75)^(1/9))-1,"-") | V75: =S75 | W75: =V75 | X75: =W75
A76: Manufacturing | B76: 986 | C76: 1363 | D76: 2051 | E76: 2223 | F76: 2924 | G76: 3574 | H76: 3698 | I76: 4311 | J76: 4445 | K76: 4483 | L76: 5602 | M76: 5842 | N76: =M76*(1+$V76) | O76: =N76*(1+$W76) | P76: =O76*(1+$X76) | R76: =((P76/M76)^(1/3))-1 | S76: =((M76/J76)^(1/3))-1 | T76: =((M76/H76)^(1/5))-1 | U76: =IF(D76>0,((M76/D76)^(1/9))-1,"-") | V76: =S76 | W76: =V76 | X76: =W76
A77: Others | B77: 3203 | C77: 3992 | D77: 5029 | E77: 5480 | F77: 4294 | G77: 4271 | H77: 4339 | I77: 5554 | J77: 6141 | K77: 2968 | L77: 3090 | M77: 3875 | N77: =M77*(1+$V77) | O77: =N77*(1+$W77) | P77: =O77*(1+$X77) | R77: =((P77/M77)^(1/3))-1 | S77: =((M77/J77)^(1/3))-1 | T77: =((M77/H77)^(1/5))-1 | U77: =IF(D77>0,((M77/D77)^(1/9))-1,"-") | V77: =S77 | W77: =V77 | X77: =W77
A78: Unallocated | B78: -390 | C78: 192 | D78: 377 | E78: 1486 | F78: 1251 | G78: 2278 | H78: 1633 | I78: 2094 | J78: 139 | K78: -2786 | L78: -1370 | M78: -2352 | N78: =M78*(1+$V78) | O78: =N78*(1+$W78) | P78: =O78*(1+$X78) | R78: =((P78/M78)^(1/3))-1 | S78: =((M78/J78)^(1/3))-1 | T78: =((M78/H78)^(1/5))-1 | U78: =IF(D78>0,((M78/D78)^(1/9))-1,"-") | V78: =S78 | W78: =V78 | X78: =W78
N79: =M79*(1+$V79) | O79: =N79*(1+$W79) | P79: =O79*(1+$X79) | R79: =((P79/M79)^(1/3))-1 | S79: =((M79/J79)^(1/3))-1 | T79: =((M79/H79)^(1/5))-1 | U79: =IF(D79>0,((M79/D79)^(1/9))-1,"-") | V79: =S79 | W79: =V79 | X79: =W79
A80: Pledge | N80: =M80*(1+$V80) | O80: =N80*(1+$W80) | P80: =O80*(1+$X80) | R80: =((P80/M80)^(1/3))-1 | S80: =((M80/J80)^(1/3))-1 | T80: =((M80/H80)^(1/5))-1 | U80: =IF(D80>0,((M80/D80)^(1/9))-1,"-") | V80: =S80 | W80: =V80 | X80: =W80
A81: TOTAL | B81: =SUM(B72:B80) | C81: =SUM(C72:C80) | D81: =SUM(D72:D80) | E81: =SUM(E72:E80) | F81: =SUM(F72:F80) | G81: =SUM(G72:G80) | H81: =SUM(H72:H80) | I81: =SUM(I72:I80) | ... P81: =SUM(P72:P80) | R81: =((P81/M81)^(1/3))-1 | S81: =((M81/J81)^(1/3))-1 | T81: =((M81/H81)^(1/5))-1 | U81: =IF(D81>0,((M81/D81)^(1/9))-1,"-") | V81: =S81 | W81: =V81 | X81: =W81
R82: =((P82/M82)^(1/3))-1 | S82: =((M82/J82)^(1/3))-1 | T82: =((M82/H82)^(1/5))-1 | U82: =IF(D82>0,((M82/D82)^(1/9))-1,"-") | V82: =S82 | W82: =V82 | X82: =W82
A83: SEGMENT CAPITAL EMPLOYED | R83: =((P83/M83)^(1/3))-1 | S83: =((M83/J83)^(1/3))-1 | T83: =((M83/H83)^(1/5))-1 | U83: =IF(D83>0,((M83/D83)^(1/9))-1,"-") | V83: =S83 | W83: =V83 | X83: =W83
A84: Banking Finance Insurance | B84: 8570 | C84: 10045 | D84: 8344 | E84: 7057 | F84: 9681 | G84: 8635 | H84: 9039 | I84: 10483 | J84: 0 | K84: 0 | L84: 0 | M84: 0 | R84: =((P84/M84)^(1/3))-1 | S84: =((M84/J84)^(1/3))-1 | T84: =((M84/H84)^(1/5))-1 | U84: =IF(D84>0,((M84/D84)^(1/9))-1,"-") | V84: =S84 | W84: =V84 | X84: =W84
A85: Communication, Media and Technology | B85: 1901 | C85: 2336 | D85: 2977 | E85: 2697 | F85: 4639 | G85: 4671 | H85: 5605 | I85: 5590 | J85: 0 | K85: 0 | L85: 0 | M85: 0 | R85: =((P85/M85)^(1/3))-1 | S85: =((M85/J85)^(1/3))-1 | T85: =((M85/H85)^(1/5))-1 | U85: =IF(D85>0,((M85/D85)^(1/9))-1,"-") | V85: =S85 | W85: =V85 | X85: =W85
A86: Retail and Consumer Packing Goods | B86: 1384 | C86: 2051 | D86: 2924 | E86: 2768 | F86: 4641 | G86: 4850 | H86: 5546 | I86: 0 | J86: 0 | K86: 0 | L86: 0 | M86: 0 | R86: =((P86/M86)^(1/3))-1 | S86: =((M86/J86)^(1/3))-1 | T86: =((M86/H86)^(1/5))-1 | U86: =IF(D86>0,((M86/D86)^(1/9))-1,"-") | V86: =S86 | W86: =V86 | X86: =W86
A87: Manufacturing | B87: 991 | C87: 1493 | D87: 1994 | E87: 2148 | F87: 2676 | G87: 3100 | H87: 3381 | I87: 4043 | J87: 0 | K87: 0 | L87: 0 | M87: 0 | R87: =((P87/M87)^(1/3))-1 | S87: =((M87/J87)^(1/3))-1 | T87: =((M87/H87)^(1/5))-1 | U87: =IF(D87>0,((M87/D87)^(1/9))-1,"-") | V87: =S87 | W87: =V87 | X87: =W87
A88: Others | B88: 5179 | C88: 6027 | D88: 7009 | E88: 7121 | F88: 5531 | G88: 5569 | H88: 6223 | I88: 6864 | J88: 0 | K88: 0 | L88: 0 | M88: 0 | R88: =((P88/M88)^(1/3))-1 | S88: =((M88/J88)^(1/3))-1 | T88: =((M88/H88)^(1/5))-1 | U88: =IF(D88>0,((M88/D88)^(1/9))-1,"-") | V88: =S88 | W88: =V88 | X88: =W88
A89: Retail and Distribution | B89: 0 | C89: 0 | D89: 0 | E89: 0 | F89: 0 | G89: 0 | H89: 0 | I89: 6447 | J89: 0 | K89: 0 | L89: 0 | M89: 0 | R89: =((P89/M89)^(1/3))-1 | S89: =((M89/J89)^(1/3))-1 | T89: =((M89/H89)^(1/5))-1 | U89: =IF(D89>0,((M89/D89)^(1/9))-1,"-") | V89: =S89 | W89: =V89 | X89: =W89
A90: Unallocated | B90: 12112 | C90: 17389 | D90: 26655 | E90: 29971 | F90: 44259 | G90: 59755 | H90: 55736 | I90: 56472 | J90: 0 | K90: 0 | L90: 0 | M90: 0 | R90: =((P90/M90)^(1/3))-1 | S90: =((M90/J90)^(1/3))-1 | T90: =((M90/H90)^(1/5))-1 | U90: =IF(D90>0,((M90/D90)^(1/9))-1,"-") | V90: =S90 | W90: =V90 | X90: =W90
R91: =((P91/M91)^(1/3))-1 | S91: =((M91/J91)^(1/3))-1 | T91: =((M91/H91)^(1/5))-1 | U91: =IF(D91>0,((M91/D91)^(1/9))-1,"-") | V91: =S91 | W91: =V91 | X91: =W91
A92: Pledge | R92: =((P92/M92)^(1/3))-1 | S92: =((M92/J92)^(1/3))-1 | T92: =((M92/H92)^(1/5))-1 | U92: =IF(D92>0,((M92/D92)^(1/9))-1,"-") | V92: =S92 | W92: =V92 | X92: =W92
A93: TOTAL | B93: =SUM(B84:B92) | C93: =SUM(C84:C92) | D93: =SUM(D84:D92) | E93: =SUM(E84:E92) | F93: =SUM(F84:F92) | G93: =SUM(G84:G92) | H93: =SUM(H84:H92) | I93: =SUM(I84:I92) | ... P93: =SUM(P84:P92) | R93: =((P93/M93)^(1/3))-1 | S93: =((M93/J93)^(1/3))-1 | T93: =((M93/H93)^(1/5))-1 | U93: =IF(D93>0,((M93/D93)^(1/9))-1,"-") | V93: =S93 | W93: =V93 | X93: =W93

Sheet Estimates
B1: ='Data Sheet'!B1 | C1: =VLOOKUP(B1,Lookup!A:C,3,FALSE) | D1: https://goindiastocks.com/GIA/stockDashboard?Fincode= | E1: =CONCATENATE(D1,C1)
C2: =VLOOKUP(B1,Lookup!A:C,2,FALSE)
A3: =[1]Sheet1!A2 | B3: =[1]Sheet1!B2 | C3: =[1]Sheet1!C2 | D3: =[1]Sheet1!D2 | E3: =[1]Sheet1!E2 | F3: =[1]Sheet1!F2 | G3: =[1]Sheet1!G2 | H3: =[1]Sheet1!H2 | ... N3: =[1]Sheet1!N2
A4: =[1]Sheet1!A3 | B4: =[1]Sheet1!B3 | C4: =[1]Sheet1!C3 | D4: =[1]Sheet1!D3 | E4: =[1]Sheet1!E3 | F4: =[1]Sheet1!F3 | G4: =[1]Sheet1!G3 | H4: =[1]Sheet1!H3 | ... N4: =[1]Sheet1!N3
A5: =[1]Sheet1!A4 | B5: =[1]Sheet1!B4 | C5: =[1]Sheet1!C4 | D5: =[1]Sheet1!D4 | E5: =[1]Sheet1!E4 | F5: =[1]Sheet1!F4 | G5: =[1]Sheet1!G4 | H5: =[1]Sheet1!H4 | ... N5: =[1]Sheet1!N4
A6: =[1]Sheet1!A5 | B6: =[1]Sheet1!B5 | C6: =[1]Sheet1!C5 | D6: =[1]Sheet1!D5 | E6: =[1]Sheet1!E5 | F6: =[1]Sheet1!F5 | G6: =[1]Sheet1!G5 | H6: =[1]Sheet1!H5 | ... N6: =[1]Sheet1!N5
A7: =[1]Sheet1!A6 | B7: =[1]Sheet1!B6 | C7: =[1]Sheet1!C6 | D7: =[1]Sheet1!D6 | E7: =[1]Sheet1!E6 | F7: =[1]Sheet1!F6 | G7: =[1]Sheet1!G6 | H7: =[1]Sheet1!H6 | ... N7: =[1]Sheet1!N6
A8: =[1]Sheet1!A7 | B8: =[1]Sheet1!B7 | C8: =[1]Sheet1!C7 | D8: =[1]Sheet1!D7 | E8: =[1]Sheet1!E7 | F8: =[1]Sheet1!F7 | G8: =[1]Sheet1!G7 | H8: =[1]Sheet1!H7 | ... N8: =[1]Sheet1!N7
A9: =[1]Sheet1!A8 | B9: =[1]Sheet1!B8 | C9: =[1]Sheet1!C8 | D9: =[1]Sheet1!D8 | E9: =[1]Sheet1!E8 | F9: =[1]Sheet1!F8 | G9: =[1]Sheet1!G8 | H9: =[1]Sheet1!H8 | ... N9: =[1]Sheet1!N8
A10: =[1]Sheet1!A9 | B10: =[1]Sheet1!B9 | C10: =[1]Sheet1!C9 | D10: =[1]Sheet1!D9 | E10: =[1]Sheet1!E9 | F10: =[1]Sheet1!F9 | G10: =[1]Sheet1!G9 | H10: =[1]Sheet1!H9 | ... N10: =[1]Sheet1!N9
A11: =[1]Sheet1!A10 | B11: =[1]Sheet1!B10 | C11: =[1]Sheet1!C10 | D11: =[1]Sheet1!D10 | E11: =[1]Sheet1!E10 | F11: =[1]Sheet1!F10 | G11: =[1]Sheet1!G10 | H11: =[1]Sheet1!H10 | ... N11: =[1]Sheet1!N10
A12: =[1]Sheet1!A11 | B12: =[1]Sheet1!B11 | C12: =[1]Sheet1!C11 | D12: =[1]Sheet1!D11 | E12: =[1]Sheet1!E11 | F12: =[1]Sheet1!F11 | G12: =[1]Sheet1!G11 | H12: =[1]Sheet1!H11 | ... N12: =[1]Sheet1!N11
A13: =[1]Sheet1!A12 | B13: =[1]Sheet1!B12 | C13: =[1]Sheet1!C12 | D13: =[1]Sheet1!D12 | E13: =[1]Sheet1!E12 | F13: =[1]Sheet1!F12 | G13: =[1]Sheet1!G12 | H13: =[1]Sheet1!H12 | ... N13: =[1]Sheet1!N12
A14: =[1]Sheet1!A13 | B14: =[1]Sheet1!B13 | C14: =[1]Sheet1!C13 | D14: =[1]Sheet1!D13 | E14: =[1]Sheet1!E13 | F14: =[1]Sheet1!F13 | G14: =[1]Sheet1!G13 | H14: =[1]Sheet1!H13 | ... N14: =[1]Sheet1!N13
... A18: =[1]Sheet1!A17 | B18: =[1]Sheet1!B17 | C18: =[1]Sheet1!C17 | D18: =[1]Sheet1!D17 | E18: =[1]Sheet1!E17 | F18: =[1]Sheet1!F17 | G18: =[1]Sheet1!G17 | H18: =[1]Sheet1!H17 | ... N18: =[1]Sheet1!N17
A20: Revenue | B20: =B4/Financial!C9-1 | C20: =C4/Financial!D9-1 | D20: =D4/Financial!E9-1 | E20: =E4/Financial!F9-1 | F20: =F4/Financial!G9-1 | G20: =G4/Financial!H9-1 | H20: =H4/Financial!I9-1 | I20: =I4/Financial!J9-1 | ... N20: =N4/Financial!O9-1
A21: EBITDA | B21: =B6/Financial!C13-1 | C21: =C6/Financial!D13-1 | D21: =D6/Financial!E13-1 | E21: =E6/Financial!F13-1 | F21: =F6/Financial!G13-1 | G21: =G6/Financial!H13-1 | H21: =H6/Financial!I13-1 | I21: =I6/Financial!J13-1 | ... N21: =N6/Financial!O13-1
A22: PAT | B22: =B9/Financial!C20-1 | C22: =C9/Financial!D20-1 | D22: =D9/Financial!E20-1 | E22: =E9/Financial!F20-1 | F22: =F9/Financial!G20-1 | G22: =G9/Financial!H20-1 | H22: =H9/Financial!I20-1 | I22: =I9/Financial!J20-1 | ... N22: =N9/Financial!O20-1
A23: BVPS | B23: =B17/Financial!C86-1 | C23: =C17/Financial!D86-1 | D23: =D17/Financial!E86-1 | E23: =E17/Financial!F86-1 | F23: =F17/Financial!G86-1 | G23: =G17/Financial!H86-1 | H23: =H17/Financial!I86-1 | I23: =I17/Financial!J86-1 | ... N23: =N17/Financial!O86-1

Sheet Customization
A1: How to use it?
A3: You can customize this workbook as you want.
B4: You can add custom formating, add conditional formating, add your own formulas… do ANYTHING.
B5: Please don't edit the "Data Sheet" only.
A7: After customization, you can upload this back on Screener.
B8: Upload on: | C8: https://www.screener.in/excel/
A10: Download your customized workbooks now onwards.
B11: Now whenever you will "Export to excel" from Screener, it will export your customized file.
A14: TESTING:
B15: This is a testing feature currently.
B16: You can report any formula errors on the worksheet at: | G16: screener.feedback@dalal-street.in

Sheet Data Sheet
A1: COMPANY NAME | B1: GRAVITA INDIA LTD | E1: =IF(B2<>B3, "A NEW VERSION OF THE WORKSHEET IS AVAILABLE", "")
A2: LATEST VERSION | B2: 2.1 | E2: PLEASE DO NOT MAKE ANY CHANGES TO THIS SHEET
A3: CURRENT VERSION | B3: 2.1
A5: META
A6: Number of shares | B6: =IF(B9>0, B9/B8, 0)
A7: Face Value | B7: 2
A8: Current Price | B8: 1777
A9: Market Capitalization | B9: 13112.41
A15: PROFIT & LOSS
A16: Report Date | B16: 42825 | C16: 43190 | D16: 43555 | E16: 43921 | F16: 44286 | G16: 44651 | H16: 45016 | I16: 45382 | J16: 45747 | K16: 46112
A17: Sales | B17: 654.84 | C17: 1017.4 | D17: 1241.73 | E17: 1347.8 | F17: 1409.75 | G17: 2215.87 | H17: 2800.6 | I17: 3160.75 | J17: 3868.77 | K17: 4265.27
A18: Raw Material Cost | B18: 519.38 | C18: 852.76 | D18: 1023.13 | E18: 1114.82 | F18: 1214.89 | G18: 1798.12 | H18: 2316.19 | I18: 2572.29 | J18: 3189.73 | K18: 3591.87
A19: Change in Inventory | B19: 4.17 | C19: 44.22 | D19: -12.31 | E19: 23.75 | F19: 82.48 | G19: 54.59 | H19: 34.17 | I19: 11.1 | J19: 16.93 | K19: 173.92
A20: Power and Fuel | B20: 5.05 | C20: 8.27 | D20: 10.83 | E20: 13.37 | F20: 14.49 | G20: 16.77 | H20: 17.8 | I20: 23.98 | J20: 25.73
A21: Other Mfr. Exp | B21: 18.06 | C21: 26.34 | D21: 36.08 | E21: 39.34 | F21: 44.07 | G21: 71.7 | H21: 97.42 | I21: 96.29 | J21: 114.36
A22: Employee Cost | B22: 35.81 | C22: 52.06 | D22: 63.47 | E22: 65.94 | F22: 72.9 | G22: 102.75 | H22: 133.56 | I22: 131.24 | J22: 159.49 | K22: 181.77
A23: Selling and admin | B23: 14.05 | C23: 21.77 | D23: 22.25 | E23: 16.23 | F23: 19.15 | G23: 30.78 | H23: 39.39 | I23: 39.72 | J23: 46.99
A24: Other Expenses | B24: 8.15 | C24: 8.81 | D24: 11.8 | E24: 13.12 | F24: 5.46 | G24: 32.86 | H24: 23.42 | I24: 20.88 | J24: 21.15 | K24: 230.62
A25: Other Income | B25: 1.45 | C25: 1.59 | D25: 5.45 | E25: -12.24 | F25: 0.9 | G25: 5.71 | H25: 88.06 | I25: 76.45 | J25: 110.73 | K25: 76.93
A26: Depreciation | B26: 5.85 | C26: 8.69 | D26: 11.56 | E26: 18.13 | F26: 20.3 | G26: 20.56 | H26: 23.96 | I26: 37.99 | J26: 29.09 | K26: 38.83
A27: Interest | B27: 10.58 | C27: 20.32 | D27: 26.16 | E27: 31.43 | F27: 30.97 | G27: 37.99 | H27: 43.5 | I27: 51.76 | J27: 46.43 | K27: 24.78
A28: Profit before tax | B28: 43.53 | C28: 64.19 | D28: 29.59 | E28: 46.93 | F28: 70.9 | G28: 164.64 | H28: 227.59 | I28: 274.15 | J28: 363.46 | K28: 448.25
A29: Tax | B29: 8.38 | C29: 16.55 | D29: 10.2 | E29: 10.35 | F29: 14.08 | G29: 16.19 | H29: 23.5 | I29: 31.87 | J29: 50.56 | K29: 69.92
A30: Net profit | B30: 32.7 | C30: 44.09 | D30: 15.49 | E30: 33.18 | F30: 52.47 | G30: 139.39 | H30: 201.1 | I30: 239.19 | J30: 312.39 | K30: 378.8
A31: Dividend Amount | B31: 4.11 | C31: 4.81 | D31: 2.06 | E31: 4.83 | F31: 7.6 | G31: 20.72 | H31: 30.04 | I31: 35.91 | J31: 46.86
A40: Quarters
A41: Report Date | B41: 45291 | C41: 45382 | D41: 45473 | E41: 45565 | F41: 45657 | G41: 45747 | H41: 45838 | I41: 45930 | J41: 46022 | K41: 46112
A42: Sales | B42: 757.77 | C42: 863.41 | D42: 907.86 | E42: 927.42 | F42: 996.42 | G42: 1037.07 | H42: 1039.94 | I42: 1035.5 | J42: 1017.07 | K42: 1172.76
A43: Expenses | B43: 677.42 | C43: 791.25 | D43: 820.19 | E43: 863.93 | F43: 915.69 | G43: 944.88 | H43: 939.31 | I43: 933.49 | J43: 897.29 | K43: 1060.25
A44: Other Income | B44: 15.44 | C44: 24.89 | D44: 6.87 | E44: 40.36 | F44: 28.86 | G44: 35.75 | H44: 30.06 | I44: 26.32 | J44: 11.69 | K44: 8.86
A45: Depreciation | B45: 9.02 | C45: 12.48 | D45: 6.52 | E45: 7.18 | F45: 7.64 | G45: 7.75 | H45: 8.71 | I45: 9.23 | J45: 9.84 | K45: 11.05
A46: Interest | B46: 13 | C46: 12.35 | D46: 12.96 | E46: 11.95 | F46: 12.84 | G46: 5.62 | H46: 6.05 | I46: 7.82 | J46: 6.54 | K46: 4.37
A47: Profit before tax | B47: 73.77 | C47: 72.22 | D47: 75.06 | E47: 84.72 | F47: 89.11 | G47: 114.57 | H47: 115.93 | I47: 111.28 | J47: 115.09 | K47: 105.95
A48: Tax | B48: 12.3 | C48: 2.8 | D48: 7.06 | E48: 12.8 | F48: 11.05 | G48: 19.65 | H48: 22.87 | I48: 15.31 | J48: 17.6 | K48: 14.14
A49: Net profit | B49: 60.27 | C49: 68.98 | D49: 67.33 | E49: 72 | F49: 77.93 | G49: 95.13 | H49: 93.26 | I49: 95.99 | J49: 97.67 | K49: 91.88
A50: Operating Profit | B50: 80.35 | C50: 72.16 | D50: 87.67 | E50: 63.49 | F50: 80.73 | G50: 92.19 | H50: 100.63 | I50: 102.01 | J50: 119.78 | K50: 112.51
A55: BALANCE SHEET
A56: Report Date | B56: 42825 | C56: 43190 | D56: 43555 | E56: 43921 | F56: 44286 | G56: 44651 | H56: 45016 | I56: 45382 | J56: 45747 | K56: 46112
A57: Equity Share Capital | B57: 13.69 | C57: 13.74 | D57: 13.75 | E57: 13.81 | F57: 13.81 | G57: 13.81 | H57: 13.81 | I57: 13.81 | J57: 14.76 | K57: 14.76
A58: Reserves | B58: 136.45 | C58: 175.94 | D58: 185.57 | E58: 211.37 | F58: 255.12 | G58: 373.04 | H58: 575.12 | I58: 823.59 | J58: 2055.15 | K58: 2436.87
A59: Borrowings | B59: 165.63 | C59: 232.52 | D59: 250.28 | E59: 279.3 | F59: 261.09 | G59: 391.52 | H59: 347.72 | I59: 547.59 | J59: 285.95 | K59: 735.9
A60: Other Liabilities | B60: 39.39 | C60: 69.59 | D60: 122.93 | E60: 109.88 | F60: 196.31 | G60: 219.13 | H60: 268.25 | I60: 217.12 | J60: 158.86 | K60: 229.42
A61: Total | B61: 355.16 | C61: 491.79 | D61: 572.53 | E61: 614.36 | F61: 726.33 | G61: 997.5 | H61: 1204.9 | I61: 1602.11 | J61: 2514.72 | K61: 3416.95
A62: Net Block | B62: 68.09 | C62: 108.91 | D62: 136.52 | E62: 181.64 | F62: 172.37 | G62: 191.26 | H62: 273.32 | I62: 348.5 | J62: 435.71 | K62: 939.26
A63: Capital Work in Progress | B63: 32.44 | C63: 23.88 | D63: 46.22 | E63: 14.65 | F63: 13.49 | G63: 42.49 | H63: 45.5 | I63: 42.76 | J63: 39.29 | K63: 47.54
A64: Investments | B64: 0.04 | C64: 0.04 | D64: 0.02 | E64: 0.01 | H64: 1.11 | I64: 16.5 | J64: 527.94 | K64: 412.71
A65: Other Assets | B65: 254.59 | C65: 358.96 | D65: 389.77 | E65: 418.06 | F65: 540.47 | G65: 763.75 | H65: 884.97 | I65: 1194.35 | J65: 1511.78 | K65: 2017.44
A66: Total | B66: 355.16 | C66: 491.79 | D66: 572.53 | E66: 614.36 | F66: 726.33 | G66: 997.5 | H66: 1204.9 | I66: 1602.11 | J66: 2514.72 | K66: 3416.95
A67: Receivables | B67: 60.27 | C67: 113.15 | D67: 96.46 | E67: 67.53 | F67: 59.38 | G67: 109.65 | H67: 137.02 | I67: 264.33 | J67: 275.08 | K67: 430.92
A68: Inventory | B68: 109.37 | C68: 158.48 | D68: 182.61 | E68: 224.36 | F68: 357.7 | G68: 513.45 | H68: 596.47 | I68: 674.63 | J68: 616.8 | K68: 1023.27
A69: Cash & Bank | B69: 17.76 | C69: 16.58 | D69: 21.87 | E69: 20.32 | F69: 19.86 | G69: 32.52 | H69: 38.12 | I69: 98.78 | J69: 407.27 | K69: 201.81
A70: No. of Equity Shares | B70: 68467514 | C70: 68704614 | D70: 68746714 | E70: 69037914 | F70: 69037914 | G70: 69037914 | H70: 69037914 | I70: 69037914 | J70: 73808451
A71: New Bonus Shares
A72: Face value | B72: 2 | C72: 2 | D72: 2 | E72: 2 | F72: 2 | G72: 2 | H72: 2 | I72: 2 | J72: 2 | K72: 2
A80: CASH FLOW:
A81: Report Date | B81: 42825 | C81: 43190 | D81: 43555 | E81: 43921 | F81: 44286 | G81: 44651 | H81: 45016 | I81: 45382 | J81: 45747 | K81: 46112
A82: Cash from Operating Activity | B82: 1 | C82: -2.55 | D82: 89.02 | E82: 33.87 | F82: 76.51 | G82: 9.61 | H82: 199.66 | I82: 42.4 | J82: 282.18 | K82: 169.29
A83: Cash from Investing Activity | B83: -48.64 | C83: -41.92 | D83: -66.35 | E83: -14.3 | F83: -19.35 | G83: -69.45 | H83: -105.35 | I83: -157.81 | J83: -863.63 | K83: -363.89
A84: Cash from Financing Activity | B84: 49.36 | C84: 40.48 | D84: -16.66 | E84: -21.18 | F84: -56.51 | G84: 71.94 | H84: -87.36 | I84: 120.85 | J84: 640.25 | K84: 177.86
A85: Net Cash Flow | B85: 1.72 | C85: -3.99 | D85: 6.01 | E85: -1.61 | F85: 0.65 | G85: 12.1 | H85: 6.95 | I85: 5.44 | J85: 58.8 | K85: -16.74
A90: PRICE: | B90: 50.95 | C90: 155.85 | D90: 81.15 | E90: 33.45 | F90: 90.5 | G90: 317.75 | H90: 484.65 | I90: 998.75 | J90: 1831.95 | K90: 1318.1
A92: DERIVED:
A93: Adjusted Equity Shares in Cr | B93: 6.85 | C93: 6.87 | D93: 6.87 | E93: 6.9 | F93: 6.9 | G93: 6.9 | H93: 6.9 | I93: 6.9 | J93: 7.38 | K93: 7.38

Sheet Lookup
A1: Company Name | B1: CD_NSE Symbol | C1: Accord Code | D1: CD_Bloomberg Code | E1: CD_ISIN No
A2: 3I Infotech Ltd | B2: 3IINFOLTD | C2: 132628 | D2: III IN | E2: INE748C01038
A3: 3M India Ltd | B3: 3MINDIA | C3: 123395 | D3: 3M IN | E3: INE470A01017
A4: 5Paisa Capital Ltd | B4: 5PAISA | C4: 228972 | D4: 5PAISA IN | E4: INE618L01018
A5: 63 Moons Technologies Ltd | B5: 63MOONS | C5: 126881 | D5: 63MOONS IN | E5: INE111B01023
A6: Aarti Drugs Ltd | B6: AARTIDRUGS | C6: 124348 | D6: ARTD IN | E6: INE767A01016
A7: Aarti Industries Ltd | B7: AARTIIND | C7: 124208 | D7: ARTO IN | E7: INE769A01020
A8: Aarti Surfactants Ltd | B8: AARTISURF | C8: 299121 | D8: AARTISUR IN | E8: INE09EO01013
A9: Aavas Financiers Ltd | B9: AAVAS | C9: 267615 | D9: AAVAS IN | E9: INE216P01012
A10: ABB India Ltd | B10: ABB | C10: 100002 | D10: ABB IN | E10: INE117A01022
A11: Abbott India Ltd | B11: ABBOTINDIA | C11: 100488 | D11: BOOT IN | E11: INE358A01014
A12: ACC Ltd | B12: ACC | C12: 100410 | D12: ACC IN | E12: INE012A01025
A13: Accelya Solutions India Ltd | B13: ACCELYA | C13: 132268 | D13: ACCELYA IN | E13: INE793A01012
... A25: Aditya Birla Sun Life AMC Ltd | B25: ABSLAMC | C25: 209979 | D25: ABSLAMC IN | E25: INE404A01024
A26: Aditya Vision Ltd | C26: 283206 | D26: AVL IN | E26: INE679V01019
A27: Ador Welding Ltd | B27: ADORWELD | C27: 117041 | D27: AWL IN | E27: INE045A01017
A28: Advanced Enzyme Technologies Ltd | B28: ADVENZYMES | C28: 207679 | D28: ADVENZY IN | E28: INE837H01020
A29: Aegis Logistics Ltd | B29: AEGISCHEM | C29: 100003 | D29: AGIS IN | E29: INE208C01025
A30: Affle (India) Ltd | B30: AFFLE | C30: 229238 | D30: AFFLE IN | E30: INE00WC01027
A31: Agarwal Industrial Corporation Ltd | B31: AGARIND | C31: 131921 | D31: AGAR IN | E31: INE204E01012
A32: Agro Tech Foods Ltd | B32: ATFL | C32: 100215 | D32: ATFL IN | E32: INE209A01019
A33: Ahluwalia Contracts (India) Ltd | B33: AHLUCONT | C33: 132811 | D33: AHLU IN | E33: INE758C01029
A34: AIA Engineering Ltd | B34: AIAENG | C34: 132683 | D34: AIAE IN | E34: INE212H01026
A35: Ajanta Pharma Ltd | B35: AJANTPHARM | C35: 132331 | D35: AJP IN | E35: INE031B01049
A36: Ajmera Realty & Infra India Ltd | B36: AJMERA | C36: 113349 | D36: AREAL IN | E36: INE298G01027
A37: Akzo Nobel India Ltd | B37: AKZOINDIA | C37: 100710 | D37: AKZO IN | E37: INE133A01011
A38: Alembic Ltd | B38: ALEMBICLTD | C38: 106235 | D38: ALBC IN | E38: INE426A01027
... A51: AMI Organics Ltd | B51: AMIORG | C51: 232793 | D51: AMIORG IN | E51: INE00FF01017
A52: Amines & Plasticizers Ltd | C52: 106248 | D52: ANPL IN | E52: INE275D01022
A53: Amrutanjan Health Care Ltd | B53: AMRUTANJAN | C53: 190006 | D53: ARJN IN | E53: INE098F01031
A54: Anand Rathi Wealth Ltd | B54: ANANDRATHI | C54: 226156 | D54: ANANDRAT IN | E54: INE463V01026
A55: Anant Raj Ltd | B55: ANANTRAJ | C55: 115055 | D55: ARCP IN | E55: INE242C01024
A56: Andhra Paper Ltd | B56: ANDHRAPAP | C56: 102330 | D56: ANHPR IN | E56: INE435A01028
A57: Andhra Petrochemicals Ltd | B57: ANDHRAPET | C57: 100012 | D57: ANDP IN | E57: INE714B01016
A58: Andrew Yule & Company Ltd | B58: ANDREWYU | C58: 126173 | D58: ANY IN | E58: INE449C01025
A59: Angel One Ltd | B59: ANGELONE | C59: 209902 | D59: ANGELONE IN | E59: INE732I01013
A60: Anjani Portland Cement Ltd | B60: APCL | C60: 118091 | D60: SHZC IN | E60: INE071F01012
A61: Antony Waste Handling Cell Ltd | B61: AWHCL | C61: 277374 | D61: AWHCL IN | E61: INE01BK01022
A62: Anuh Pharma Ltd | C62: 106260 | D62: ANUH IN | E62: INE489G01022
A63: Anupam Rasayan India Ltd | B63: ANURAS | C63: 226328 | D63: ANURAS IN | E63: INE930P01018
A64: Apar Industries Ltd | B64: APARINDS | C64: 132259 | D64: APR IN | E64: INE372A01015
A65: Apcotex Industries Ltd | B65: APCOTEXIND | C65: 123694 | D65: APCO IN | E65: INE116A01032
A66: Apex Frozen Foods Ltd | B66: APEX | C66: 285359 | D66: APEX IN | E66: INE346W01013
A67: APL Apollo Tubes Ltd | B67: APLAPOLLO | C67: 190059 | D67: APAT IN | E67: INE702C01027
A68: Apollo Hospitals Enterprise Ltd | B68: APOLLOHOSP | C68: 108869 | D68: APHS IN | E68: INE437A01024
A69: Apollo Pipes Ltd | B69: APOLLOPIPE | C69: 131761 | D69: APOLP IN | E69: INE126J01016
A70: Apollo Tricoat Tubes Ltd | C70: 267529 | D70: APOLTRI IN | E70: INE919P01029
A71: Apollo Tyres Ltd | B71: APOLLOTYRE | C71: 100877 | D71: APTY IN | E71: INE438A01022
A72: Aptech Ltd | B72: APTECHT | C72: 132475 | D72: APTR IN | E72: INE266F01018
A73: Aptus Value Housing Finance India Ltd | B73: APTUS | C73: 251791 | D73: APTUS IN | E73: INE852O01025
A74: Arihant Superstructures Ltd | B74: ARIHANTSUP | C74: 106194 | D74: ARSU IN | E74: INE643K01018
A75: Arman Financial Services Ltd | B75: ARMANFIN | C75: 131179 | D75: ARLF IN | E75: INE109C01017
A76: Arshiya Ltd | B76: ARSHIYA | C76: 106074 | D76: ARSL IN | E76: INE968D01022
A77: Artemis Medicare Services Ltd | B77: ARTEMISMED | C77: 236257 | D77: ARTMSL IN | E77: INE025R01021
A78: Arvind Fashions Ltd | B78: ARVINDFASN | C78: 293665 | D78: ARVINDFA IN | E78: INE955V01021
A79: Arvind Ltd | B79: ARVIND | C79: 100101 | D79: ARVND IN | E79: INE034A01011
A80: Arvind Smartspaces Ltd | B80: ARVSMART | C80: 228011 | D80: ARIL IN | E80: INE034S01021
A81: Asahi India Glass Ltd | B81: ASAHIINDIA | C81: 115030 | D81: AISG IN | E81: INE439A01020
A82: Ashapura Minechem Ltd | B82: ASHAPURMIN | C82: 127001 | D82: ASMN IN | E82: INE348A01023
... A88: Asian Paints Ltd | B88: ASIANPAINT | C88: 100820 | D88: APNT IN | E88: INE021A01026
A89: Asian Star Company Ltd | C89: 131847 | D89: ASN IN | E89: INE194D01017
A90: ASM Technologies Ltd | C90: 126433 | D90: ASM IN | E90: INE867C01010
A91: Associated Alcohols & Breweries Ltd | B91: ASALCBR | C91: 107526 | D91: AAB IN | E91: INE073G01016
A92: Astec Lifesciences Ltd | B92: ASTEC | C92: 212609 | D92: ASTEL IN | E92: INE563J01010
A93: Aster DM Healthcare Ltd | B93: ASTERDM | C93: 221033 | D93: ASTERDM IN | E93: INE914M01019
A94: Astra Microwave Products Ltd | B94: ASTRAMICRO | C94: 132493 | D94: ASTM IN | E94: INE386C01029
A95: Astral Ltd | B95: ASTRAL | C95: 132830 | D95: ASTRA IN | E95: INE006I01046
A96: Astrazeneca Pharma India Ltd | B96: ASTRAZEN | C96: 106820 | D96: ASTR IN | E96: INE203A01020
A97: Atul Ltd | B97: ATUL | C97: 100027 | D97: ATLP IN | E97: INE100A01010
A98: AU Small Finance Bank Ltd | B98: AUBANK | C98: 286335 | D98: AUBANK IN | E98: INE949L01017
A99: Aurionpro Solutions Ltd | B99: AURIONPRO | C99: 132668 | D99: AUPS IN | E99: INE132H01018
A100: Aurobindo Pharma Ltd | B100: AUROPHARMA | C100: 124804 | D100: ARBP IN | E100: INE406A01037
A101: Authum Investment & Infrastructure Ltd | C101: 243036 | D101: AUIN IN | E101: INE206F01022
A102: Automobile Corporation of Goa Ltd | B102: AUTOCORP | C102: 105036 | D102: ACGL IN | E102: INE451C01013
A103: Automotive Axles Ltd | B103: AUTOAXLES | C103: 105010 | D103: ATXL IN | E103: INE449A01011
A104: Automotive Stampings and Assemblies Ltd | B104: ASAL | C104: 120119 | D104: ATSA IN | E104: INE900C01027
A105: Avadh Sugar & Energy Ltd | B105: AVADHSUGAR | C105: 286952 | D105: AVADHSUG IN | E105: INE349W01017
A106: Avanti Feeds Ltd | B106: AVANTIFEED | C106: 112573 | D106: AVNT IN | E106: INE871C01038
A107: Avenue Supermarts Ltd | B107: DMART | C107: 223595 | D107: DMART IN | E107: INE192R01011
A108: AVT Natural Products Ltd | B108: AVTNPL | C108: 119105 | D108: AVTH IN | E108: INE488D01021
A109: Axis Bank Ltd | B109: AXISBANK | C109: 132215 | D109: AXSB IN | E109: INE238A01034
A110: Axtel Industries Ltd | C110: 123850 | D110: ADVX IN | E110: INE767C01012
A111: BLKashyap and Sons Ltd | B111: BLKASHYAP | C111: 132719 | D111: KASH IN | E111: INE350H01032
A112: Bajaj Auto Ltd | B112: BAJAJ-AUTO | C112: 200132 | D112: BJAUT IN | E112: INE917I01010
A113: Bajaj Consumer Care Ltd | B113: BAJAJCON | C113: 220519 | D113: BAJAJCON IN | E113: INE933K01021
A114: Bajaj Electricals Ltd | B114: BAJAJELEC | C114: 100031 | D114: BJE IN | E114: INE193E01025
A115: Bajaj Finance Ltd | B115: BAJFINANCE | C115: 100034 | D115: BAF IN | E115: INE296A01024
A116: Bajaj Finserv Ltd | B116: BAJAJFINSV | C116: 205198 | D116: BJFIN IN | E116: INE918I01018
A117: Bajaj Healthcare Ltd | B117: BAJAJHCARE | C117: 212661 | D117: BAJAJHEA IN | E117: INE411U01027
A118: Bajaj Hindusthan Sugar Ltd | B118: BAJAJHIND | C118: 100032 | D118: BJH IN | E118: INE306A01021
A119: Bajaj Holdings & Investment Ltd | B119: BAJAJHLDNG | C119: 100490 | D119: BJHI IN | E119: INE118A01012
A120: Balaji Amines Ltd | B120: BALAMINES | C120: 130999 | D120: BLA IN | E120: INE050E01027
A121: Balaji Telefilms Ltd | B121: BALAJITELE | C121: 132382 | D121: BLJT IN | E121: INE794B01026
A122: Balkrishna Industries Ltd | B122: BALKRISIND | C122: 102355 | D122: BIL IN | E122: INE787D01026
A123: Balmer Lawrie & Company Ltd | B123: BALMLAWRIE | C123: 123319 | D123: BLCL IN | E123: INE164A01016
A124: Balmer Lawrie Investments Ltd | C124: 132485 | D124: BALM IN | E124: INE525F01017
A125: Balrampur Chini Mills Ltd | B125: BALRAMCHIN | C125: 100038 | D125: BRCM IN | E125: INE119A01028
A126: Balu Forge Industries Ltd | C126: 131112 | D126: BLAM IN | E126: INE011E01029
A127: Banco Products (India) Ltd | B127: BANCOINDIA | C127: 100039 | D127: BNCO IN | E127: INE213C01025
A128: Bandhan Bank Ltd | B128: BANDHANBNK | C128: 279527 | D128: BANDHAN IN | E128: INE545U01014
...

Sheet Cover
A1: GRAVITA INDIA LTD
A2: Metal & Metal Products | TIKONA CAPITAL
A4: CMP (₹) | B4: 1777
A5: Target (₹) | B5: 2380
A6: Upside | B6: 33.9%
A7: Rating | B7: BUY
A8: Market Cap (₹ Cr) | B8: 13112.41
A9: Shares (Cr) | B9: 7.38
A10: Base Year | B10: FY26
A12: RATING: BUY | Target: ₹2,380 | Upside: 33.9%
A14: Gravita is poised to benefit from India's circular economy push and regulatory tailwinds in battery recycling. The company's capacity doubling to 7 lakh MTPA by FY28, diversification into lithium-ion and rubber recycling, and improving domestic scrap availability provide strong growth visibility. Management's Vision 2029 targets 25%+ volume CAGR with expanding non-lead contribution create multiple re-rating catalysts.
A19: KEY CATALYSTS
A20: • Completion of 1.25 lakh MTPA lead capacity by Q4 FY26
A21: • Lithium-ion battery recycling plant commissioning at Mundra
A22: • Copper recycling plant setup at Mandvi, Gujarat (29,400 MTPA)
A23: • RMIL acquisition synergies and integration completion
A25: KEY RISKS
A26: • Regulatory delays in capacity expansion approvals
A27: • Raw material scrap availability fluctuations
A28: • Commodity price volatility affecting margins
A29: • New vertical execution and scaling risks
A31: SAARTHI SCORE: 78.0/100 → BUY

Sheet Assumptions
A1: Particulars | B1: FY21A | C1: FY22A | D1: FY23A | E1: FY24A | F1: FY25A | G1: FY26A | H1: FY27E | I1: FY28E | J1: FY29E | K1: FY30E | L1: FY31E
A2: Revenue Growth % | H2: 16.5 | I2: 22 | J2: 18.5 | K2: 15.2 | L2: 12.8
A3: RM % of Revenue | H3: 83.2 | I3: 82.5 | J3: 81.8 | K3: 81.2 | L3: 80.8
A4: Employee % of Revenue | H4: 4.1 | I4: 3.9 | J4: 3.8 | K4: 3.7 | L4: 3.6
A5: Power & Fuel % | H5: 0.9 | I5: 0.8 | J5: 0.8 | K5: 0.8 | L5: 0.7
A6: Other Mfg % | H6: 2.1 | I6: 2 | J6: 1.9 | K6: 1.8 | L6: 1.8
A7: Selling & Admin % | H7: 1 | I7: 1 | J7: 1 | K7: 1 | L7: 1
A8: Other Expenses % | H8: 1.2 | I8: 1.1 | J8: 1 | K8: 0.9 | L8: 0.9
A9: Chg in Inventory % | H9: 3.8 | I9: 4.2 | J9: 3.5 | K9: 3.2 | L9: 2.8
A10: Depreciation (₹ Cr) | H10: 58 | I10: 78 | J10: 105 | K10: 128 | L10: 148
A11: Interest (₹ Cr) | H11: 32 | I11: 45 | J11: 52 | K11: 58 | L11: 62
A12: Other Income (₹ Cr) | H12: 95 | I12: 118 | J12: 142 | K12: 165 | L12: 185
A13: Tax Rate % | H13: 15.8 | I13: 16.2 | J13: 16.5 | K13: 17 | L13: 17.5
... A16: Inventory Days | H16: 82 | I16: 78 | J16: 75 | K16: 72 | L16: 70
A18: VALUATION ASSUMPTIONS
A19: WACC % | B19: 11.8
A20: Terminal Growth % | B20: 4.2
A21: Target PE (x) | B21: 28.5
A22: Target EV/EBITDA (x) | B22: 18.2
A23: Dividend Payout % | B23: 15
A25: RATIONALE
A26: Growth driven by 7 lakh MTPA capacity by FY28, new verticals (lithium-ion, rubber, copper), improving domestic scrap availability, and rising non-lead contribution to 30% by FY29. Management targets 25%+ volume CAGR and 35%+ profit growth backed by Rs1,225cr capex.

Sheet P&L
A1: All figures in ₹ Cr
A2: Particulars | B2: FY21A | C2: FY22A | D2: FY23A | E2: FY24A | F2: FY25A | G2: FY26A | H2: FY27E | I2: FY28E | J2: FY29E | K2: FY30E | L2: FY31E
A3: Revenue | B3: ='Data Sheet'!F17 | C3: ='Data Sheet'!G17 | D3: ='Data Sheet'!H17 | E3: ='Data Sheet'!I17 | F3: ='Data Sheet'!J17 | G3: ='Data Sheet'!K17 | H3: =G3*(1+'Assumptions'!H2/100) | I3: =H3*(1+'Assumptions'!I2/100) | J3: =I3*(1+'Assumptions'!J2/100) | K3: =J3*(1+'Assumptions'!K2/100) | L3: =K3*(1+'Assumptions'!L2/100)
A4: Raw Material Cost | B4: ='Data Sheet'!F18 | C4: ='Data Sheet'!G18 | D4: ='Data Sheet'!H18 | E4: ='Data Sheet'!I18 | F4: ='Data Sheet'!J18 | G4: ='Data Sheet'!K18 | H4: =H3*'Assumptions'!H3/100 | I4: =I3*'Assumptions'!I3/100 | J4: =J3*'Assumptions'!J3/100 | K4: =K3*'Assumptions'!K3/100 | L4: =L3*'Assumptions'!L3/100
A5: Chg in Inventory | B5: ='Data Sheet'!F19 | C5: ='Data Sheet'!G19 | D5: ='Data Sheet'!H19 | E5: ='Data Sheet'!I19 | F5: ='Data Sheet'!J19 | G5: ='Data Sheet'!K19 | H5: =H3*'Assumptions'!H9/100 | I5: =I3*'Assumptions'!I9/100 | J5: =J3*'Assumptions'!J9/100 | K5: =K3*'Assumptions'!K9/100 | L5: =L3*'Assumptions'!L9/100
A6: Employee Cost | B6: ='Data Sheet'!F22 | C6: ='Data Sheet'!G22 | D6: ='Data Sheet'!H22 | E6: ='Data Sheet'!I22 | F6: ='Data Sheet'!J22 | G6: ='Data Sheet'!K22 | H6: =H3*'Assumptions'!H4/100 | I6: =I3*'Assumptions'!I4/100 | J6: =J3*'Assumptions'!J4/100 | K6: =K3*'Assumptions'!K4/100 | L6: =L3*'Assumptions'!L4/100
A7: Power & Fuel | B7: ='Data Sheet'!F20 | C7: ='Data Sheet'!G20 | D7: ='Data Sheet'!H20 | E7: ='Data Sheet'!I20 | F7: ='Data Sheet'!J20 | G7: ='Data Sheet'!K20 | H7: =H3*'Assumptions'!H5/100 | I7: =I3*'Assumptions'!I5/100 | J7: =J3*'Assumptions'!J5/100 | K7: =K3*'Assumptions'!K5/100 | L7: =L3*'Assumptions'!L5/100
A8: Other Mfg Exp | B8: ='Data Sheet'!F21 | C8: ='Data Sheet'!G21 | D8: ='Data Sheet'!H21 | E8: ='Data Sheet'!I21 | F8: ='Data Sheet'!J21 | G8: ='Data Sheet'!K21 | H8: =H3*'Assumptions'!H6/100 | I8: =I3*'Assumptions'!I6/100 | J8: =J3*'Assumptions'!J6/100 | K8: =K3*'Assumptions'!K6/100 | L8: =L3*'Assumptions'!L6/100
A9: Selling & Admin | B9: ='Data Sheet'!F23 | C9: ='Data Sheet'!G23 | D9: ='Data Sheet'!H23 | E9: ='Data Sheet'!I23 | F9: ='Data Sheet'!J23 | G9: ='Data Sheet'!K23 | H9: =H3*'Assumptions'!H7/100 | I9: =I3*'Assumptions'!I7/100 | J9: =J3*'Assumptions'!J7/100 | K9: =K3*'Assumptions'!K7/100 | L9: =L3*'Assumptions'!L7/100
A10: Other Expenses | B10: ='Data Sheet'!F24 | C10: ='Data Sheet'!G24 | D10: ='Data Sheet'!H24 | E10: ='Data Sheet'!I24 | F10: ='Data Sheet'!J24 | G10: ='Data Sheet'!K24 | H10: =H3*'Assumptions'!H8/100 | I10: =I3*'Assumptions'!I8/100 | J10: =J3*'Assumptions'!J8/100 | K10: =K3*'Assumptions'!K8/100 | L10: =L3*'Assumptions'!L8/100
A11: Total Expenses | B11: =SUM(B4:B10) | C11: =SUM(C4:C10) | D11: =SUM(D4:D10) | E11: =SUM(E4:E10) | F11: =SUM(F4:F10) | G11: =SUM(G4:G10) | H11: =SUM(H4:H10) | I11: =SUM(I4:I10) | ... L11: =SUM(L4:L10)
A12: EBITDA | B12: =B3-B11 | C12: =C3-C11 | D12: =D3-D11 | E12: =E3-E11 | F12: =F3-F11 | G12: =G3-G11 | H12: =H3-H11 | I12: =I3-I11 | ... L12: =L3-L11
A13: EBITDA Margin % | B13: =IF(B3=0,0,B12/B3) | C13: =IF(C3=0,0,C12/C3) | D13: =IF(D3=0,0,D12/D3) | E13: =IF(E3=0,0,E12/E3) | F13: =IF(F3=0,0,F12/F3) | G13: =IF(G3=0,0,G12/G3) | H13: =IF(H3=0,0,H12/H3) | I13: =IF(I3=0,0,I12/I3) | ... L13: =IF(L3=0,0,L12/L3)
A14: Other Income | B14: ='Data Sheet'!F25 | C14: ='Data Sheet'!G25 | D14: ='Data Sheet'!H25 | E14: ='Data Sheet'!I25 | F14: ='Data Sheet'!J25 | G14: ='Data Sheet'!K25 | H14: ='Assumptions'!H12 | I14: ='Assumptions'!I12 | J14: ='Assumptions'!J12 | K14: ='Assumptions'!K12 | L14: ='Assumptions'!L12
A15: Depreciation | B15: ='Data Sheet'!F26 | C15: ='Data Sheet'!G26 | D15: ='Data Sheet'!H26 | E15: ='Data Sheet'!I26 | F15: ='Data Sheet'!J26 | G15: ='Data Sheet'!K26 | H15: ='Assumptions'!H10 | I15: ='Assumptions'!I10 | J15: ='Assumptions'!J10 | K15: ='Assumptions'!K10 | L15: ='Assumptions'!L10
A16: EBIT | B16: =B12+B14-B15 | C16: =C12+C14-C15 | D16: =D12+D14-D15 | E16: =E12+E14-E15 | F16: =F12+F14-F15 | G16: =G12+G14-G15 | H16: =H12+H14-H15 | I16: =I12+I14-I15 | ... L16: =L12+L14-L15
A17: Finance Cost | B17: ='Data Sheet'!F27 | C17: ='Data Sheet'!G27 | D17: ='Data Sheet'!H27 | E17: ='Data Sheet'!I27 | F17: ='Data Sheet'!J27 | G17: ='Data Sheet'!K27 | H17: ='Assumptions'!H11 | I17: ='Assumptions'!I11 | J17: ='Assumptions'!J11 | K17: ='Assumptions'!K11 | L17: ='Assumptions'!L11
A18: Profit Before Tax | B18: =B16-B17 | C18: =C16-C17 | D18: =D16-D17 | E18: =E16-E17 | F18: =F16-F17 | G18: =G16-G17 | H18: =H16-H17 | I18: =I16-I17 | ... L18: =L16-L17
A19: Tax | B19: ='Data Sheet'!F29 | C19: ='Data Sheet'!G29 | D19: ='Data Sheet'!H29 | E19: ='Data Sheet'!I29 | F19: ='Data Sheet'!J29 | G19: ='Data Sheet'!K29 | H19: =MAX(0,H18*'Assumptions'!H13/100) | I19: =MAX(0,I18*'Assumptions'!I13/100) | J19: =MAX(0,J18*'Assumptions'!J13/100) | K19: =MAX(0,K18*'Assumptions'!K13/100) | L19: =MAX(0,L18*'Assumptions'!L13/100)
A20: Profit After Tax (PAT) | B20: =B18-B19 | C20: =C18-C19 | D20: =D18-D19 | E20: =E18-E19 | F20: =F18-F19 | G20: =G18-G19 | H20: =H18-H19 | I20: =I18-I19 | ... L20: =L18-L19
A21: PAT Margin % | B21: =IF(B3=0,0,B20/B3) | C21: =IF(C3=0,0,C20/C3) | D21: =IF(D3=0,0,D20/D3) | E21: =IF(E3=0,0,E20/E3) | F21: =IF(F3=0,0,F20/F3) | G21: =IF(G3=0,0,G20/G3) | H21: =IF(H3=0,0,H20/H3) | I21: =IF(I3=0,0,I20/I3) | ... L21: =IF(L3=0,0,L20/L3)
A22: PAT Growth % | C22: =IF(B20<=0,0,(C20/B20)-1) | D22: =IF(C20<=0,0,(D20/C20)-1) | E22: =IF(D20<=0,0,(E20/D20)-1) | F22: =IF(E20<=0,0,(F20/E20)-1) | G22: =IF(F20<=0,0,(G20/F20)-1) | H22: =IF(G20<=0,0,(H20/G20)-1) | I22: =IF(H20<=0,0,(I20/H20)-1) | J22: =IF(I20<=0,0,(J20/I20)-1) | ... L22: =IF(K20<=0,0,(L20/K20)-1)
A23: EPS (₹) | B23: =B20/7.38 | C23: =C20/7.38 | D23: =D20/7.38 | E23: =E20/7.38 | F23: =F20/7.38 | G23: =G20/7.38 | H23: =H20/7.38 | I23: =I20/7.38 | ... L23: =L20/7.38

Sheet Balance Sheet
A1: All figures in ₹ Cr
A2: Particulars | B2: FY21A | C2: FY22A | D2: FY23A | E2: FY24A | F2: FY25A | G2: FY26A | H2: FY27E | I2: FY28E | J2: FY29E | K2: FY30E | L2: FY31E
A3: Share Capital | B3: ='Data Sheet'!F57 | C3: ='Data Sheet'!G57 | D3: ='Data Sheet'!H57 | E3: ='Data Sheet'!I57 | F3: ='Data Sheet'!J57 | G3: ='Data Sheet'!K57 | H3: 15 | I3: 15 | J3: 15 | K3: 15 | L3: 15
A4: Reserves | B4: ='Data Sheet'!F58 | C4: ='Data Sheet'!G58 | D4: ='Data Sheet'!H58 | E4: ='Data Sheet'!I58 | F4: ='Data Sheet'!J58 | G4: ='Data Sheet'!K58 | H4: 2858 | I4: 3485 | J4: 4295 | K4: 5187 | L4: 6145
A5: Total Equity | B5: =B3+B4 | C5: =C3+C4 | D5: =D3+D4 | E5: =E3+E4 | F5: =F3+F4 | G5: =G3+G4 | H5: =H3+H4 | I5: =I3+I4 | ... L5: =L3+L4
A6: Borrowings | B6: ='Data Sheet'!F59 | C6: ='Data Sheet'!G59 | D6: ='Data Sheet'!H59 | E6: ='Data Sheet'!I59 | F6: ='Data Sheet'!J59 | G6: ='Data Sheet'!K59 | H6: 920 | I6: 1285 | J6: 1450 | K6: 1520 | L6: 1580
A7: Other Liabilities | B7: ='Data Sheet'!F60 | C7: ='Data Sheet'!G60 | D7: ='Data Sheet'!H60 | E7: ='Data Sheet'!I60 | F7: ='Data Sheet'!J60 | G7: ='Data Sheet'!K60 | H7: 285 | I7: 365 | J7: 425 | K7: 485 | L7: 535
A8: Total Liabilities & Equity | B8: =B5+B6+B7 | C8: =C5+C6+C7 | D8: =D5+D6+D7 | E8: =E5+E6+E7 | F8: =F5+F6+F7 | G8: =G5+G6+G7 | H8: =H5+H6+H7 | I8: =I5+I6+I7 | ... L8: =L5+L6+L7
A10: APPLICATION OF FUNDS
A11: Net Block | B11: ='Data Sheet'!F62 | C11: ='Data Sheet'!G62 | D11: ='Data Sheet'!H62 | E11: ='Data Sheet'!I62 | F11: ='Data Sheet'!J62 | G11: ='Data Sheet'!K62 | H11: 1285 | I11: 1840 | J11: 2185 | K11: 2377 | L11: 2509
A12: CWIP | B12: ='Data Sheet'!F63 | C12: ='Data Sheet'!G63 | D12: ='Data Sheet'!H63 | E12: ='Data Sheet'!I63 | F12: ='Data Sheet'!J63 | G12: ='Data Sheet'!K63 | H12: 62 | I12: 85 | J12: 95 | K12: 72 | L12: 58
A13: Investments | B13: ='Data Sheet'!F64 | C13: ='Data Sheet'!G64 | D13: ='Data Sheet'!H64 | E13: ='Data Sheet'!I64 | F13: ='Data Sheet'!J64 | G13: ='Data Sheet'!K64 | H13: 450 | I13: 520 | J13: 610 | K13: 725 | L13: 820
A14: Trade Receivables | B14: ='Data Sheet'!F67 | C14: ='Data Sheet'!G67 | D14: ='Data Sheet'!H67 | E14: ='Data Sheet'!I67 | F14: ='Data Sheet'!J67 | G14: ='Data Sheet'!K67 | H14: ='P&L'!H3*'Assumptions'!H15/365 | I14: ='P&L'!I3*'Assumptions'!I15/365 | J14: ='P&L'!J3*'Assumptions'!J15/365 | K14: ='P&L'!K3*'Assumptions'!K15/365 | L14: ='P&L'!L3*'Assumptions'!L15/365
A15: Inventory | B15: ='Data Sheet'!F68 | C15: ='Data Sheet'!G68 | D15: ='Data Sheet'!H68 | E15: ='Data Sheet'!I68 | F15: ='Data Sheet'!J68 | G15: ='Data Sheet'!K68 | H15: ='P&L'!H4*'Assumptions'!H16/365 | I15: ='P&L'!I4*'Assumptions'!I16/365 | J15: ='P&L'!J4*'Assumptions'!J16/365 | K15: ='P&L'!K4*'Assumptions'!K16/365 | L15: ='P&L'!L4*'Assumptions'!L16/365
A16: Cash & Bank (Plug) | B16: ='Data Sheet'!F69 | C16: ='Data Sheet'!G69 | D16: ='Data Sheet'!H69 | E16: ='Data Sheet'!I69 | F16: ='Data Sheet'!J69 | G16: ='Data Sheet'!K69 | H16: =H8-H11+H12+H13+H14+H15-H17 | I16: =I8-I11+I12+I13+I14+I15-I17 | J16: =J8-J11+J12+J13+J14+J15-J17 | K16: =K8-K11+K12+K13+K14+K15-K17 | L16: =L8-L11+L12+L13+L14+L15-L17
A17: Other Assets | B17: ='Data Sheet'!F65-'Data Sheet'!F67-'Data Sheet'!F68-'Data Sheet'!F69 | C17: ='Data Sheet'!G65-'Data Sheet'!G67-'Data Sheet'!G68-'Data Sheet'!G69 | D17: ='Data Sheet'!H65-'Data Sheet'!H67-'Data Sheet'!H68-'Data Sheet'!H69 | E17: ='Data Sheet'!I65-'Data Sheet'!I67-'Data Sheet'!I68-'Data Sheet'!I69 | F17: ='Data Sheet'!J65-'Data Sheet'!J67-'Data Sheet'!J68-'Data Sheet'!J69 | G17: ='Data Sheet'!K65-'Data Sheet'!K67-'Data Sheet'!K68-'Data Sheet'!K69 | H17: 2580 | I17: 3420 | J17: 4280 | K17: 5050 | L17: 5720
A18: Total Assets | B18: =B11+B12+B13+B14+B15+B16+B17 | C18: =C11+C12+C13+C14+C15+C16+C17 | D18: =D11+D12+D13+D14+D15+D16+D17 | E18: =E11+E12+E13+E14+E15+E16+E17 | F18: =F11+F12+F13+F14+F15+F16+F17 | G18: =G11+G12+G13+G14+G15+G16+G17 | H18: =H11+H12+H13+H14+H15+H16+H17 | I18: =I11+I12+I13+I14+I15+I16+I17 | ... L18: =L11+L12+L13+L14+L15+L16+L17
A19: CHECK (TA - TL&E = 0) | B19: =B18-B8 | C19: =C18-C8 | D19: =D18-D8 | E19: =E18-E8 | F19: =F18-F8 | G19: =G18-G8 | H19: =H18-H8 | I19: =I18-I8 | ... L19: =L18-L8

Sheet Cash Flow
A2: Particulars | B2: FY21A | C2: FY22A | D2: FY23A | E2: FY24A | F2: FY25A | G2: FY26A | H2: FY27E | I2: FY28E | J2: FY29E | K2: FY30E | L2: FY31E
A3: CFO | B3: ='Data Sheet'!F82 | C3: ='Data Sheet'!G82 | D3: ='Data Sheet'!H82 | E3: ='Data Sheet'!I82 | F3: ='Data Sheet'!J82 | G3: ='Data Sheet'!K82 | H3: 485 | I3: 625 | J3: 785 | K3: 920 | L3: 1048
A4: CFI | B4: ='Data Sheet'!F83 | C4: ='Data Sheet'!G83 | D4: ='Data Sheet'!H83 | E4: ='Data Sheet'!I83 | F4: ='Data Sheet'!J83 | G4: ='Data Sheet'!K83 | H4: -365 | I4: -612 | J4: -435 | K4: -308 | L4: -268
A5: CFF | B5: ='Data Sheet'!F84 | C5: ='Data Sheet'!G84 | D5: ='Data Sheet'!H84 | E5: ='Data Sheet'!I84 | F5: ='Data Sheet'!J84 | G5: ='Data Sheet'!K84 | H5: 125 | I5: 215 | J5: -85 | K5: -125 | L5: -165
A6: Net Cash Flow | B6: ='Data Sheet'!F85 | C6: ='Data Sheet'!G85 | D6: ='Data Sheet'!H85 | E6: ='Data Sheet'!I85 | F6: ='Data Sheet'!J85 | G6: ='Data Sheet'!K85 | H6: =H3+H4+H5 | I6: =I3+I4+I5 | J6: =J3+J4+J5 | K6: =K3+K4+K5 | L6: =L3+L4+L5
A8: Free Cash Flow (FCF) | B8: =B3+B4 | C8: =C3+C4 | D8: =D3+D4 | E8: =E3+E4 | F8: =F3+F4 | G8: =G3+G4 | H8: =H3+H4 | I8: =I3+I4 | ... L8: =L3+L4

Sheet Ratios
A1: Key Financial Ratios
A2: Particulars | B2: FY21A | C2: FY22A | D2: FY23A | E2: FY24A | F2: FY25A | G2: FY26A | H2: FY27E | I2: FY28E | J2: FY29E | K2: FY30E | L2: FY31E
A3: EBITDA Margin % | B3: =IF('P&L'!B3=0,0,'P&L'!B12/'P&L'!B3) | C3: =IF('P&L'!C3=0,0,'P&L'!C12/'P&L'!C3) | D3: =IF('P&L'!D3=0,0,'P&L'!D12/'P&L'!D3) | E3: =IF('P&L'!E3=0,0,'P&L'!E12/'P&L'!E3) | F3: =IF('P&L'!F3=0,0,'P&L'!F12/'P&L'!F3) | G3: =IF('P&L'!G3=0,0,'P&L'!G12/'P&L'!G3) | H3: =IF('P&L'!H3=0,0,'P&L'!H12/'P&L'!H3) | I3: =IF('P&L'!I3=0,0,'P&L'!I12/'P&L'!I3) | ... L3: =IF('P&L'!L3=0,0,'P&L'!L12/'P&L'!L3)
A4: PAT Margin % | B4: =IF('P&L'!B3=0,0,'P&L'!B20/'P&L'!B3) | C4: =IF('P&L'!C3=0,0,'P&L'!C20/'P&L'!C3) | D4: =IF('P&L'!D3=0,0,'P&L'!D20/'P&L'!D3) | E4: =IF('P&L'!E3=0,0,'P&L'!E20/'P&L'!E3) | F4: =IF('P&L'!F3=0,0,'P&L'!F20/'P&L'!F3) | G4: =IF('P&L'!G3=0,0,'P&L'!G20/'P&L'!G3) | H4: =IF('P&L'!H3=0,0,'P&L'!H20/'P&L'!H3) | I4: =IF('P&L'!I3=0,0,'P&L'!I20/'P&L'!I3) | ... L4: =IF('P&L'!L3=0,0,'P&L'!L20/'P&L'!L3)
A5: ROE % | B5: =IF('Balance Sheet'!B5=0,0,'P&L'!B20/'Balance Sheet'!B5) | C5: =IF('Balance Sheet'!C5=0,0,'P&L'!C20/'Balance Sheet'!C5) | D5: =IF('Balance Sheet'!D5=0,0,'P&L'!D20/'Balance Sheet'!D5) | E5: =IF('Balance Sheet'!E5=0,0,'P&L'!E20/'Balance Sheet'!E5) | F5: =IF('Balance Sheet'!F5=0,0,'P&L'!F20/'Balance Sheet'!F5) | G5: =IF('Balance Sheet'!G5=0,0,'P&L'!G20/'Balance Sheet'!G5) | H5: =IF('Balance Sheet'!H5=0,0,'P&L'!H20/'Balance Sheet'!H5) | I5: =IF('Balance Sheet'!I5=0,0,'P&L'!I20/'Balance Sheet'!I5) | ... L5: =IF('Balance Sheet'!L5=0,0,'P&L'!L20/'Balance Sheet'!L5)
A6: ROCE % | B6: =IF(('Balance Sheet'!B5+'Balance Sheet'!B6)=0,0,'P&L'!B16/('Balance Sheet'!B5+'Balance Sheet'!B6)) | C6: =IF(('Balance Sheet'!C5+'Balance Sheet'!C6)=0,0,'P&L'!C16/('Balance Sheet'!C5+'Balance Sheet'!C6)) | D6: =IF(('Balance Sheet'!D5+'Balance Sheet'!D6)=0,0,'P&L'!D16/('Balance Sheet'!D5+'Balance Sheet'!D6)) | E6: =IF(('Balance Sheet'!E5+'Balance Sheet'!E6)=0,0,'P&L'!E16/('Balance Sheet'!E5+'Balance Sheet'!E6)) | F6: =IF(('Balance Sheet'!F5+'Balance Sheet'!F6)=0,0,'P&L'!F16/('Balance Sheet'!F5+'Balance Sheet'!F6)) | G6: =IF(('Balance Sheet'!G5+'Balance Sheet'!G6)=0,0,'P&L'!G16/('Balance Sheet'!G5+'Balance Sheet'!G6)) | H6: =IF(('Balance Sheet'!H5+'Balance Sheet'!H6)=0,0,'P&L'!H16/('Balance Sheet'!H5+'Balance Sheet'!H6)) | I6: =IF(('Balance Sheet'!I5+'Balance Sheet'!I6)=0,0,'P&L'!I16/('Balance Sheet'!I5+'Balance Sheet'!I6)) | ... L6: =IF(('Balance Sheet'!L5+'Balance Sheet'!L6)=0,0,'P&L'!L16/('Balance Sheet'!L5+'Balance Sheet'!L6))
A7: Debt/Equity (x) | B7: =IF('Balance Sheet'!B5=0,0,'Balance Sheet'!B6/'Balance Sheet'!B5) | C7: =IF('Balance Sheet'!C5=0,0,'Balance Sheet'!C6/'Balance Sheet'!C5) | D7: =IF('Balance Sheet'!D5=0,0,'Balance Sheet'!D6/'Balance Sheet'!D5) | E7: =IF('Balance Sheet'!E5=0,0,'Balance Sheet'!E6/'Balance Sheet'!E5) | F7: =IF('Balance Sheet'!F5=0,0,'Balance Sheet'!F6/'Balance Sheet'!F5) | G7: =IF('Balance Sheet'!G5=0,0,'Balance Sheet'!G6/'Balance Sheet'!G5) | H7: =IF('Balance Sheet'!H5=0,0,'Balance Sheet'!H6/'Balance Sheet'!H5) | I7: =IF('Balance Sheet'!I5=0,0,'Balance Sheet'!I6/'Balance Sheet'!I5) | ... L7: =IF('Balance Sheet'!L5=0,0,'Balance Sheet'!L6/'Balance Sheet'!L5)
A8: Receivable Days | B8: =IF('P&L'!B3=0,0,'Balance Sheet'!B14/'P&L'!B3*365) | C8: =IF('P&L'!C3=0,0,'Balance Sheet'!C14/'P&L'!C3*365) | D8: =IF('P&L'!D3=0,0,'Balance Sheet'!D14/'P&L'!D3*365) | E8: =IF('P&L'!E3=0,0,'Balance Sheet'!E14/'P&L'!E3*365) | F8: =IF('P&L'!F3=0,0,'Balance Sheet'!F14/'P&L'!F3*365) | G8: =IF('P&L'!G3=0,0,'Balance Sheet'!G14/'P&L'!G3*365) | H8: =IF('P&L'!H3=0,0,'Balance Sheet'!H14/'P&L'!H3*365) | I8: =IF('P&L'!I3=0,0,'Balance Sheet'!I14/'P&L'!I3*365) | ... L8: =IF('P&L'!L3=0,0,'Balance Sheet'!L14/'P&L'!L3*365)
A9: Inventory Days | B9: =IF('P&L'!B4=0,0,'Balance Sheet'!B15/'P&L'!B4*365) | C9: =IF('P&L'!C4=0,0,'Balance Sheet'!C15/'P&L'!C4*365) | D9: =IF('P&L'!D4=0,0,'Balance Sheet'!D15/'P&L'!D4*365) | E9: =IF('P&L'!E4=0,0,'Balance Sheet'!E15/'P&L'!E4*365) | F9: =IF('P&L'!F4=0,0,'Balance Sheet'!F15/'P&L'!F4*365) | G9: =IF('P&L'!G4=0,0,'Balance Sheet'!G15/'P&L'!G4*365) | H9: =IF('P&L'!H4=0,0,'Balance Sheet'!H15/'P&L'!H4*365) | I9: =IF('P&L'!I4=0,0,'Balance Sheet'!I15/'P&L'!I4*365) | ... L9: =IF('P&L'!L4=0,0,'Balance Sheet'!L15/'P&L'!L4*365)
A10: Asset Turnover (x) | B10: =IF('Balance Sheet'!B18=0,0,'P&L'!B3/'Balance Sheet'!B18) | C10: =IF('Balance Sheet'!C18=0,0,'P&L'!C3/'Balance Sheet'!C18) | D10: =IF('Balance Sheet'!D18=0,0,'P&L'!D3/'Balance Sheet'!D18) | E10: =IF('Balance Sheet'!E18=0,0,'P&L'!E3/'Balance Sheet'!E18) | F10: =IF('Balance Sheet'!F18=0,0,'P&L'!F3/'Balance Sheet'!F18) | G10: =IF('Balance Sheet'!G18=0,0,'P&L'!G3/'Balance Sheet'!G18) | H10: =IF('Balance Sheet'!H18=0,0,'P&L'!H3/'Balance Sheet'!H18) | I10: =IF('Balance Sheet'!I18=0,0,'P&L'!I3/'Balance Sheet'!I18) | ... L10: =IF('Balance Sheet'!L18=0,0,'P&L'!L3/'Balance Sheet'!L18)
A11: EPS (₹) | B11: ='P&L'!B20/7.38 | C11: ='P&L'!C20/7.38 | D11: ='P&L'!D20/7.38 | E11: ='P&L'!E20/7.38 | F11: ='P&L'!F20/7.38 | G11: ='P&L'!G20/7.38 | H11: ='P&L'!H20/7.38 | I11: ='P&L'!I20/7.38 | ... L11: ='P&L'!L20/7.38
A12: BVPS (₹) | B12: ='Balance Sheet'!B5/7.38 | C12: ='Balance Sheet'!C5/7.38 | D12: ='Balance Sheet'!D5/7.38 | E12: ='Balance Sheet'!E5/7.38 | F12: ='Balance Sheet'!F5/7.38 | G12: ='Balance Sheet'!G5/7.38 | H12: ='Balance Sheet'!H5/7.38 | I12: ='Balance Sheet'!I5/7.38 | ... L12: ='Balance Sheet'!L5/7.38

Sheet Valuation - Model
A1: VALUATION SUMMARY
A3: DCF Fair Value (₹) | B3: 2125
A4: PE Fair Value (₹) | B4: 2580
A5: EV/EBITDA Fair Value (₹) | B5: 2430
A6: Blended Fair Value (₹) | B6: 2380
A7: CMP (₹) | B7: 1777
A8: Rating | B8: BUY
A9: Target Price (₹) | B9: 2380
A10: Upside % | B10: 33.9
A12: PEER COMPARISON
A13: Company | B13: MCap | C13: PE | D13: EV/EBITDA | E13: Margin | F13: ROE
A14: Pondy Oxides & Chemicals | B14: 890 | C14: 15.8 | D14: 12.2 | E14: 11.5 | F14: 18.2
A15: Exide Industries | B15: 28500 | C15: 28.5 | D15: 16.8 | E15: 8.2 | F15: 14.8
A16: Nile Ltd | B16: 185 | C16: 12.4 | D16: 9.8 | E16: 7.8 | F16: 16.5
A17: Eco Recycling | B17: 125 | C17: 18.6 | D17: 14.2 | E17: 12.8 | F17: 22.1
A20: SENSITIVITY TABLE
A21: PE Multiple \ EPS Growth % | B21: 15 | C21: 20 | D21: 25 | E21: 30 | F21: 35
A22: 24 | B22: 1920 | C22: 2076 | D22: 2232 | E22: 2388 | F22: 2544
A23: 26.5 | B23: 2120 | C23: 2291 | D23: 2462 | E23: 2633 | F23: 2804
A24: 29 | B24: 2320 | C24: 2506 | D24: 2692 | E24: 2878 | F24: 3064
A25: 31.5 | B25: 2520 | C25: 2721 | D25: 2922 | E25: 3123 | F25: 3324
A26: 34 | B26: 2720 | C26: 2936 | D26: 3152 | E26: 3368 | F26: 3584

Sheet KPI Dashboard
A2: Particulars | B2: FY21A | C2: FY22A | D2: FY23A | E2: FY24A | F2: FY25A | G2: FY26A | H2: FY27E | I2: FY28E | J2: FY29E | K2: FY30E | L2: FY31E
A3: Revenue (₹ Cr) | B3: ='P&L'!B3 | C3: ='P&L'!C3 | D3: ='P&L'!D3 | E3: ='P&L'!E3 | F3: ='P&L'!F3 | G3: ='P&L'!G3 | H3: ='P&L'!H3 | I3: ='P&L'!I3 | ... L3: ='P&L'!L3
A4: EBITDA (₹ Cr) | B4: ='P&L'!B12 | C4: ='P&L'!C12 | D4: ='P&L'!D12 | E4: ='P&L'!E12 | F4: ='P&L'!F12 | G4: ='P&L'!G12 | H4: ='P&L'!H12 | I4: ='P&L'!I12 | ... L4: ='P&L'!L12
A5: PAT (₹ Cr) | B5: ='P&L'!B20 | C5: ='P&L'!C20 | D5: ='P&L'!D20 | E5: ='P&L'!E20 | F5: ='P&L'!F20 | G5: ='P&L'!G20 | H5: ='P&L'!H20 | I5: ='P&L'!I20 | ... L5: ='P&L'!L20
A6: EPS (₹) | B6: ='P&L'!B23 | C6: ='P&L'!C23 | D6: ='P&L'!D23 | E6: ='P&L'!E23 | F6: ='P&L'!F23 | G6: ='P&L'!G23 | H6: ='P&L'!H23 | I6: ='P&L'!I23 | ... L6: ='P&L'!L23
A7: EBITDA Margin % | B7: =IF('P&L'!B3=0,0,'P&L'!B12/'P&L'!B3) | C7: =IF('P&L'!C3=0,0,'P&L'!C12/'P&L'!C3) | D7: =IF('P&L'!D3=0,0,'P&L'!D12/'P&L'!D3) | E7: =IF('P&L'!E3=0,0,'P&L'!E12/'P&L'!E3) | F7: =IF('P&L'!F3=0,0,'P&L'!F12/'P&L'!F3) | G7: =IF('P&L'!G3=0,0,'P&L'!G12/'P&L'!G3) | H7: =IF('P&L'!H3=0,0,'P&L'!H12/'P&L'!H3) | I7: =IF('P&L'!I3=0,0,'P&L'!I12/'P&L'!I3) | ... L7: =IF('P&L'!L3=0,0,'P&L'!L12/'P&L'!L3)
A8: ROE % | B8: =IF('Balance Sheet'!B5=0,0,'P&L'!B20/'Balance Sheet'!B5) | C8: =IF('Balance Sheet'!C5=0,0,'P&L'!C20/'Balance Sheet'!C5) | D8: =IF('Balance Sheet'!D5=0,0,'P&L'!D20/'Balance Sheet'!D5) | E8: =IF('Balance Sheet'!E5=0,0,'P&L'!E20/'Balance Sheet'!E5) | F8: =IF('Balance Sheet'!F5=0,0,'P&L'!F20/'Balance Sheet'!F5) | G8: =IF('Balance Sheet'!G5=0,0,'P&L'!G20/'Balance Sheet'!G5) | H8: =IF('Balance Sheet'!H5=0,0,'P&L'!H20/'Balance Sheet'!H5) | I8: =IF('Balance Sheet'!I5=0,0,'P&L'!I20/'Balance Sheet'!I5) | ... L8: =IF('Balance Sheet'!L5=0,0,'P&L'!L20/'Balance Sheet'!L5)
A9: D/E (x) | B9: =IF('Balance Sheet'!B5=0,0,'Balance Sheet'!B6/'Balance Sheet'!B5) | C9: =IF('Balance Sheet'!C5=0,0,'Balance Sheet'!C6/'Balance Sheet'!C5) | D9: =IF('Balance Sheet'!D5=0,0,'Balance Sheet'!D6/'Balance Sheet'!D5) | E9: =IF('Balance Sheet'!E5=0,0,'Balance Sheet'!E6/'Balance Sheet'!E5) | F9: =IF('Balance Sheet'!F5=0,0,'Balance Sheet'!F6/'Balance Sheet'!F5) | G9: =IF('Balance Sheet'!G5=0,0,'Balance Sheet'!G6/'Balance Sheet'!G5) | H9: =IF('Balance Sheet'!H5=0,0,'Balance Sheet'!H6/'Balance Sheet'!H5) | I9: =IF('Balance Sheet'!I5=0,0,'Balance Sheet'!I6/'Balance Sheet'!I5) | ... L9: =IF('Balance Sheet'!L5=0,0,'Balance Sheet'!L6/'Balance Sheet'!L5)

Sheet Fin_Summary
A1: GRAVITA INDIA LTD — Financial Summary Dashboard
A2: Sector: Metal & Metal Products | All figures ₹ Cr unless noted | Source: Screener / Tikona Model
A4: Particulars | B4: FY22A | C4: FY23A | D4: FY24A | E4: FY25A | F4: FY26A | G4: FY27E | H4: FY28E | I4: FY29E | J4: FY30E | K4: FY31E
A5: PROFIT & LOSS
A6: Net Revenue (₹ Cr) | B6: 2215.87 | C6: 2800.6 | D6: 3160.75 | E6: 3868.77 | F6: 4265.27 | G6: 4969.0396 | H6: 6062.2283 | I6: 7183.7405 | J6: 8275.669 | K6: 9334.9547
A7: Revenue Growth % | B7: - | C7: 0.26388281 | D7: 0.12859744 | E7: 0.2240038 | F7: 0.10248735 | G7: 0.165 | H7: 0.22 | I7: 0.185 | J7: 0.152 | K7: 0.128
A8: EBITDA (₹ Cr) | B8: 217.48 | C8: 206.99 | D8: 287.45 | E8: 328.25 | F8: 434.93 | G8: 183.85446 | H8: 272.80027 | I8: 445.39191 | J8: 612.39951 | K8: 784.13619
A9: EBITDA Margin % | B9: 0.098146552 | C9: 0.073909162 | D9: 0.090943605 | E9: 0.084846088 | F9: 0.1019701 | G9: 0.037 | H9: 0.045 | I9: 0.062 | J9: 0.074 | K9: 0.084
A10: Depreciation (₹ Cr) | B10: 20.56 | C10: 23.96 | D10: 37.99 | E10: 29.09 | F10: 38.83 | G10: 58 | H10: 78 | I10: 105 | J10: 128 | K10: 148
A11: EBIT (₹ Cr) | B11: 196.92 | C11: 183.03 | D11: 249.46 | E11: 299.16 | F11: 396.1 | G11: 125.85446 | H11: 194.80027 | I11: 340.39191 | J11: 484.39951 | K11: 636.13619
A12: Interest (₹ Cr) | B12: 37.99 | C12: 43.5 | D12: 51.76 | E12: 46.43 | F12: 24.78 | G12: 32 | H12: 45 | I12: 52 | J12: 58 | K12: 62
A13: PBT (₹ Cr) | B13: 164.64 | C13: 227.59 | D13: 274.15 | E13: 363.46 | F13: 448.25 | G13: 188.85446 | H13: 267.80027 | I13: 430.39191 | J13: 591.39951 | K13: 759.13619
A14: PAT (₹ Cr) | B14: 139.39 | C14: 201.1 | D14: 239.19 | E14: 312.39 | F14: 378.8 | G14: 159.01546 | H14: 224.41663 | I14: 359.37724 | J14: 490.86159 | K14: 626.28736
A15: PAT Margin % | B15: 0.062905315 | C15: 0.071806042 | D15: 0.075675077 | E15: 0.080746594 | F15: 0.088810322 | G15: 0.032001246 | H15: 0.037018835 | I15: 0.050026479 | J15: 0.059313826 | K15: 0.067090562
A16: PAT Growth % | B16: - | C16: 0.44271469 | D16: 0.18940825 | E16: 0.30603286 | F16: 0.21258683 | G16: -0.58021262 | H16: 0.41128812 | I16: 0.60138421 | J16: 0.3658672 | K16: 0.275894
A17: EPS (₹) | B17: 18.887534 | C17: 27.249322 | D17: 32.410569 | E17: 42.329268 | F17: 51.327913 | G17: 21.54681 | H17: 30.408757 | I17: 48.696104 | J17: 66.512411 | K17: 84.862786
A18: DPS (₹) | B18: 2.8075881 | C18: 4.0704607 | D18: 4.8658537 | E18: 6.3495935 | F18: - | G18: 3.2320215 | H18: 4.5613136 | I18: 7.3044155 | J18: 9.9768616 | K18: 12.729418
A19: BALANCE SHEET
A20: Net Worth (₹ Cr) | B20: 386.85 | C20: 588.93 | D20: 837.4 | E20: 2069.91 | F20: 2451.63 | G20: 2873 | H20: 3500 | I20: 4310 | J20: 5202 | K20: 6160
A21: Total Debt (₹ Cr) | B21: 391.52 | C21: 347.72 | D21: 547.59 | E21: 285.95 | F21: 735.9 | G21: 920 | H21: 1285 | I21: 1450 | J21: 1520 | K21: 1580
A22: Capital Employed (₹ Cr) | B22: 778.37 | C22: 936.65 | D22: 1384.99 | E22: 2355.86 | F22: 3187.53 | G22: 3793 | H22: 4785 | I22: 5760 | J22: 6722 | K22: 7740
A23: Net Fixed Assets (₹ Cr) | B23: 191.26 | C23: 273.32 | D23: 348.5 | E23: 435.71 | F23: 939.26 | G23: 1285 | H23: 1840 | I23: 2185 | J23: 2377 | K23: 2509
A24: Working Capital (₹ Cr) | B24: 623.1 | C24: 733.49 | D24: 938.96 | E24: 891.88 | F24: 1454.19 | G24: 1405.2716 | H24: 1616.871 | I24: 1837.2662 | J24: 2028.4232 | K24: 2213.7909
A25: Debt/Equity (x) | B25: 1.0120719 | C25: 0.59042671 | D25: 0.65391689 | E25: 0.1381461 | F25: 0.30016764 | G25: 0.32022276 | H25: 0.36714286 | I25: 0.33642691 | J25: 0.29219531 | K25: 0.25649351
A26: CASH FLOWS
A27: CFO (₹ Cr) | B27: 9.61 | C27: 199.66 | D27: 42.4 | E27: 282.18 | F27: 169.29 | G27: 485 | H27: 625 | I27: 785 | J27: 920 | K27: 1048
A28: Capex (₹ Cr) | B28: 69.45 | C28: 105.35 | D28: 157.81 | E28: 863.63 | F28: 363.89 | G28: 385 | H28: 630 | I28: 450 | J28: 320 | K28: 280
A29: Free Cash Flow (₹ Cr) | B29: -59.84 | C29: 94.31 | D29: -115.41 | E29: -581.45 | F29: -194.6 | G29: 100 | H29: -5 | I29: 335 | J29: 600 | K29: 768
A30: CFO/EBITDA % | B30: 0.044187971 | C30: 0.96458766 | D30: 0.14750391 | E30: 0.85964966 | F30: 0.38923505 | G30: 2.6379561 | H30: 2.2910534 | I30: 1.7624927 | J30: 1.5022873 | K30: 1.3365025
A31: KEY RATIOS
A32: ROE % | B32: 0.373 | C32: 0.352 | D32: 0.289 | E32: 0.151 | F32: 0.156 | G32: 0.055348228 | H32: 0.064119036 | I32: 0.083382191 | J32: 0.094360168 | K32: 0.10167003
A33: ROCE % | B33: 0.285 | C33: 0.248 | D33: 0.221 | E33: 0.198 | F33: 0.212 | G33: 0.033180718 | H33: 0.040710611 | I33: 0.059095818 | J33: 0.072061813 | K33: 0.082188138
A34: Debtor Days | B34: 18 | C34: 18 | D34: 31 | E34: 26 | F34: 37 | G34: 35 | H34: 33 | I34: 32 | J34: 31 | K34: 30
A35: Inventory Days | B35: 104 | C35: 94 | D35: 78 | E35: 58 | F35: 104 | G35: 82 | H35: 78 | I35: 75 | J35: 72 | K35: 70
A36: VALUATIONS (at CMP)
A37: P/E (x) | B37: 94.08322 | C37: 65.212631 | D37: 54.827794 | E37: 41.980409 | F37: 34.620539 | G37: 82.471605 | H37: 58.437114 | I37: 36.491626 | J37: 26.716818 | K37: 20.939685
A38: P/B (x) | B38: 33.900116 | C38: 22.267944 | D38: 15.660688 | E38: 6.3356668 | F38: 5.3492003 | G38: 4.5646572 | H38: 3.7469314 | I38: 3.0427517 | J38: 2.5210035 | K38: 2.1289383
A39: P/S (x) | B39: 5.9183346 | C39: 4.6826609 | D39: 4.1490975 | E39: 3.389775 | F39: 3.0746612 | G39: 2.6391941 | H39: 2.1632739 | I39: 1.8255476 | J39: 1.5846767 | K39: 1.4048552
A40: EV/EBITDA (x) | B40: 63.676246 | C40: 66.90328 | D40: 48.176413 | E40: 42.188302 | F40: 31.840319 | G40: 75.322131 | H40: 50.763549 | I40: 31.092415 | J40: 22.613196 | K40: 17.660593

Sheet Earnings_Forecast
A1: GRAVITA INDIA LTD — Earnings Forecast
A2: Forward-looking income statement | All figures ₹ Cr | Estimate years shaded in cream
A4: Particulars | B4: FY22A | C4: FY23A | D4: FY24A | E4: FY25A | F4: FY26A | G4: FY27E | H4: FY28E | I4: FY29E | J4: FY30E | K4: FY31E
A5: INCOME STATEMENT
A6: Revenue (₹ Cr) | B6: 2215.87 | C6: 2800.6 | D6: 3160.75 | E6: 3868.77 | F6: 4265.27 | G6: 4969.0396 | H6: 6062.2283 | I6: 7183.7405 | J6: 8275.669 | K6: 9334.9547
A7: YoY Growth % | B7: - | C7: 0.26388281 | D7: 0.12859744 | E7: 0.2240038 | F7: 0.10248735 | G7: 0.165 | H7: 0.22 | I7: 0.185 | J7: 0.152 | K7: 0.128
A8: Gross Profit (₹ Cr) | B8: 417.75 | C8: 484.41 | D8: 588.46 | E8: 679.04 | F8: 673.4 | G8: 834.79864 | H8: 1060.8899 | I8: 1307.4408 | J8: 1555.8258 | K8: 1792.3113
A9: Gross Margin % | B9: 0.1885264 | C9: 0.17296651 | D9: 0.18617733 | E9: 0.17551832 | F9: 0.15787981 | G9: 0.168 | H9: 0.175 | I9: 0.182 | J9: 0.188 | K9: 0.192
A10: EBITDA (₹ Cr) | B10: 217.48 | C10: 206.99 | D10: 287.45 | E10: 328.25 | F10: 434.93 | G10: 183.85446 | H10: 272.80027 | I10: 445.39191 | J10: 612.39951 | K10: 784.13619
A11: EBITDA Margin % | B11: 0.098146552 | C11: 0.073909162 | D11: 0.090943605 | E11: 0.084846088 | F11: 0.1019701 | G11: 0.037 | H11: 0.045 | I11: 0.062 | J11: 0.074 | K11: 0.084
A12: EBITDA Growth % | B12: - | C12: -0.04823432 | D12: 0.38871443 | E12: 0.14193773 | F12: 0.32499619 | G12: -0.57727804 | H12: 0.48378378 | I12: 0.63266667 | J12: 0.37496774 | K12: 0.28043243
A13: Depreciation (₹ Cr) | B13: 20.56 | C13: 23.96 | D13: 37.99 | E13: 29.09 | F13: 38.83 | G13: 58 | H13: 78 | I13: 105 | J13: 128 | K13: 148
A14: EBIT (₹ Cr) | B14: 196.92 | C14: 183.03 | D14: 249.46 | E14: 299.16 | F14: 396.1 | G14: 125.85446 | H14: 194.80027 | I14: 340.39191 | J14: 484.39951 | K14: 636.13619
A15: Finance Costs (₹ Cr) | B15: 37.99 | C15: 43.5 | D15: 51.76 | E15: 46.43 | F15: 24.78 | G15: 32 | H15: 45 | I15: 52 | J15: 58 | K15: 62
A16: Other Income (₹ Cr) | B16: 5.71 | C16: 88.06 | D16: 76.45 | E16: 110.73 | F16: 76.93 | G16: 95 | H16: 118 | I16: 142 | J16: 165 | K16: 185
A17: PBT (₹ Cr) | B17: 164.64 | C17: 227.59 | D17: 274.15 | E17: 363.46 | F17: 448.25 | G17: 188.85446 | H17: 267.80027 | I17: 430.39191 | J17: 591.39951 | K17: 759.13619
A18: Tax (₹ Cr) | B18: 16.19 | C18: 23.5 | D18: 31.87 | E18: 50.56 | F18: 69.92 | G18: 29.839005 | H18: 43.383644 | I18: 71.014665 | J18: 100.53792 | K18: 132.84883
A19: Effective Tax Rate % | B19: 0.098335763 | C19: 0.10325585 | D19: 0.11625023 | E19: 0.13910747 | F19: 0.15598438 | G19: 0.158 | H19: 0.162 | I19: 0.165 | J19: 0.17 | K19: 0.175
A20: PAT (₹ Cr) | B20: 139.39 | C20: 201.1 | D20: 239.19 | E20: 312.39 | F20: 378.8 | G20: 159.01546 | H20: 224.41663 | I20: 359.37724 | J20: 490.86159 | K20: 626.28736
A21: PAT Growth % | B21: - | C21: 0.44271469 | D21: 0.18940825 | E21: 0.30603286 | F21: 0.21258683 | G21: -0.58021262 | H21: 0.41128812 | I21: 0.60138421 | J21: 0.3658672 | K21: 0.275894
A22: PAT Margin % | B22: 0.062905315 | C22: 0.071806042 | D22: 0.075675077 | E22: 0.080746594 | F22: 0.088810322 | G22: 0.032001246 | H22: 0.037018835 | I22: 0.050026479 | J22: 0.059313826 | K22: 0.067090562
A23: PER SHARE DATA
A24: EPS (₹) | B24: 18.887534 | C24: 27.249322 | D24: 32.410569 | E24: 42.329268 | F24: 51.327913 | G24: 21.54681 | H24: 30.408757 | I24: 48.696104 | J24: 66.512411 | K24: 84.862786
A25: EPS Growth % | B25: - | C25: 0.44271469 | D25: 0.18940825 | E25: 0.30603286 | F25: 0.21258683 | G25: -0.58021262 | H25: 0.41128812 | I25: 0.60138421 | J25: 0.3658672 | K25: 0.275894
A26: DPS (₹) | B26: 2.8331301 | C26: 4.0873984 | D26: 4.8615854 | E26: 6.3493902 | F26: 7.699187 | G26: 3.2320215 | H26: 4.5613136 | I26: 7.3044155 | J26: 9.9768616 | K26: 12.729418
A27: Book Value per Share (₹) | B27: 52.418699 | C27: 79.800813 | D27: 113.46883 | E27: 280.47561 | F27: 332.19919 | G27: 389.29539 | H27: 474.25474 | I27: 584.01084 | J27: 704.87805 | K27: 834.68835
A28: ASSUMPTIONS & DRIVERS
A29: Volume Growth % (est) | B29: - | C29: - | D29: - | E29: - | F29: - | G29: 0.099 | H29: 0.132 | I29: 0.111 | J29: 0.0912 | K29: 0.0768
A30: Realization Growth % (est) | B30: - | C30: - | D30: - | E30: - | F30: - | G30: 0.066 | H30: 0.088 | I30: 0.074 | J30: 0.0608 | K30: 0.0512
A31: Revenue Growth % | B31: - | C31: - | D31: - | E31: - | F31: - | G31: 0.165 | H31: 0.22 | I31: 0.185 | J31: 0.152 | K31: 0.128
A32: EBITDA Margin % | B32: 0.098146552 | C32: 0.073909162 | D32: 0.090943605 | E32: 0.084846088 | F32: 0.1019701 | G32: 0.037 | H32: 0.045 | I32: 0.062 | J32: 0.074 | K32: 0.084
A33: Capex (₹ Cr) | B33: - | C33: - | D33: - | E33: - | F33: - | G33: 385 | H33: 630 | I33: 450 | J33: 320 | K33: 280
A34: Working Capital Days | B34: - | C34: - | D34: - | E34: - | F34: - | G34: 117 | H34: 111 | I34: 107 | J34: 103 | K34: 100

Sheet Financials_Table
A1: GRAVITA INDIA LTD — Standardised Financial Statements
A2: Cells link directly to P&L / Balance Sheet / Cash Flow sheets (fully dynamic)
A4: Particulars | B4: FY21A | C4: FY22A | D4: FY23A | E4: FY24A | F4: FY25A | G4: FY26A | H4: FY27E | I4: FY28E | J4: FY29E | K4: FY30E | L4: FY31E
A5: PROFIT & LOSS
A6: Revenue | B6: ='P&L'!B3 | C6: ='P&L'!C3 | D6: ='P&L'!D3 | E6: ='P&L'!E3 | F6: ='P&L'!F3 | G6: ='P&L'!G3 | H6: ='P&L'!H3 | I6: ='P&L'!I3 | ... L6: ='P&L'!L3
A7: Raw Material Cost | B7: ='P&L'!B4 | C7: ='P&L'!C4 | D7: ='P&L'!D4 | E7: ='P&L'!E4 | F7: ='P&L'!F4 | G7: ='P&L'!G4 | H7: ='P&L'!H4 | I7: ='P&L'!I4 | ... L7: ='P&L'!L4
A8: Employee Cost | B8: ='P&L'!B6 | C8: ='P&L'!C6 | D8: ='P&L'!D6 | E8: ='P&L'!E6 | F8: ='P&L'!F6 | G8: ='P&L'!G6 | H8: ='P&L'!H6 | I8: ='P&L'!I6 | ... L8: ='P&L'!L6
A9: Other Operating Expenses | B9: ='P&L'!B5+'P&L'!B7+'P&L'!B8+'P&L'!B9+'P&L'!B10 | C9: ='P&L'!C5+'P&L'!C7+'P&L'!C8+'P&L'!C9+'P&L'!C10 | D9: ='P&L'!D5+'P&L'!D7+'P&L'!D8+'P&L'!D9+'P&L'!D10 | E9: ='P&L'!E5+'P&L'!E7+'P&L'!E8+'P&L'!E9+'P&L'!E10 | F9: ='P&L'!F5+'P&L'!F7+'P&L'!F8+'P&L'!F9+'P&L'!F10 | G9: ='P&L'!G5+'P&L'!G7+'P&L'!G8+'P&L'!G9+'P&L'!G10 | H9: ='P&L'!H5+'P&L'!H7+'P&L'!H8+'P&L'!H9+'P&L'!H10 | I9: ='P&L'!I5+'P&L'!I7+'P&L'!I8+'P&L'!I9+'P&L'!I10 | ... L9: ='P&L'!L5+'P&L'!L7+'P&L'!L8+'P&L'!L9+'P&L'!L10
A10: EBITDA | B10: ='P&L'!B12 | C10: ='P&L'!C12 | D10: ='P&L'!D12 | E10: ='P&L'!E12 | F10: ='P&L'!F12 | G10: ='P&L'!G12 | H10: ='P&L'!H12 | I10: ='P&L'!I12 | ... L10: ='P&L'!L12
A11: EBITDA Margin % | B11: =IF('P&L'!B3=0,0,'P&L'!B12/'P&L'!B3) | C11: =IF('P&L'!C3=0,0,'P&L'!C12/'P&L'!C3) | D11: =IF('P&L'!D3=0,0,'P&L'!D12/'P&L'!D3) | E11: =IF('P&L'!E3=0,0,'P&L'!E12/'P&L'!E3) | F11: =IF('P&L'!F3=0,0,'P&L'!F12/'P&L'!F3) | G11: =IF('P&L'!G3=0,0,'P&L'!G12/'P&L'!G3) | H11: =IF('P&L'!H3=0,0,'P&L'!H12/'P&L'!H3) | I11: =IF('P&L'!I3=0,0,'P&L'!I12/'P&L'!I3) | ... L11: =IF('P&L'!L3=0,0,'P&L'!L12/'P&L'!L3)
A12: Depreciation | B12: ='P&L'!B15 | C12: ='P&L'!C15 | D12: ='P&L'!D15 | E12: ='P&L'!E15 | F12: ='P&L'!F15 | G12: ='P&L'!G15 | H12: ='P&L'!H15 | I12: ='P&L'!I15 | ... L12: ='P&L'!L15
A13: EBIT | B13: ='P&L'!B16 | C13: ='P&L'!C16 | D13: ='P&L'!D16 | E13: ='P&L'!E16 | F13: ='P&L'!F16 | G13: ='P&L'!G16 | H13: ='P&L'!H16 | I13: ='P&L'!I16 | ... L13: ='P&L'!L16
A14: Interest | B14: ='P&L'!B17 | C14: ='P&L'!C17 | D14: ='P&L'!D17 | E14: ='P&L'!E17 | F14: ='P&L'!F17 | G14: ='P&L'!G17 | H14: ='P&L'!H17 | I14: ='P&L'!I17 | ... L14: ='P&L'!L17
A15: Other Income | B15: ='P&L'!B14 | C15: ='P&L'!C14 | D15: ='P&L'!D14 | E15: ='P&L'!E14 | F15: ='P&L'!F14 | G15: ='P&L'!G14 | H15: ='P&L'!H14 | I15: ='P&L'!I14 | ... L15: ='P&L'!L14
A16: PBT | B16: ='P&L'!B18 | C16: ='P&L'!C18 | D16: ='P&L'!D18 | E16: ='P&L'!E18 | F16: ='P&L'!F18 | G16: ='P&L'!G18 | H16: ='P&L'!H18 | I16: ='P&L'!I18 | ... L16: ='P&L'!L18
A17: Tax | B17: ='P&L'!B19 | C17: ='P&L'!C19 | D17: ='P&L'!D19 | E17: ='P&L'!E19 | F17: ='P&L'!F19 | G17: ='P&L'!G19 | H17: ='P&L'!H19 | I17: ='P&L'!I19 | ... L17: ='P&L'!L19
A18: PAT | B18: ='P&L'!B20 | C18: ='P&L'!C20 | D18: ='P&L'!D20 | E18: ='P&L'!E20 | F18: ='P&L'!F20 | G18: ='P&L'!G20 | H18: ='P&L'!H20 | I18: ='P&L'!I20 | ... L18: ='P&L'!L20
A19: EPS (₹) | B19: ='P&L'!B20/7.3800 | C19: ='P&L'!C20/7.3800 | D19: ='P&L'!D20/7.3800 | E19: ='P&L'!E20/7.3800 | F19: ='P&L'!F20/7.3800 | G19: ='P&L'!G20/7.3800 | H19: ='P&L'!H20/7.3800 | I19: ='P&L'!I20/7.3800 | ... L19: ='P&L'!L20/7.3800
A20: BALANCE SHEET
A21: Equity Capital | B21: ='Balance Sheet'!B3 | C21: ='Balance Sheet'!C3 | D21: ='Balance Sheet'!D3 | E21: ='Balance Sheet'!E3 | F21: ='Balance Sheet'!F3 | G21: ='Balance Sheet'!G3 | H21: ='Balance Sheet'!H3 | I21: ='Balance Sheet'!I3 | ... L21: ='Balance Sheet'!L3
A22: Reserves & Surplus | B22: ='Balance Sheet'!B4 | C22: ='Balance Sheet'!C4 | D22: ='Balance Sheet'!D4 | E22: ='Balance Sheet'!E4 | F22: ='Balance Sheet'!F4 | G22: ='Balance Sheet'!G4 | H22: ='Balance Sheet'!H4 | I22: ='Balance Sheet'!I4 | ... L22: ='Balance Sheet'!L4
A23: Net Worth | B23: ='Balance Sheet'!B5 | C23: ='Balance Sheet'!C5 | D23: ='Balance Sheet'!D5 | E23: ='Balance Sheet'!E5 | F23: ='Balance Sheet'!F5 | G23: ='Balance Sheet'!G5 | H23: ='Balance Sheet'!H5 | I23: ='Balance Sheet'!I5 | ... L23: ='Balance Sheet'!L5
A24: Total Debt | B24: ='Balance Sheet'!B6 | C24: ='Balance Sheet'!C6 | D24: ='Balance Sheet'!D6 | E24: ='Balance Sheet'!E6 | F24: ='Balance Sheet'!F6 | G24: ='Balance Sheet'!G6 | H24: ='Balance Sheet'!H6 | I24: ='Balance Sheet'!I6 | ... L24: ='Balance Sheet'!L6
A25: Other Liabilities | B25: ='Balance Sheet'!B7 | C25: ='Balance Sheet'!C7 | D25: ='Balance Sheet'!D7 | E25: ='Balance Sheet'!E7 | F25: ='Balance Sheet'!F7 | G25: ='Balance Sheet'!G7 | H25: ='Balance Sheet'!H7 | I25: ='Balance Sheet'!I7 | ... L25: ='Balance Sheet'!L7
A26: Total Liabilities & Equity | B26: ='Balance Sheet'!B8 | C26: ='Balance Sheet'!C8 | D26: ='Balance Sheet'!D8 | E26: ='Balance Sheet'!E8 | F26: ='Balance Sheet'!F8 | G26: ='Balance Sheet'!G8 | H26: ='Balance Sheet'!H8 | I26: ='Balance Sheet'!I8 | ... L26: ='Balance Sheet'!L8
A27: Working Capital | B27: ='Balance Sheet'!B14+'Balance Sheet'!B15 | C27: ='Balance Sheet'!C14+'Balance Sheet'!C15 | D27: ='Balance Sheet'!D14+'Balance Sheet'!D15 | E27: ='Balance Sheet'!E14+'Balance Sheet'!E15 | F27: ='Balance Sheet'!F14+'Balance Sheet'!F15 | G27: ='Balance Sheet'!G14+'Balance Sheet'!G15 | H27: ='Balance Sheet'!H14+'Balance Sheet'!H15 | I27: ='Balance Sheet'!I14+'Balance Sheet'!I15 | ... L27: ='Balance Sheet'!L14+'Balance Sheet'!L15
A28: Total Assets | B28: ='Balance Sheet'!B18 | C28: ='Balance Sheet'!C18 | D28: ='Balance Sheet'!D18 | E28: ='Balance Sheet'!E18 | F28: ='Balance Sheet'!F18 | G28: ='Balance Sheet'!G18 | H28: ='Balance Sheet'!H18 | I28: ='Balance Sheet'!I18 | ... L28: ='Balance Sheet'!L18
A29: CASH FLOW
A30: CFO | B30: ='Cash Flow'!B3 | C30: ='Cash Flow'!C3 | D30: ='Cash Flow'!D3 | E30: ='Cash Flow'!E3 | F30: ='Cash Flow'!F3 | G30: ='Cash Flow'!G3 | H30: ='Cash Flow'!H3 | I30: ='Cash Flow'!I3 | ... L30: ='Cash Flow'!L3
A31: CFI (Investing) | B31: ='Cash Flow'!B4 | C31: ='Cash Flow'!C4 | D31: ='Cash Flow'!D4 | E31: ='Cash Flow'!E4 | F31: ='Cash Flow'!F4 | G31: ='Cash Flow'!G4 | H31: ='Cash Flow'!H4 | I31: ='Cash Flow'!I4 | ... L31: ='Cash Flow'!L4
A32: CFF (Financing) | B32: ='Cash Flow'!B5 | C32: ='Cash Flow'!C5 | D32: ='Cash Flow'!D5 | E32: ='Cash Flow'!E5 | F32: ='Cash Flow'!F5 | G32: ='Cash Flow'!G5 | H32: ='Cash Flow'!H5 | I32: ='Cash Flow'!I5 | ... L32: ='Cash Flow'!L5
A33: Net Cash Change | B33: ='Cash Flow'!B3+'Cash Flow'!B4+'Cash Flow'!B5 | C33: ='Cash Flow'!C3+'Cash Flow'!C4+'Cash Flow'!C5 | D33: ='Cash Flow'!D3+'Cash Flow'!D4+'Cash Flow'!D5 | E33: ='Cash Flow'!E3+'Cash Flow'!E4+'Cash Flow'!E5 | F33: ='Cash Flow'!F3+'Cash Flow'!F4+'Cash Flow'!F5 | G33: ='Cash Flow'!G3+'Cash Flow'!G4+'Cash Flow'!G5 | H33: ='Cash Flow'!H3+'Cash Flow'!H4+'Cash Flow'!H5 | I33: ='Cash Flow'!I3+'Cash Flow'!I4+'Cash Flow'!I5 | ... L33: ='Cash Flow'!L3+'Cash Flow'!L4+'Cash Flow'!L5
A34: Capex | B34: =-'Cash Flow'!B4 | C34: =-'Cash Flow'!C4 | D34: =-'Cash Flow'!D4 | E34: =-'Cash Flow'!E4 | F34: =-'Cash Flow'!F4 | G34: =-'Cash Flow'!G4 | H34: =-'Cash Flow'!H4 | I34: =-'Cash Flow'!I4 | ... L34: =-'Cash Flow'!L4
A35: Free Cash Flow | B35: ='Cash Flow'!B3+'Cash Flow'!B4 | C35: ='Cash Flow'!C3+'Cash Flow'!C4 | D35: ='Cash Flow'!D3+'Cash Flow'!D4 | E35: ='Cash Flow'!E3+'Cash Flow'!E4 | F35: ='Cash Flow'!F3+'Cash Flow'!F4 | G35: ='Cash Flow'!G3+'Cash Flow'!G4 | H35: ='Cash Flow'!H3+'Cash Flow'!H4 | I35: ='Cash Flow'!I3+'Cash Flow'!I4 | ... L35: ='Cash Flow'!L3+'Cash Flow'!L4
A36: KEY RATIOS
A37: Gross Margin % | B37: =IF('P&L'!B3=0,0,('P&L'!B3-'P&L'!B4)/'P&L'!B3) | C37: =IF('P&L'!C3=0,0,('P&L'!C3-'P&L'!C4)/'P&L'!C3) | D37: =IF('P&L'!D3=0,0,('P&L'!D3-'P&L'!D4)/'P&L'!D3) | E37: =IF('P&L'!E3=0,0,('P&L'!E3-'P&L'!E4)/'P&L'!E3) | F37: =IF('P&L'!F3=0,0,('P&L'!F3-'P&L'!F4)/'P&L'!F3) | G37: =IF('P&L'!G3=0,0,('P&L'!G3-'P&L'!G4)/'P&L'!G3) | H37: =IF('P&L'!H3=0,0,('P&L'!H3-'P&L'!H4)/'P&L'!H3) | I37: =IF('P&L'!I3=0,0,('P&L'!I3-'P&L'!I4)/'P&L'!I3) | ... L37: =IF('P&L'!L3=0,0,('P&L'!L3-'P&L'!L4)/'P&L'!L3)
A38: EBITDA Margin % | B38: =IF('P&L'!B3=0,0,'P&L'!B12/'P&L'!B3) | C38: =IF('P&L'!C3=0,0,'P&L'!C12/'P&L'!C3) | D38: =IF('P&L'!D3=0,0,'P&L'!D12/'P&L'!D3) | E38: =IF('P&L'!E3=0,0,'P&L'!E12/'P&L'!E3) | F38: =IF('P&L'!F3=0,0,'P&L'!F12/'P&L'!F3) | G38: =IF('P&L'!G3=0,0,'P&L'!G12/'P&L'!G3) | H38: =IF('P&L'!H3=0,0,'P&L'!H12/'P&L'!H3) | I38: =IF('P&L'!I3=0,0,'P&L'!I12/'P&L'!I3) | ... L38: =IF('P&L'!L3=0,0,'P&L'!L12/'P&L'!L3)
A39: PAT Margin % | B39: =IF('P&L'!B3=0,0,'P&L'!B20/'P&L'!B3) | C39: =IF('P&L'!C3=0,0,'P&L'!C20/'P&L'!C3) | D39: =IF('P&L'!D3=0,0,'P&L'!D20/'P&L'!D3) | E39: =IF('P&L'!E3=0,0,'P&L'!E20/'P&L'!E3) | F39: =IF('P&L'!F3=0,0,'P&L'!F20/'P&L'!F3) | G39: =IF('P&L'!G3=0,0,'P&L'!G20/'P&L'!G3) | H39: =IF('P&L'!H3=0,0,'P&L'!H20/'P&L'!H3) | I39: =IF('P&L'!I3=0,0,'P&L'!I20/'P&L'!I3) | ... L39: =IF('P&L'!L3=0,0,'P&L'!L20/'P&L'!L3)
A40: ROE % | B40: =IF('Balance Sheet'!B5=0,0,'P&L'!B20/'Balance Sheet'!B5) | C40: =IF('Balance Sheet'!C5=0,0,'P&L'!C20/'Balance Sheet'!C5) | D40: =IF('Balance Sheet'!D5=0,0,'P&L'!D20/'Balance Sheet'!D5) | E40: =IF('Balance Sheet'!E5=0,0,'P&L'!E20/'Balance Sheet'!E5) | F40: =IF('Balance Sheet'!F5=0,0,'P&L'!F20/'Balance Sheet'!F5) | G40: =IF('Balance Sheet'!G5=0,0,'P&L'!G20/'Balance Sheet'!G5) | H40: =IF('Balance Sheet'!H5=0,0,'P&L'!H20/'Balance Sheet'!H5) | I40: =IF('Balance Sheet'!I5=0,0,'P&L'!I20/'Balance Sheet'!I5) | ... L40: =IF('Balance Sheet'!L5=0,0,'P&L'!L20/'Balance Sheet'!L5)
A41: ROCE % | B41: =IF(('Balance Sheet'!B5+'Balance Sheet'!B6)=0,0,'P&L'!B16/('Balance Sheet'!B5+'Balance Sheet'!B6)) | C41: =IF(('Balance Sheet'!C5+'Balance Sheet'!C6)=0,0,'P&L'!C16/('Balance Sheet'!C5+'Balance Sheet'!C6)) | D41: =IF(('Balance Sheet'!D5+'Balance Sheet'!D6)=0,0,'P&L'!D16/('Balance Sheet'!D5+'Balance Sheet'!D6)) | E41: =IF(('Balance Sheet'!E5+'Balance Sheet'!E6)=0,0,'P&L'!E16/('Balance Sheet'!E5+'Balance Sheet'!E6)) | F41: =IF(('Balance Sheet'!F5+'Balance Sheet'!F6)=0,0,'P&L'!F16/('Balance Sheet'!F5+'Balance Sheet'!F6)) | G41: =IF(('Balance Sheet'!G5+'Balance Sheet'!G6)=0,0,'P&L'!G16/('Balance Sheet'!G5+'Balance Sheet'!G6)) | H41: =IF(('Balance Sheet'!H5+'Balance Sheet'!H6)=0,0,'P&L'!H16/('Balance Sheet'!H5+'Balance Sheet'!H6)) | I41: =IF(('Balance Sheet'!I5+'Balance Sheet'!I6)=0,0,'P&L'!I16/('Balance Sheet'!I5+'Balance Sheet'!I6)) | ... L41: =IF(('Balance Sheet'!L5+'Balance Sheet'!L6)=0,0,'P&L'!L16/('Balance Sheet'!L5+'Balance Sheet'!L6))
A42: Debt-Equity (x) | B42: =IF('Balance Sheet'!B5=0,0,'Balance Sheet'!B6/'Balance Sheet'!B5) | C42: =IF('Balance Sheet'!C5=0,0,'Balance Sheet'!C6/'Balance Sheet'!C5) | D42: =IF('Balance Sheet'!D5=0,0,'Balance Sheet'!D6/'Balance Sheet'!D5) | E42: =IF('Balance Sheet'!E5=0,0,'Balance Sheet'!E6/'Balance Sheet'!E5) | F42: =IF('Balance Sheet'!F5=0,0,'Balance Sheet'!F6/'Balance Sheet'!F5) | G42: =IF('Balance Sheet'!G5=0,0,'Balance Sheet'!G6/'Balance Sheet'!G5) | H42: =IF('Balance Sheet'!H5=0,0,'Balance Sheet'!H6/'Balance Sheet'!H5) | I42: =IF('Balance Sheet'!I5=0,0,'Balance Sheet'!I6/'Balance Sheet'!I5) | ... L42: =IF('Balance Sheet'!L5=0,0,'Balance Sheet'!L6/'Balance Sheet'!L5)
A43: Interest Coverage (x) | B43: =IF('P&L'!B17=0,0,'P&L'!B16/'P&L'!B17) | C43: =IF('P&L'!C17=0,0,'P&L'!C16/'P&L'!C17) | D43: =IF('P&L'!D17=0,0,'P&L'!D16/'P&L'!D17) | E43: =IF('P&L'!E17=0,0,'P&L'!E16/'P&L'!E17) | F43: =IF('P&L'!F17=0,0,'P&L'!F16/'P&L'!F17) | G43: =IF('P&L'!G17=0,0,'P&L'!G16/'P&L'!G17) | H43: =IF('P&L'!H17=0,0,'P&L'!H16/'P&L'!H17) | I43: =IF('P&L'!I17=0,0,'P&L'!I16/'P&L'!I17) | ... L43: =IF('P&L'!L17=0,0,'P&L'!L16/'P&L'!L17)
A44: Asset Turnover (x) | B44: =IF('Balance Sheet'!B18=0,0,'P&L'!B3/'Balance Sheet'!B18) | C44: =IF('Balance Sheet'!C18=0,0,'P&L'!C3/'Balance Sheet'!C18) | D44: =IF('Balance Sheet'!D18=0,0,'P&L'!D3/'Balance Sheet'!D18) | E44: =IF('Balance Sheet'!E18=0,0,'P&L'!E3/'Balance Sheet'!E18) | F44: =IF('Balance Sheet'!F18=0,0,'P&L'!F3/'Balance Sheet'!F18) | G44: =IF('Balance Sheet'!G18=0,0,'P&L'!G3/'Balance Sheet'!G18) | H44: =IF('Balance Sheet'!H18=0,0,'P&L'!H3/'Balance Sheet'!H18) | I44: =IF('Balance Sheet'!I18=0,0,'P&L'!I3/'Balance Sheet'!I18) | ... L44: =IF('Balance Sheet'!L18=0,0,'P&L'!L3/'Balance Sheet'!L18)
A45: Debtor Days | B45: =IF('P&L'!B3=0,0,'Balance Sheet'!B14/'P&L'!B3*365) | C45: =IF('P&L'!C3=0,0,'Balance Sheet'!C14/'P&L'!C3*365) | D45: =IF('P&L'!D3=0,0,'Balance Sheet'!D14/'P&L'!D3*365) | E45: =IF('P&L'!E3=0,0,'Balance Sheet'!E14/'P&L'!E3*365) | F45: =IF('P&L'!F3=0,0,'Balance Sheet'!F14/'P&L'!F3*365) | G45: =IF('P&L'!G3=0,0,'Balance Sheet'!G14/'P&L'!G3*365) | H45: =IF('P&L'!H3=0,0,'Balance Sheet'!H14/'P&L'!H3*365) | I45: =IF('P&L'!I3=0,0,'Balance Sheet'!I14/'P&L'!I3*365) | ... L45: =IF('P&L'!L3=0,0,'Balance Sheet'!L14/'P&L'!L3*365)
A46: Inventory Days | B46: =IF('P&L'!B4=0,0,'Balance Sheet'!B15/'P&L'!B4*365) | C46: =IF('P&L'!C4=0,0,'Balance Sheet'!C15/'P&L'!C4*365) | D46: =IF('P&L'!D4=0,0,'Balance Sheet'!D15/'P&L'!D4*365) | E46: =IF('P&L'!E4=0,0,'Balance Sheet'!E15/'P&L'!E4*365) | F46: =IF('P&L'!F4=0,0,'Balance Sheet'!F15/'P&L'!F4*365) | G46: =IF('P&L'!G4=0,0,'Balance Sheet'!G15/'P&L'!G4*365) | H46: =IF('P&L'!H4=0,0,'Balance Sheet'!H15/'P&L'!H4*365) | I46: =IF('P&L'!I4=0,0,'Balance Sheet'!I15/'P&L'!I4*365) | ... L46: =IF('P&L'!L4=0,0,'Balance Sheet'!L15/'P&L'!L4*365)
A47: CFO/EBITDA % | B47: =IF('P&L'!B12=0,0,'Cash Flow'!B3/'P&L'!B12) | C47: =IF('P&L'!C12=0,0,'Cash Flow'!C3/'P&L'!C12) | D47: =IF('P&L'!D12=0,0,'Cash Flow'!D3/'P&L'!D12) | E47: =IF('P&L'!E12=0,0,'Cash Flow'!E3/'P&L'!E12) | F47: =IF('P&L'!F12=0,0,'Cash Flow'!F3/'P&L'!F12) | G47: =IF('P&L'!G12=0,0,'Cash Flow'!G3/'P&L'!G12) | H47: =IF('P&L'!H12=0,0,'Cash Flow'!H3/'P&L'!H12) | I47: =IF('P&L'!I12=0,0,'Cash Flow'!I3/'P&L'!I12) | ... L47: =IF('P&L'!L12=0,0,'Cash Flow'!L3/'P&L'!L12)

Sheet Valuations_Table
A1: GRAVITA INDIA LTD — Valuation Matrix
A2: CMP: ₹1,777 | Target: ₹2,380 | Rating: BUY | All multiples at CMP
A4: Particulars | B4: FY22A | C4: FY23A | D4: FY24A | E4: FY25A | F4: FY26A | G4: FY27E | H4: FY28E | I4: FY29E | J4: FY30E | K4: FY31E
A5: MARKET DATA
A6: CMP (₹) | B6: 1777 | C6: 1777 | D6: 1777 | E6: 1777 | F6: 1777 | G6: 1777 | H6: 1777 | I6: 1777 | J6: 1777 | K6: 1777
A7: Market Cap (₹ Cr) | B7: 13114.26 | C7: 13114.26 | D7: 13114.26 | E7: 13114.26 | F7: 13114.26 | G7: 13114.26 | H7: 13114.26 | I7: 13114.26 | J7: 13114.26 | K7: 13114.26
A8: Enterprise Value (₹ Cr) | B8: 13505.78 | C8: 13461.98 | D8: 13661.85 | E8: 13400.21 | F8: 13850.16 | G8: 14034.26 | H8: 14399.26 | I8: 14564.26 | J8: 14634.26 | K8: 14694.26
A9: EARNINGS MULTIPLES
A10: P/E (x) | B10: 94.08322 | C10: 65.212631 | D10: 54.827794 | E10: 41.980409 | F10: 34.620539 | G10: 82.471605 | H10: 58.437114 | I10: 36.491626 | J10: 26.716818 | K10: 20.939685
A11: P/B (x) | B11: 33.900116 | C11: 22.267944 | D11: 15.660688 | E11: 6.3356668 | F11: 5.3492003 | G11: 4.5646572 | H11: 3.7469314 | I11: 3.0427517 | J11: 2.5210035 | K11: 2.1289383
A12: P/Sales (x) | B12: 5.9183346 | C12: 4.6826609 | D12: 4.1490975 | E12: 3.389775 | F12: 3.0746612 | G12: 2.6391941 | H12: 2.1632739 | I12: 1.8255476 | J12: 1.5846767 | K12: 1.4048552
A13: EV/EBITDA (x) | B13: 62.101251 | C13: 65.036862 | D13: 47.527744 | E13: 40.823184 | F13: 31.844573 | G13: 76.333529 | H13: 52.783159 | I13: 32.699876 | J13: 23.89659 | K13: 18.739423
A14: EV/Sales (x) | B14: 6.0950236 | C14: 4.80682 | D14: 4.3223444 | E14: 3.4636874 | F14: 3.2471942 | G14: 2.8243406 | H14: 2.3752421 | I14: 2.0273923 | J14: 1.7683477 | K14: 1.5741116
A15: EV/EBIT (x) | B15: 68.585111 | C15: 73.550675 | D15: 54.765694 | E15: 44.792786 | F15: 34.966322 | G15: 111.51182 | H15: 73.91807 | I15: 42.78674 | J15: 30.211137 | K15: 23.099236
A16: PER SHARE
A17: EPS (₹) | B17: 18.887534 | C17: 27.249322 | D17: 32.410569 | E17: 42.329268 | F17: 51.327913 | G17: 21.54681 | H17: 30.408757 | I17: 48.696104 | J17: 66.512411 | K17: 84.862786
A18: Book Value (₹) | B18: 52.418699 | C18: 79.800813 | D18: 113.46883 | E18: 280.47561 | F18: 332.19919 | G18: 389.29539 | H18: 474.25474 | I18: 584.01084 | J18: 704.87805 | K18: 834.68835
A19: Sales/Share (₹) | B19: 300.25339 | C19: 379.48509 | D19: 428.28591 | E19: 524.22358 | F19: 577.94986 | G19: 673.31159 | H19: 821.44014 | I19: 973.40657 | J19: 1121.3644 | K19: 1264.899
A20: CFO/Share (₹) | B20: 1.302168 | C20: 27.054201 | D20: 5.7452575 | E20: 38.235772 | F20: 22.939024 | G20: 65.718157 | H20: 84.688347 | I20: 106.36856 | J20: 124.66125 | K20: 142.00542
A21: DPS (₹) | B21: 2.8331301 | C21: 4.0873984 | D21: 4.8615854 | E21: 6.3493902 | F21: 7.699187 | G21: 3.2320215 | H21: 4.5613136 | I21: 7.3044155 | J21: 9.9768616 | K21: 12.729418
A22: RETURN METRICS
A23: ROE % | B23: 0.36032054 | C23: 0.34146673 | D23: 0.28563411 | E23: 0.15091961 | F23: 0.15450945 | G23: 0.055348228 | H23: 0.064119036 | I23: 0.083382191 | J23: 0.094360168 | K23: 0.10167003
A24: ROCE % | B24: 0.25299022 | C24: 0.19540917 | D24: 0.18011682 | E24: 0.12698547 | F24: 0.1242655 | G24: 0.033180718 | H24: 0.040710611 | I24: 0.059095818 | J24: 0.072061813 | K24: 0.082188138
A25: Earnings Yield % | B25: 0.010628888 | C25: 0.015334453 | D25: 0.018238925 | E25: 0.023820635 | F25: 0.028884588 | G25: 0.012125386 | H25: 0.017112413 | I25: 0.027403547 | J25: 0.037429607 | K25: 0.04775621
A26: Dividend Yield % | B26: 0.0015943332 | C26: 0.0023001679 | D26: 0.0027358387 | E26: 0.0035730952 | F26: 0.0043326882 | G26: 0.0018188078 | H26: 0.0025668619 | I26: 0.0041105321 | J26: 0.005614441 | K26: 0.0071634315
A27: FCF Yield % | B27: 0.00073279011 | C27: 0.015224649 | D27: 0.0032331218 | E27: 0.021517036 | F27: 0.012908849 | G27: 0.0076252873 | H27: -0.00038126436 | I27: 0.025544712 | J27: 0.045751724 | K27: 0.058562206
A29: DCF ASSUMPTIONS
A30: Risk-Free Rate % | G30: 0.07 | H30: 0.07 | I30: 0.07 | J30: 0.07 | K30: 0.07
A31: Equity Risk Premium % | G31: 0.06 | H31: 0.06 | I31: 0.06 | J31: 0.06 | K31: 0.06
A32: Beta | G32: 1.1 | H32: 1.1 | I32: 1.1 | J32: 1.1 | K32: 1.1
A33: Cost of Equity % | G33: 0.136 | H33: 0.136 | I33: 0.136 | J33: 0.136 | K33: 0.136
A34: WACC % | G34: 0.118 | H34: 0.118 | I34: 0.118 | J34: 0.118 | K34: 0.118
A35: Terminal Growth Rate % | G35: 0.042 | H35: 0.042 | I35: 0.042 | J35: 0.042 | K35: 0.042
A36: Implied DCF Price (₹) | G36: 2125
A37: Upside / (Downside) % | G37: 0.33933596
A39: PE SENSITIVITY (Target Price ₹)
A40: PE Multiple \ EPS Growth % | B40: 15 | C40: 20 | D40: 25 | E40: 30 | F40: 35
A41: 24 | B41: 1920 | C41: 2076 | D41: 2232 | E41: 2388 | F41: 2544
A42: 26.5 | B42: 2120 | C42: 2291 | D42: 2462 | E42: 2633 | F42: 2804
A43: 29 | B43: 2320 | C43: 2506 | D43: 2692 | E43: 2878 | F43: 3064
A44: 31.5 | B44: 2520 | C44: 2721 | D44: 2922 | E44: 3123 | F44: 3324
A45: 34 | B45: 2720 | C45: 2936 | D45: 3152 | E45: 3368 | F45: 3584

Sheet Key_Risks
A1: GRAVITA INDIA LTD — Key Risks Register
A2: Structured risk assessment | Sector: Metal & Metal Products | Source: Tikona Research
A4: # | B4: Risk Category | C4: Risk Factor | D4: Description | E4: Mitigation | F4: Probability | G4: Impact | H4: Overall Rating
A5: 1 | B5: Regulatory | C5: Environmental compliance and licensing delays | D5: Capacity expansion projects dependent on state-level consent-to-operate licenses, with recent delays in Gujarat affecting timeline. | E5: Proactive engagement with regulatory authorities and maintaining buffer timelines for project completion | F5: M | G5: H | H5: MEDIUM
A6: 2 | B6: Market | C6: Commodity price volatility | D6: Aluminum and plastic recycling exposed to price fluctuations due to lack of effective hedging mechanisms unlike lead operations. | E6: Gradual introduction of aluminum hedging on MCX and focus on value-added products with stable margins | F6: H | G6: M | H6: MEDIUM
A7: 3 | B7: Operational | C7: Raw material scrap availability | D7: Dependency on consistent scrap supply from domestic and international sources, with geopolitical tensions affecting import logistics. | E7: Diversified supplier network across 70+ countries and increasing domestic scrap sourcing to 60%+ | F7: M | G7: H | H7: MEDIUM
A8: 4 | B8: Competition | C8: Market share erosion from organized players | D8: Entry of large corporations and battery OEMs into recycling space could intensify competition and margin pressure. | E8: Strong brand relationships with OEMs, technical expertise, and focus on value-added products differentiation | F8: M | G8: M | H8: LOW
A9: 5 | B9: Execution | C9: New vertical scaling challenges | D9: Lithium-ion, rubber, and copper recycling ventures require different technical expertise and market development than core lead business. | E9: Pilot projects, strategic partnerships, and phased capacity additions with continuous monitoring of returns | F9: H | G9: M | H9: MEDIUM
A10: 6 | B10: Financial | C10: High capital expenditure execution risk | D10: Rs 1,225cr capex plan through FY28 requires efficient capital allocation and project management across multiple geographies. | E10: Disciplined ROIC benchmark of 25% for new investments and focus on brownfield expansion to reduce risks | F10: M | G10: H | H10: MEDIUM
A11: 7 | B11: Economic | C11: Global economic slowdown impact | D11: Reduced industrial activity and infrastructure spending could affect demand for recycled metals and scrap availability. | E11: Diversified end-user industries, export market presence, and focus on essential applications like batteries | F11: M | G11: M | H11: LOW
A12: 8 | B12: Technology | C12: Technological obsolescence in recycling processes | D12: Rapid advancement in recycling technologies could make current processes less competitive or require significant upgrades. | E12: Continuous R&D investment, technology partnerships, and regular equipment upgrades to maintain efficiency | F12: L | G12: M | H12: LOW

Sheet Peer_Compare
A1: GRAVITA INDIA LTD — Peer Comparison
A2: Revenue / EBITDA / PAT / Valuation across listed peers | ₹ Cr | Source: Screener / Tikona
A4: REVENUE COMPARISON (₹ Cr)
A5: Company | B5: FY22A | C5: FY23A | D5: FY24A | E5: FY25A | F5: FY26A
A6: GRAVITA INDIA LTD | B6: 2215.87 | C6: 2800.6 | D6: 3160.75 | E6: 3868.77 | F6: 4265.27
A7: Pondy Oxides & Chemicals | B7: 580 | C7: 720 | D7: 890 | E7: 1050 | F7: 1180
A8: Jain Resource Recycling | B8: 320 | C8: 380 | D8: 445 | E8: 520 | F8: 595
A9: Nile Ltd | B9: 145 | C9: 162 | D9: 185 | E9: 208 | F9: 225
A11: EBITDA MARGIN COMPARISON %
A12: Company | B12: FY22A | C12: FY23A | D12: FY24A | E12: FY25A | F12: FY26A
A13: GRAVITA INDIA LTD | B13: 0.098146552 | C13: 0.073909162 | D13: 0.090943605 | E13: 0.084846088 | F13: 0.1019701
A14: Pondy Oxides & Chemicals | B14: 0.095 | C14: 0.108 | D14: 0.115 | E14: 0.118 | F14: 0.122
A15: Jain Resource Recycling | B15: 0.082 | C15: 0.089 | D15: 0.094 | E15: 0.098 | F15: 0.102
A16: Nile Ltd | B16: 0.065 | C16: 0.072 | D16: 0.078 | E16: 0.081 | F16: 0.084
A18: PAT COMPARISON (₹ Cr)
A19: Company | B19: FY22A | C19: FY23A | D19: FY24A | E19: FY25A | F19: FY26A
A20: GRAVITA INDIA LTD | B20: 139.39 | C20: 201.1 | D20: 239.19 | E20: 312.39 | F20: 378.8
A21: Pondy Oxides & Chemicals | B21: 42 | C21: 58 | D21: 72 | E21: 85 | F21: 98
A22: Jain Resource Recycling | B22: 18 | C22: 24 | D22: 29 | E22: 36 | F22: 42
A23: Nile Ltd | B23: 8 | C23: 11 | D23: 14 | E23: 17 | F23: 19
A25: CURRENT VALUATION SNAPSHOT
A26: Company | B26: MCap (₹ Cr) | C26: P/E (x) | D26: P/B (x) | E26: ROCE % | F26: ROE %
A27: GRAVITA INDIA LTD | B27: 13112.41 | C27: 34.620539 | D27: - | E27: 0.212 | F27: 0.156
A28: Pondy Oxides & Chemicals | B28: 890 | C28: 15.8 | D28: 2.1 | E28: 0.168 | F28: 0.182
A29: Jain Resource Recycling | B29: 425 | C29: 18.2 | D29: 1.8 | E29: 0.145 | F29: 0.196
A30: Nile Ltd | B30: 185 | C30: 12.4 | D30: 1.4 | E30: 0.128 | F30: 0.165
A31: Eco Recycling | B31: 125 | C31: 18.6 | D31: 2.3 | E31: 0.182 | F31: 0.221
A70: ChartData: Revenue (last 3 yrs) | B70: FY24 | C70: FY25 | D70: FY26
A71: GRAVITA INDIA LTD | B71: 3160.75 | C71: 3868.77 | D71: 4265.27
A72: Pondy Oxides & Chemicals | B72: 890 | C72: 1050 | D72: 1180
A73: Jain Resource Recycling | B73: 445 | C73: 520 | D73: 595
A74: Nile Ltd | B74: 185 | C74: 208 | D74: 225
A78: ChartData: EBITDA Margin % | B78: FY24 | C78: FY25 | D78: FY26
A79: GRAVITA INDIA LTD | B79: 0.090943605 | C79: 0.084846088 | D79: 0.1019701
A80: Pondy Oxides & Chemicals | B80: 0.115 | C80: 0.118 | D80: 0.122
A81: Jain Resource Recycling | B81: 0.094 | C81: 0.098 | D81: 0.102
A82: Nile Ltd | B82: 0.078 | C82: 0.081 | D82: 0.084

Sheet Operational_Data
A1: GRAVITA INDIA LTD — Operational Metrics
A2: Volume / capacity / productivity | Source: Annual Reports / Company filings via web search
A4: Particulars | B4: FY22A | C4: FY23A | D4: FY24A | E4: FY25A | F4: FY26A | G4: FY27E | H4: FY28E | I4: FY29E
A5: VOLUME DATA (MT)
A6: Lead Recycling (MT) | B6: 88000 | C6: 135000 | D6: 168000 | E6: 195000 | F6: 235000 | G6: 248000 | H6: 295000 | I6: 385000
A7: Aluminum Recycling (MT) | B7: 12500 | C7: 18000 | D7: 22000 | E7: 26500 | F7: 31500 | G7: 29800 | H7: 38000 | I7: 52000
A8: Plastic Recycling (MT) | B8: 8200 | C8: 11500 | D8: 14200 | E8: 16800 | F8: 19500 | G8: 18700 | H8: 24000 | I8: 32000
A9: Total Volume (MT) | B9: 108700 | C9: 164500 | D9: 204200 | E9: 238300 | F9: 286000 | G9: 296500 | H9: 357000 | I9: 469000
A10: CAPACITY & UTILISATION
A11: Capacity Utilisation % | B11: 0.62 | C11: 0.72 | D11: 0.78 | E11: 0.75 | F11: 0.8 | G11: 0.73 | H11: 0.84 | I11: 0.87
A12: Countries of Operation | B12: 18 | C12: 22 | D12: 26 | E12: 28 | F12: 32 | G12: 34 | H12: 38 | I12: 42
A13: Plants India | B13: 4 | C13: 5 | D13: 6 | E13: 7 | F13: 8 | G13: 9 | H13: 10 | I13: 12
A14: Plants Overseas | B14: 3 | C14: 4 | D14: 5 | E14: 6 | F14: 7 | G14: 8 | H14: 9 | I14: 11
A15: REVENUE MIX %
A16: Lead | B16: 0.72 | C16: 0.72 | D16: 0.72 | E16: 0.72 | F16: 0.72 | G16: 0.72 | H16: 0.72 | I16: 0.72
A17: Aluminum | B17: 0.18 | C17: 0.18 | D17: 0.18 | E17: 0.18 | F17: 0.18 | G17: 0.18 | H17: 0.18 | I17: 0.18
A18: Plastic | B18: 0.08 | C18: 0.08 | D18: 0.08 | E18: 0.08 | F18: 0.08 | G18: 0.08 | H18: 0.08 | I18: 0.08
A19: Others | B19: 0.02 | C19: 0.02 | D19: 0.02 | E19: 0.02 | F19: 0.02 | G19: 0.02 | H19: 0.02 | I19: 0.02
A20: GEOGRAPHY MIX %
A21: India | B21: 0.62 | C21: 0.62 | D21: 0.62 | E21: 0.62 | F21: 0.62 | G21: 0.62 | H21: 0.62 | I21: 0.62
A22: Europe | B22: 0.18 | C22: 0.18 | D22: 0.18 | E22: 0.18 | F22: 0.18 | G22: 0.18 | H22: 0.18 | I22: 0.18
A23: Asia Pacific | B23: 0.12 | C23: 0.12 | D23: 0.12 | E23: 0.12 | F23: 0.12 | G23: 0.12 | H23: 0.12 | I23: 0.12
A24: Others | B24: 0.08 | C24: 0.08 | D24: 0.08 | E24: 0.08 | F24: 0.08 | G24: 0.08 | H24: 0.08 | I24: 0.08
A25: FINANCIAL PRODUCTIVITY
A26: Revenue/Employee (₹ Lakh) | B26: 119.77676 | C26: 151.38378 | D26: 170.85135 | E26: 209.1227 | F26: 230.55514 | G26: 268.59673 | H26: 327.68801 | I26: 388.3103
A27: EBITDA/Tonne (₹/MT) | B27: 20007.36 | C27: 12582.979 | D27: 14076.885 | E27: 13774.654 | F27: 15207.343 | G27: 6200.8251 | H27: 7641.4642 | I27: 9496.6292
A28: Revenue/Tonne (₹/MT) | B28: 203851.89 | C28: 170249.24 | D28: 154786.97 | E28: 162348.72 | F28: 149135.31 | G28: 167589.87 | H28: 169810.32 | I28: 153171.44
A29: Capex/Tonne (₹/MT) | B29: 6389.1444 | C29: 6404.2553 | D29: 7728.2076 | E29: 36241.292 | F29: 12723.427 | G29: 12984.823 | H29: 17647.059 | I29: 9594.8827

Sheet Governance
A1: GRAVITA INDIA LTD — Corporate Governance
A2: Board, shareholding, governance metrics | Source: Annual Report / BSE filings
A4: BOARD OF DIRECTORS
A5: Name | B5: Designation | C5: Status | D5: DIN | E5: Since
A6: Mahavir Prasad Agarwal | B6: Chairman & Managing Director | C6: Promoter Executive | D6: 00221469 | E6: 1992
A7: Rajat Agarwal | B7: Managing Director | C7: Promoter Executive | D7: 00920071 | E7: 2001
A8: Yogesh Malhotra | B8: Whole Time Director & CEO | C8: Executive | D8: 07018778 | E8: 2018
A9: Sunil Agarwal | B9: Independent Director | C9: Independent | D9: 00221460 | E9: 2010
A10: Tanvi Agarwal | B10: Executive Director | C10: Promoter Executive | D10: 07664470 | E10: 2020
A11: Deepika Agarwal | B11: Independent Director | C11: Independent | D11: 08764521 | E11: 2019
A13: SHAREHOLDING PATTERN %
A14: Category | B14: FY23 | C14: FY24 | D14: FY25 | E14: FY26
A15: Promoter | B15: 0.729 | C15: 0.681 | D15: 0.618 | E15: 0.559
A16: FII | B16: 0.085 | C16: 0.124 | D16: 0.158 | E16: 0.182
A17: DII | B17: 0.142 | C17: 0.156 | D17: 0.178 | E17: 0.195
A18: Public | B18: 0.044 | C18: 0.039 | D18: 0.046 | E18: 0.064
A20: KEY GOVERNANCE METRICS
A21: Promoter Pledge % | B21: 0 | C21: Source: Annual Report / BSE filings
A22: Board Size | B22: 6 | C22: Source: Annual Report / BSE filings
A23: Independent Directors (count) | B23: 2 | C23: Source: Annual Report / BSE filings
A24: Women Directors | B24: 2 | C24: Source: Annual Report / BSE filings
A25: Managerial Remuneration (₹ Cr) | B25: 18.5 | C25: Source: Annual Report / BSE filings
A26: Auditor Fees – Audit (₹ Cr) | B26: 1.2 | C26: Source: Annual Report / BSE filings
A27: Auditor Fees – Non-Audit (₹ Cr) | B27: 0.3 | C27: Source: Annual Report / BSE filings
A28: Statutory Auditor | B28: Walker Chandiok & Co LLP | C28: Source: Annual Report / BSE filings
A29: Dividend Payout % | B29: 0.15 | C29: Source: Annual Report / BSE filings
A30: Related Party Transactions (₹ Cr) | B30: 45.8 | C30: Source: Annual Report / BSE filings

Sheet Timeline
A1: GRAVITA INDIA LTD — Company Timeline
A2: Key milestones extracted from thesis / catalysts / management commentary
A4: Year | B4: Event Category | C4: Description | D4: Strategic Impact
A5: 1992 | B5: Founding | C5: Company incorporated as Gravita India Limited in Jaipur | D5: Foundation for lead recycling business
A6: 2001 | B6: Expansion | C6: Rajat Agarwal joins as Managing Director, family business expansion | D6: Leadership transition and growth acceleration
A7: 2010 | B7: IPO | C7: Public listing on NSE and BSE | D7: Access to capital markets for expansion funding
A8: 2015 | B8: International Expansion | C8: First overseas recycling facility established | D8: Global footprint development begins
A9: 2019 | B9: Strategy | C9: Hedging strategy extended to core inventory for margin stability | D9: Risk management enhancement and margin protection
A10: 2022 | B10: New Vertical | C10: Entry into aluminum and plastic recycling segments | D10: Diversification beyond lead recycling
A11: 2025 | B11: Milestone | C11: Rs 1,000cr QIP oversubscribed 3.5x, achieving net debt-free status | D11: Strong balance sheet for expansion plans
A12: 2026 | B12: Expansion | C12: RMIL acquisition completed for ₹559cr, entry into copper recycling | D12: Copper vertical addition and manufacturing capacity boost
A13: 2026E | B13: New Vertical | C13: Lithium-ion battery recycling plant commissioning at Mundra | D13: Entry into high-growth EV battery recycling market
A14: 2027E | B14: Expansion | C14: Target capacity expansion to 5.5 lakh MTPA | D14: Significant scale-up in core recycling operations
A15: 2028E | B15: Milestone | C15: Vision 2028 achievement - 7 lakh MTPA capacity, 25%+ ROIC | D15: Capacity doubling with maintained high returns
A16: 2029E | B16: Outlook | C16: Non-lead business contribution target of 30% revenue | D16: Successful diversification into multiple recycling verticals

Sheet Op_Charts
A1: GRAVITA INDIA LTD — Operational Charts
A2: Six analytical charts on historical + projected financials
A60: ChartData 1 — Revenue/EBITDA/PAT | B60: FY22A | C60: FY23A | D60: FY24A | E60: FY25A | F60: FY26A | G60: FY27E | H60: FY28E | I60: FY29E | J60: FY30E | K60: FY31E
A61: Revenue | B61: 2215.87 | C61: 2800.6 | D61: 3160.75 | E61: 3868.77 | F61: 4265.27 | G61: 4969.0396 | H61: 6062.2283 | I61: 7183.7405 | J61: 8275.669 | K61: 9334.9547
A62: EBITDA | B62: 217.48 | C62: 206.99 | D62: 287.45 | E62: 328.25 | F62: 434.93 | G62: 183.85446 | H62: 272.80027 | I62: 445.39191 | J62: 612.39951 | K62: 784.13619
A63: PAT | B63: 139.39 | C63: 201.1 | D63: 239.19 | E63: 312.39 | F63: 378.8 | G63: 159.01546 | H63: 224.41663 | I63: 359.37724 | J63: 490.86159 | K63: 626.28736
A66: ChartData 2 — Margins | B66: FY22A | C66: FY23A | D66: FY24A | E66: FY25A | F66: FY26A | G66: FY27E | H66: FY28E | I66: FY29E | J66: FY30E | K66: FY31E
A67: EBITDA Margin % | B67: 9.8146552 | C67: 7.3909162 | D67: 9.0943605 | E67: 8.4846088 | F67: 10.19701 | G67: 3.7 | H67: 4.5 | I67: 6.2 | J67: 7.4 | K67: 8.4
A68: PAT Margin % | B68: 6.2905315 | C68: 7.1806042 | D68: 7.5675077 | E68: 8.0746594 | F68: 8.8810322 | G68: 3.2001246 | H68: 3.7018835 | I68: 5.0026479 | J68: 5.9313826 | K68: 6.7090562
A71: ChartData 3 — Revenue by Segment | B71: FY22A | C71: FY23A | D71: FY24A | E71: FY25A | F71: FY26A | G71: FY27E | H71: FY28E | I71: FY29E | J71: FY30E | K71: FY31E
A72: Core | B72: 1440.3155 | C72: 1820.39 | D72: 2054.4875 | E72: 2514.7005 | F72: 2772.4255 | G72: 3229.8757 | H72: 3940.4484 | I72: 4669.4313 | J72: 5379.1849 | K72: 6067.7205
A73: Adjacent | B73: 553.9675 | C73: 700.15 | D73: 790.1875 | E73: 967.1925 | F73: 1066.3175 | G73: 1242.2599 | H73: 1515.5571 | I73: 1795.9351 | J73: 2068.9173 | K73: 2333.7387
A74: Others | B74: 221.587 | C74: 280.06 | D74: 316.075 | E74: 386.877 | F74: 426.527 | G74: 496.90396 | H74: 606.22283 | I74: 718.37405 | J74: 827.5669 | K74: 933.49547
A77: ChartData 4 — ROE/ROCE | B77: FY22A | C77: FY23A | D77: FY24A | E77: FY25A | F77: FY26A | G77: FY27E | H77: FY28E | I77: FY29E | J77: FY30E | K77: FY31E
A78: ROE % | B78: 36.032054 | C78: 34.146673 | D78: 28.563411 | E78: 15.091961 | F78: 15.450945 | G78: 5.5348228 | H78: 6.4119036 | I78: 8.3382191 | J78: 9.4360168 | K78: 10.167003
A79: ROCE % | B79: 25.299022 | C79: 19.540917 | D79: 18.011682 | E79: 12.698547 | F79: 12.42655 | G79: 3.3180718 | H79: 4.0710611 | I79: 5.9095818 | J79: 7.2061813 | K79: 8.2188138
A82: ChartData 5 — CFO/Capex/FCF | B82: FY22A | C82: FY23A | D82: FY24A | E82: FY25A | F82: FY26A | G82: FY27E | H82: FY28E | I82: FY29E | J82: FY30E | K82: FY31E
A83: CFO | B83: 9.61 | C83: 199.66 | D83: 42.4 | E83: 282.18 | F83: 169.29 | G83: 485 | H83: 625 | I83: 785 | J83: 920 | K83: 1048
A84: Capex | B84: 69.45 | C84: 105.35 | D84: 157.81 | E84: 863.63 | F84: 363.89 | G84: 385 | H84: 630 | I84: 450 | J84: 320 | K84: 280
A85: FCF | B85: -59.84 | C85: 94.31 | D85: -115.41 | E85: -581.45 | F85: -194.6 | G85: 100 | H85: -5 | I85: 335 | J85: 600 | K85: 768
A88: ChartData 6 — EPS Trend | B88: FY22A | C88: FY23A | D88: FY24A | E88: FY25A | F88: FY26A | G88: FY27E | H88: FY28E | I88: FY29E | J88: FY30E | K88: FY31E
A89: EPS (₹) | B89: 18.887534 | C89: 27.249322 | D89: 32.410569 | E89: 42.329268 | F89: 51.327913 | G89: 21.54681 | H89: 30.408757 | I89: 48.696104 | J89: 66.512411 | K89: 84.862786

Sheet Model Diagnostics
A1: MODEL DIAGNOSTICS
A2: Warnings detected during Python pre-flight checks.
A4: - Cash plug projected NEGATIVE in FY27E (-1704 Cr) — borrowings/reserves likely understated relative to asset base for GRAVITA INDIA LTD
A5: - Cash plug projected NEGATIVE in FY28E (-2332 Cr) — borrowings/reserves likely understated relative to asset base for GRAVITA INDIA LTD
A6: - Cash plug projected NEGATIVE in FY29E (-2822 Cr) — borrowings/reserves likely understated relative to asset base for GRAVITA INDIA LTD
A7: - Cash plug projected NEGATIVE in FY30E (-3045 Cr) — borrowings/reserves likely understated relative to asset base for GRAVITA INDIA LTD
A8: - Cash plug projected NEGATIVE in FY31E (-3046 Cr) — borrowings/reserves likely understated relative to asset base for GRAVITA INDIA LTD
